Workbook

Sheet KSA — Regulator Master
A1: 🇸🇦 KSA GRC REGULATOR MASTER CATALOGUE · Local (60+) + International (15) = 75+ Active Regulators in KSA
A2: LOCAL REGULATORS · Tier 1 (Primary) + Tier 2 (Sector) + Tier 3 (Specialised)
A3: Code | B3: Name (EN) | C3: Name (AR) | D3: Sector Group | E3: Tier | F3: Own Frameworks | G3: Power Index (0-100) | H3: Enforcement | I3: Key Frameworks | J3: Mandatory for | K3: Saudisation? | L3: Website | M3: Sectors Covered | N3: Annual Compliance Cost (Est.) | O3: Notes
A4: NCA | B4: National Cybersecurity Authority | C4: الهيئة الوطنية للأمن السيبراني | D4: Cybersecurity | E4: 🔴 T1 | F4: 7 | G4: 98 | H4: MANDATORY | I4: - | J4: Sector-dependent | K4: Yes (where applicable) | L4: https://nca.gov.sa | M4: - | N4: - | O4: Issues ECC, OTCC, CCC, DCC, CSCC
A5: SDAIA | B5: Saudi Data & AI Authority | C5: هيئة البيانات والذكاء الاصطناعي | D5: Data/AI | E5: 🔴 T1 | F5: 5 | G5: 95 | H5: MANDATORY | I5: - | J5: Sector-dependent | K5: Yes (where applicable) | L5: https://sdaia.gov.sa | M5: - | N5: - | O5: PDPL regulator, AI strategy
A6: SAMA | B6: Saudi Arabian Monetary Authority | C6: البنك المركزي السعودي | D6: Financial | E6: 🔴 T1 | F6: 8 | G6: 98 | H6: MANDATORY | I6: - | J6: Sector-dependent | K6: Yes (where applicable) | L6: https://sama.gov.sa | M6: - | N6: - | O6: Banks, insurance, payments, fintechs
A7: CMA | B7: Capital Market Authority | C7: هيئة السوق المالية | D7: Capital Markets | E7: 🔴 T1 | F7: 5 | G7: 90 | H7: MANDATORY | I7: - | J7: Sector-dependent | K7: Yes (where applicable) | L7: https://cma.org.sa | M7: - | N7: - | O7: Tadawul, listed cos, investment funds
A8: CITC | B8: Communications & IT Commission | C8: هيئة الاتصالات وتقنية المعلومات | D8: ICT/Telecom | E8: 🔴 T1 | F8: 4 | G8: 88 | H8: MANDATORY | I8: - | J8: Sector-dependent | K8: Yes (where applicable) | L8: https://citc.gov.sa | M8: - | N8: - | O8: Telecom licensing, digital services
A9: SFDA | B9: Saudi Food & Drug Authority | C9: الهيئة العامة للغذاء والدواء | D9: Healthcare/Pharma | E9: 🔴 T1 | F9: 6 | G9: 87 | H9: MANDATORY | I9: - | J9: Sector-dependent | K9: Yes (where applicable) | L9: https://sfda.gov.sa | M9: - | N9: - | O9: Medical devices, pharma, food safety
A10: MOH | B10: Ministry of Health | C10: وزارة الصحة | D10: Healthcare | E10: 🔴 T1 | F10: 5 | G10: 85 | H10: MANDATORY | I10: - | J10: Sector-dependent | K10: Yes (where applicable) | L10: https://moh.gov.sa | M10: - | N10: - | O10: Hospital standards, HIS, patient data
A11: ZATCA | B11: Zakat, Tax & Customs Authority | C11: هيئة الزكاة والضريبة والجمارك | D11: Tax/Customs | E11: 🔴 T1 | F11: 4 | G11: 90 | H11: MANDATORY | I11: - | J11: Sector-dependent | K11: Yes (where applicable) | L11: https://zatca.gov.sa | M11: - | N11: - | O11: VAT, e-invoicing (Fatoorah), customs
A12: MHRSD | B12: Ministry of HR & Social Development | C12: وزارة الموارد البشرية والتنمية الاجتماعية | D12: Labour | E12: 🔴 T1 | F12: 3 | G12: 80 | H12: MANDATORY | I12: - | J12: Sector-dependent | K12: Yes (where applicable) | L12: https://mhrsd.gov.sa | M12: - | N12: - | O12: Nitaqat, Saudisation, labour contracts
A13: MOI | B13: Ministry of Interior | C13: وزارة الداخلية | D13: Security/CNI | E13: 🔴 T1 | F13: 2 | G13: 95 | H13: MANDATORY | I13: - | J13: Sector-dependent | K13: Yes (where applicable) | L13: https://moi.gov.sa | M13: - | N13: - | O13: CNI protection, national security
A14: CCHI | B14: Council of Cooperative Health Insurance | C14: مجلس الضمان الصحي التعاوني | D14: Healthcare Insurance | E14: 🟠 T2 | F14: 3 | G14: 82 | H14: MANDATORY | I14: - | J14: Sector-dependent | K14: Yes (where applicable) | L14: https://cchi.gov.sa | M14: - | N14: - | O14: Health insurance mandates
A15: CBAHI | B15: Central Board for Accreditation of HCI | C15: المركز السعودي لاعتماد المنشآت الصحية | D15: Healthcare Accred. | E15: 🟠 T2 | F15: 3 | G15: 78 | H15: MANDATORY | I15: - | J15: Sector-dependent | K15: Yes (where applicable) | L15: https://cbahi.gov.sa | M15: - | N15: - | O15: Hospital accreditation standards
A16: GAHAR | B16: General Authority for Healthcare Accreditation & Research | C16: الهيئة العامة للاعتماد وتقييم المنشآت الصحية | D16: Healthcare | E16: 🟠 T2 | F16: 2 | G16: 75 | H16: MANDATORY | I16: - | J16: Sector-dependent | K16: Yes (where applicable) | L16: https://gahar.gov.sa | M16: - | N16: - | O16: Quality & patient safety
A17: SCA | B17: Saudi Contractors Authority | C17: هيئة المقاولين | D17: Construction | E17: 🟠 T2 | F17: 2 | G17: 55 | H17: MANDATORY | I17: - | J17: Sector-dependent | K17: Yes (where applicable) | M17: - | N17: -
A18: NCSC | B18: National Cybersecurity Committee (Ops) | C18: اللجنة الوطنية للأمن السيبراني | D18: Cybersecurity Ops | E18: 🟠 T2 | F18: 1 | G18: 70 | H18: MANDATORY | I18: - | J18: Sector-dependent | K18: Yes (where applicable) | M18: - | N18: - | O18: Coordinates with NCA
A19: NDMO | B19: National Data Management Office | C19: مكتب إدارة البيانات الوطني | D19: Data Gov. | E19: 🟠 T2 | F19: 2 | G19: 72 | H19: MANDATORY | I19: - | J19: Sector-dependent | K19: Yes (where applicable) | L19: https://ndmo.gov.sa | M19: - | N19: - | O19: Data governance policy (under SDAIA)
A20: MISA | B20: Ministry of Investment | C20: وزارة الاستثمار | D20: Investment | E20: 🟠 T2 | F20: 1 | G20: 65 | H20: MANDATORY | I20: - | J20: Sector-dependent | K20: Yes (where applicable) | L20: https://misa.gov.sa | M20: - | N20: - | O20: Foreign investment, economic zones
A21: DGA | B21: Digital Government Authority | C21: هيئة الحكومة الرقمية | D21: Digital Gov. | E21: 🟠 T2 | F21: 3 | G21: 78 | H21: MANDATORY | I21: - | J21: Sector-dependent | K21: Yes (where applicable) | L21: https://dga.gov.sa | M21: - | N21: - | O21: Gov cloud, digital transformation
A22: MCIT | B22: Ministry of Communications & IT | C22: وزارة الاتصالات وتقنية المعلومات | D22: ICT | E22: 🟠 T2 | F22: 3 | G22: 75 | H22: MANDATORY | I22: - | J22: Sector-dependent | K22: Yes (where applicable) | L22: https://mcit.gov.sa | M22: - | N22: - | O22: Digital economy strategy
A23: MOE_ED | B23: Ministry of Education | C23: وزارة التعليم | D23: Education | E23: 🟠 T2 | F23: 2 | G23: 60 | H23: MANDATORY | I23: - | J23: Sector-dependent | K23: Yes (where applicable) | L23: https://moe.gov.sa | M23: - | N23: - | O23: EdTech, student data protection
A24: MOJ | B24: Ministry of Justice | C24: وزارة العدل | D24: Legal | E24: 🟠 T2 | F24: 2 | G24: 70 | H24: MANDATORY | I24: - | J24: Sector-dependent | K24: Yes (where applicable) | L24: https://moj.gov.sa | M24: - | N24: - | O24: Electronic transactions, Notary
A25: MOF | B25: Ministry of Finance | C25: وزارة المالية | D25: Public Finance | E25: 🟠 T2 | F25: 2 | G25: 75 | H25: MANDATORY | I25: - | J25: Sector-dependent | K25: Yes (where applicable) | L25: https://mof.gov.sa | M25: - | N25: - | O25: Gov procurement, IPSAS
A26: ECRA | B26: Electricity & Cogeneration Regulatory Authority | C26: هيئة تنظيم الكهرباء | D26: Energy | E26: 🟠 T2 | F26: 3 | G26: 72 | H26: MANDATORY | I26: - | J26: Sector-dependent | K26: Yes (where applicable) | L26: https://ecra.gov.sa | M26: - | N26: - | O26: Power grid, renewable energy
A27: NCPD | B27: National Center for Privatization & PPP | C27: المركز الوطني للتخصيص والشراكة | D27: PPP/Privatisation | E27: 🟠 T2 | F27: 1 | G27: 58 | H27: MANDATORY | I27: - | J27: Sector-dependent | K27: Yes (where applicable) | M27: - | N27: -
A28: GAC | B28: General Authority of Customs | C28: الهيئة العامة للجمارك | D28: Customs | E28: 🟠 T2 | F28: 2 | G28: 70 | H28: MANDATORY | I28: - | J28: Sector-dependent | K28: Yes (where applicable) | L28: https://gca.gov.sa | M28: - | N28: - | O28: Trade compliance, AEO
A29: GOSI | B29: General Organisation for Social Insurance | C29: المؤسسة العامة للتأمينات الاجتماعية | D29: Social Insurance | E29: 🟠 T2 | F29: 2 | G29: 68 | H29: MANDATORY | I29: - | J29: Sector-dependent | K29: Yes (where applicable) | L29: https://gosi.gov.sa | M29: - | N29: - | O29: Pension, work injury
A30: ETEC | B30: Education Evaluation & Training Accreditation Commission | C30: المركز الوطني للتقويم والاعتماد الأكاديمي | D30: Education Accred. | E30: 🟠 T2 | F30: 2 | G30: 55 | H30: MANDATORY | I30: - | J30: Sector-dependent | K30: Yes (where applicable) | M30: - | N30: -
A31: SCFHS | B31: Saudi Commission for Health Specialties | C31: الهيئة السعودية للتخصصات الصحية | D31: Health Workforce | E31: 🟠 T2 | F31: 2 | G31: 62 | H31: MANDATORY | I31: - | J31: Sector-dependent | K31: Yes (where applicable) | L31: https://scfhs.org.sa | M31: - | N31: - | O31: Health professional licensing
A32: SCTH | B32: Saudi Commission for Tourism & National Heritage | C32: الهيئة السعودية للسياحة | D32: Tourism | E32: 🟠 T2 | F32: 1 | G32: 45 | H32: MANDATORY | I32: - | J32: Sector-dependent | K32: Yes (where applicable) | M32: - | N32: -
A33: GACA | B33: General Authority of Civil Aviation | C33: الهيئة العامة للطيران المدني | D33: Aviation | E33: 🟠 T2 | F33: 3 | G33: 78 | H33: MANDATORY | I33: - | J33: Sector-dependent | K33: Yes (where applicable) | L33: https://gaca.gov.sa | M33: - | N33: - | O33: ICAO compliance, aviation safety
A34: MAWANI | B34: Saudi Ports Authority | C34: الهيئة العامة للموانئ | D34: Maritime/Ports | E34: 🟠 T2 | F34: 2 | G34: 62 | H34: MANDATORY | I34: - | J34: Sector-dependent | K34: Yes (where applicable) | L34: https://mawani.gov.sa | M34: - | N34: - | O34: Port operations, trade
A35: MOT | B35: Ministry of Transport | C35: وزارة النقل | D35: Transport | E35: 🟠 T2 | F35: 2 | G35: 65 | H35: MANDATORY | I35: - | J35: Sector-dependent | K35: Yes (where applicable) | L35: https://mot.gov.sa | M35: - | N35: - | O35: Road, rail, logistics
A36: WERA | B36: Water & Electricity Regulatory Authority | C36: الهيئة التنظيمية للمياه والكهرباء | D36: Water/Energy | E36: 🟠 T2 | F36: 2 | G36: 65 | H36: MANDATORY | I36: - | J36: Sector-dependent | K36: Yes (where applicable) | L36: https://wera.gov.sa | M36: - | N36: - | O36: Utility regulation
A37: NHC | B37: National Housing Company | C37: الشركة الوطنية للإسكان | D37: Real Estate | E37: 🟠 T2 | F37: 1 | G37: 50 | H37: MANDATORY | I37: - | J37: Sector-dependent | K37: Yes (where applicable) | M37: - | N37: -
A38: MOMRAH | B38: Ministry of Municipal & Rural Affairs & Housing | C38: وزارة الشؤون البلدية والقروية والإسكان | D38: Municipal | E38: 🟠 T2 | F38: 2 | G38: 55 | H38: MANDATORY | I38: - | J38: Sector-dependent | K38: Yes (where applicable) | M38: - | N38: -
A39: GASTAT | B39: General Authority for Statistics | C39: الهيئة العامة للإحصاء | D39: Statistics | E39: 🟠 T2 | F39: 1 | G39: 48 | H39: MANDATORY | I39: - | J39: Sector-dependent | K39: Yes (where applicable) | L39: https://stats.gov.sa | M39: - | N39: - | O39: Data sharing, national statistics
A40: NAZAHA | B40: National Anti-Corruption Commission | C40: هيئة الرقابة ومكافحة الفساد – نزاهة | D40: Anti-Corruption | E40: 🟠 T2 | F40: 2 | G40: 82 | H40: MANDATORY | I40: - | J40: Sector-dependent | K40: Yes (where applicable) | L40: https://nazaha.gov.sa | M40: - | N40: - | O40: Whistleblowing, integrity
A41: NCWCD | B41: National Centre for Wildlife Conservation | C41: المركز الوطني لتنمية الحياة الفطرية | D41: Environment | E41: 🟡 T3 | F41: 1 | G41: 35 | H41: MANDATORY | I41: - | J41: Sector-dependent | K41: Yes (where applicable) | M41: - | N41: -
A42: GCAM | B42: General Commission for Audiovisual Media | C42: هيئة الأفلام | D42: Media | E42: 🟡 T3 | F42: 1 | G42: 42 | H42: MANDATORY | I42: - | J42: Sector-dependent | K42: Yes (where applicable) | M42: - | N42: - | O42: Content regulations
A43: SMEA | B43: Small & Medium Enterprises Authority | C43: هيئة المنشآت الصغيرة والمتوسطة | D43: SME | E43: 🟡 T3 | F43: 1 | G43: 48 | H43: MANDATORY | I43: - | J43: Sector-dependent | K43: Yes (where applicable) | L43: https://monshaat.gov.sa | M43: - | N43: - | O43: SME enabling, simplified compliance
A44: SASO | B44: Saudi Standards, Metrology & Quality Org. | C44: المؤسسة العربية السعودية للمواصفات والمقاييس | D44: Standards | E44: 🟠 T2 | F44: 4 | G44: 68 | H44: MANDATORY | I44: - | J44: Sector-dependent | K44: Yes (where applicable) | L44: https://saso.gov.sa | M44: - | N44: - | O44: Product standards, halal, conformity
A45: PIF | B45: Public Investment Fund | C45: صندوق الاستثمارات العامة | D45: Sovereign Investment | E45: 🟠 T2 | F45: 1 | G45: 75 | H45: MANDATORY | I45: - | J45: Sector-dependent | K45: Yes (where applicable) | L45: https://pif.gov.sa | M45: - | N45: - | O45: Giga-project compliance
A46: SIDF | B46: Saudi Industrial Development Fund | C46: صندوق التنمية الصناعية السعودية | D46: Industry Finance | E46: 🟡 T3 | F46: 1 | G46: 52 | H46: MANDATORY | I46: - | J46: Sector-dependent | K46: Yes (where applicable) | M46: - | N46: -
A47: SIMAH | B47: Saudi Credit Bureau | C47: الشركة السعودية للمعلومات الائتمانية | D47: Credit | E47: 🟡 T3 | F47: 1 | G47: 55 | H47: MANDATORY | I47: - | J47: Sector-dependent | K47: Yes (where applicable) | L47: https://simah.com | M47: - | N47: - | O47: Credit reporting, SAMA oversight
A48: TADAWUL | B48: Saudi Exchange | C48: تداول السعودية | D48: Capital Markets Exchange | E48: 🟠 T2 | F48: 3 | G48: 72 | H48: MANDATORY | I48: - | J48: Sector-dependent | K48: Yes (where applicable) | L48: https://saudiexchange.sa | M48: - | N48: - | O48: Listing requirements, disclosure
A49: TVTC | B49: Technical & Vocational Training Corporation | C49: المؤسسة العامة للتدريب التقني والمهني | D49: Vocational Training | E49: 🟡 T3 | F49: 1 | G49: 40 | H49: MANDATORY | I49: - | J49: Sector-dependent | K49: Yes (where applicable) | M49: - | N49: -
A50: HRDF | B50: Human Resources Development Fund | C50: صندوق تنمية الموارد البشرية | D50: Workforce Dev. | E50: 🟡 T3 | F50: 1 | G50: 42 | H50: MANDATORY | I50: - | J50: Sector-dependent | K50: Yes (where applicable) | M50: - | N50: - | O50: Saudisation programs
A51: KACARE | B51: King Abdullah City for Atomic & Renewable Energy | C51: مدينة الملك عبدالله للطاقة الذرية والمتجددة | D51: Nuclear/Renewable | E51: 🟠 T2 | F51: 3 | G51: 70 | H51: MANDATORY | I51: - | J51: Sector-dependent | K51: Yes (where applicable) | L51: https://kacare.gov.sa | M51: - | N51: - | O51: Nuclear safety, renewable standards
A52: NCEL | B52: National Centre for Environmental Lab | C52: المركز الوطني للرقابة على الالتزام البيئي | D52: Environment | E52: 🟡 T3 | F52: 2 | G52: 45 | H52: MANDATORY | I52: - | J52: Sector-dependent | K52: Yes (where applicable) | M52: - | N52: -
A53: MEWA | B53: Ministry of Environment, Water & Agriculture | C53: وزارة البيئة والمياه والزراعة | D53: Environment/Agriculture | E53: 🟠 T2 | F53: 2 | G53: 55 | H53: MANDATORY | I53: - | J53: Sector-dependent | K53: Yes (where applicable) | M53: - | N53: -
A54: MODON | B54: Saudi Authority for Industrial Cities & Tech Zones | C54: المدن الصناعية ومناطق التقنية | D54: Industrial Zones | E54: 🟠 T2 | F54: 2 | G54: 58 | H54: MANDATORY | I54: - | J54: Sector-dependent | K54: Yes (where applicable) | L54: https://modon.gov.sa | M54: - | N54: - | O54: Industrial city compliance
A55: RCJY | B55: Royal Commission for Jubail & Yanbu | C55: الهيئة الملكية للجبيل وينبع | D55: Special Industrial | E55: 🟠 T2 | F55: 2 | G55: 60 | H55: MANDATORY | I55: - | J55: Sector-dependent | K55: Yes (where applicable) | L55: https://rcjy.gov.sa | M55: - | N55: - | O55: Industrial zone standards
A56: NEOM | B56: NEOM Company | C56: نيوم | D56: Giga Projects | E56: 🟠 T2 | F56: 2 | G56: 65 | H56: MANDATORY | I56: - | J56: Sector-dependent | K56: Yes (where applicable) | L56: https://neom.com | M56: - | N56: - | O56: Smart city, technology regulations
A57: NHIC | B57: National Health Information Centre | C57: المركز الوطني للمعلومات الصحية | D57: Health Data | E57: 🟠 T2 | F57: 2 | G57: 68 | H57: MANDATORY | I57: - | J57: Sector-dependent | K57: Yes (where applicable) | M57: - | N57: - | O57: NABIDH data exchange standards
A58: SHC_KSA | B58: Saudi Health Council | C58: المجلس الصحي السعودي | D58: Healthcare Policy | E58: 🟠 T2 | F58: 2 | G58: 65 | H58: MANDATORY | I58: - | J58: Sector-dependent | K58: Yes (where applicable) | M58: - | N58: - | O58: Health strategy coordination
A59: QIWA | B59: QIWA Platform (MHRSD) | C59: منصة قوى | D59: Labour Digital | E59: 🟡 T3 | F59: 1 | G59: 60 | H59: MANDATORY | I59: - | J59: Sector-dependent | K59: Yes (where applicable) | L59: https://qiwa.com.sa | M59: - | N59: - | O59: Labour contract management platform
A60: YESSER | B60: Yesser – e-Government programme | C60: برنامج يسر | D60: e-Gov | E60: 🟡 T3 | F60: 2 | G60: 58 | H60: MANDATORY | I60: - | J60: Sector-dependent | K60: Yes (where applicable) | L60: https://yesser.gov.sa | M60: - | N60: - | O60: Interoperability, national ID
A61: SPL | B61: Saudi Post / SPL | C61: البريد السعودي | D61: Post/Logistics | E61: 🟡 T3 | F61: 1 | G61: 40 | H61: MANDATORY | I61: - | J61: Sector-dependent | K61: Yes (where applicable) | M61: - | N61: -
A62: SSC | B62: Social Security Commission | C62: هيئة الضمان الاجتماعي | D62: Social Security | E62: 🟡 T3 | F62: 1 | G62: 45 | H62: MANDATORY | I62: - | J62: Sector-dependent | K62: Yes (where applicable) | M62: - | N62: -
A63: MOIA | B63: Ministry of Islamic Affairs | C63: وزارة الشؤون الإسلامية | D63: Religious | E63: 🟡 T3 | F63: 1 | G63: 42 | H63: MANDATORY | I63: - | J63: Sector-dependent | K63: Yes (where applicable) | M63: - | N63: -
A66: INTERNATIONAL REGULATORS / BODIES OPERATING IN KSA
A67: Code | B67: Name (EN) | C67: Body | D67: Applies To | E67: Focal KSA Regulator | F67: Mandatory? | G67: Enforcement Mechanism | H67: Frameworks (in KSA) | I67: Controls | J67: Mutual Evaluation? | K67: KSA Status | L67: Notes
A68: FATF | B68: Financial Action Task Force | C68: FATF | D68: ALL | E68: SAMA/FIU | F68: YES | G68: Via national law | H68: FATF-40 Recommendations · FATF VAs Standard | I68: 65 | J68: YES | K68: Active | L68: KSA is MENA-FATF member; SAMA/FIA enforce
A69: BCBS | B69: Basel Committee on Banking Supervision | C69: BIS | D69: Banks | E69: SAMA | F69: YES | G69: Via SAMA regulations | H69: Basel III · Basel IV (phased) | I69: 125 | J69: NO | K69: Active | L69: SAMA implements via banking regulations
A70: IOSCO | B70: IOSCO – Intl Org of Securities Commissions | C70: IOSCO | D70: Capital Markets | E70: CMA | F70: YES | G70: Via CMA rules | H70: IOSCO Principles | I70: 38 | J70: NO | K70: Active | L70: CMA is full IOSCO member
A71: AAOIFI | B71: AAOIFI – Accounting & Audit for Islamic Finance | C71: AAOIFI | D71: Islamic Finance | E71: SAMA/CMA | F71: YES | G71: SAMA endorses | H71: AAOIFI Sharia Standards | I71: 60 | J71: NO | K71: Active | L71: Mandatory for Islamic banks in KSA
A72: IFSB | B72: IFSB – Islamic Financial Stability Board | C72: IFSB | D72: Islamic Finance | E72: SAMA | F72: YES | G72: Via SAMA | H72: IFSB Core Principles | I72: 29 | J72: NO | K72: Active | L72: Prudential standards for Islamic banking
A73: SWIFT_BODY | B73: SWIFT – Society for Worldwide Interbank Telecom | C73: SWIFT | D73: Banks/FIs | E73: SAMA | F73: YES | G73: Technical requirement | H73: SWIFT CSP 2024 | I73: 31 | J73: NO | K73: Active | L73: 31 controls (23 mandatory); annual attestation
A74: ISO_IEC | B74: ISO/IEC – International Standards Bodies | C74: ISO/IEC | D74: ALL | E74: NCA/SASO | F74: YES | G74: NCA mandates ISO 27001 for regulated sectors | H74: ISO 27001:2022 · ISO 27701 · ISO 27017 · IEC 62443 | I74: 230 | J74: NO | K74: Active | L74: ISO 27001 now mandatory for NCA-regulated entities
A75: NIST_US | B75: NIST – US National Inst. Standards & Technology | C75: NIST | D75: ALL (benchmark) | E75: NCA | F75: NO (benchmark) | G75: Voluntary benchmark | H75: NIST CSF 2.0 · NIST SP 800-53 | I75: 106 | J75: NO | K75: Active | L75: NCA ECC aligned to NIST; widely referenced
A76: PCI_SSC | B76: PCI SSC – Payment Card Industry Security Council | C76: PCI SSC | D76: Payment/Cards | E76: SAMA/CITC | F76: YES | G76: Card brand requirement | H76: PCI DSS v4.0 | I76: 300 | J76: NO | K76: Active | L76: Mandatory for any org accepting card payments
A77: IASB | B77: IASB – International Accounting Standards Board | C77: IASB | D77: Listed Companies | E77: CMA/MOF | F77: YES | G77: CMA requires IFRS for listed | H77: IFRS Standards | I77: 0 | J77: NO | K77: Active | L77: All TADAWUL-listed companies must report IFRS
A78: GCC_SEC | B78: GCC Secretariat – Gulf Cooperation Council | C78: GCC | D78: Cross-GCC | E78: MOF/SAMA | F78: YES | G78: Regional treaty obligations | H78: GCC Unified AML Framework · GCC Customs Union | I78: 30 | J78: NO | K78: Active | L78: Cross-border regulatory harmonisation
A79: ICRG | B79: ICRG – FATF-Style Regional Body (MENAFATF) | C79: MENAFATF | D79: ALL | E79: SAMA/FIA | F79: YES | G79: Mutual evaluation binding | H79: FATF 40 Recommendations (MENA Focus) | I79: 40 | J79: NO | K79: Active | L79: KSA underwent FATF mutual evaluation 2024
... A82: WHO_BODY | B82: WHO – World Health Organization | C82: WHO | D82: Healthcare | E82: MOH | F82: NO (benchmark) | G82: Guidance | H82: IHR 2005 · WHO Standards | I82: 20 | J82: NO | K82: Active | L82: Pandemic preparedness, health standards
A85: TOTAL: 60 Local + 15 International = 75 Active Regulatory Bodies in KSA

Sheet KSA — GRC Dashboard
A1: 🇸🇦 SHAHIN-AI · KSA GRC INTELLIGENCE DASHBOARD · Full Regulatory Universe
A3: Total Regulators in KSA | D3: 60 local + 15 international = 75 total
A4: Tier 1 (Critical Power) | D4: 10 local primary regulators
A5: Tier 2 (Sector) | D5: 37 sector-level regulators
A6: International Bodies Active in KSA | D6: 15 (FATF, Basel, IOSCO, SWIFT, ISO, IEC, etc.)
A7: KSA Frameworks (key) | D7: 23 documented key frameworks
A8: Total Control Count (KSA) | D8: 28,239 individual controls (from 405 frameworks)
A9: Sectors Covered | D9: 13 sectors with full regulatory mapping
A10: Org Types Mapped | D10: 12 organisation types with obligation matrix
A11: Org Size Tiers | D11: 6 tiers (Micro → SIFI) with cost/burden estimates
A12: Risk Domains Tracked | D12: 12 risk domains with KRIs and thresholds
A13: Evidence Types Required | D13: 15 types of compliance evidence
A16: KSA SECTOR SUMMARY
A17: Sector | B17: Emoji | C17: Local Regs | D17: Intl Regs | E17: Total Regs | F17: Key Frameworks | G17: Controls | H17: Risk Level | I17: IoT Intensity | J17: Risk Score
A18: Financial Services | B18: 🏦 | C18: 3 | D18: 7 | E18: 10 | F18: 8 | G18: 387 | H18: CRITICAL | I18: LOW | J18: 740
A19: Healthcare & Life Sciences | B19: 🏥 | C19: 7 | D19: 3 | E19: 10 | F19: 8 | G19: 298 | H19: CRITICAL | I19: HIGHEST | J19: 746
A20: Cybersecurity & Data | B20: 🔒 | C20: 4 | D20: 3 | E20: 7 | F20: 7 | G20: 358 | H20: CRITICAL | I20: HIGHEST | J20: 493
A21: ICT / Digital / Telecom | B21: 📡 | C21: 4 | D21: 2 | E21: 6 | F21: 6 | G21: 245 | H21: HIGH | I21: HIGH | J21: 493
A22: Energy & Utilities | B22: ⚡ | C22: 5 | D22: 2 | E22: 7 | F22: 6 | G22: 223 | H22: CRITICAL | I22: HIGHEST | J22: 673
A23: Government & Public Sector | B23: 🏛️ | C23: 6 | D23: 1 | E23: 7 | F23: 6 | G23: 305 | H23: CRITICAL | I23: MODERATE | J23: 648
A24: Tax / Customs / Trade | B24: 📋 | C24: 3 | D24: 2 | E24: 5 | F24: 5 | G24: 115 | H24: HIGH | I24: LOW | J24: 585
A25: Standards & Quality | B25: ✅ | C25: 2 | D25: 2 | E25: 4 | F25: 4 | G25: 85 | H25: MEDIUM | I25: LOW | J25: 493
A26: Transport & Logistics | B26: 🚢 | C26: 4 | D26: 1 | E26: 5 | F26: 4 | G26: 132 | H26: HIGH | I26: HIGH | J26: 493
A27: Industry & Manufacturing | B27: 🏭 | C27: 4 | D27: 2 | E27: 6 | F27: 5 | G27: 145 | H27: HIGH | I27: HIGH | J27: 588
A28: Education & Research | B28: 🎓 | C28: 4 | D28: 1 | E28: 5 | F28: 4 | G28: 95 | H28: MEDIUM | I28: MODERATE | J28: 493
A29: Legal & Anti-Corruption | B29: ⚖️ | C29: 3 | D29: 1 | E29: 4 | F29: 4 | G29: 68 | H29: HIGH | I29: LOW | J29: 493
A30: Giga & Special Zones | B30: 🌆 | C30: 5 | D30: 2 | E30: 7 | F30: 4 | G30: 178 | H30: HIGH | I30: HIGHEST | J30: 585
A34: NAVIGATION — DRILL-DOWN SHEETS IN THIS WORKBOOK
A35: → KSA — Regulator Master | B35: All 75 regulators: local + international, tiers, power index, frameworks
A36: → KSA — Sector Drill-Down | B36: All 13 sectors: per sector regulators, frameworks, evidence, risk
A37: → KSA — Org Type Matrix | B37: All 12 org types: obligation matrix, CISO/DPO/MLRO requirements
A38: → KSA — Org Size Guide | B38: All 6 size tiers: compliance cost, controls, audit requirements
A39: → KSA — Framework Master | B39: All 23 key frameworks: domains, controls, evidence, risk, effective date
A40: → KSA — Evidence Matrix | B40: All 15 evidence types × org type cross-reference
A41: → KSA — Risk Matrix | B41: All 12 risk domains: heat map, KRIs, thresholds, escalation

Sheet Navigation Hub
A1: 🏠 KSA GRC KNOWLEDGE BASE — NAVIGATION HUB
A2: The Most Comprehensive GRC Intelligence Platform for Saudi Arabia • 108 Regulators • 452 Frameworks • 28,000+ Controls
A4: 📚 CORE DATA SHEETS
A5: # | B5: Sheet Name | C5: Description | D5: Rows | E5: Purpose
A6: 1 | B6: All 108 Regulators - Frameworks | C6: Master database: 452 framework entries across 53 data dimensions per framework | D6: 452 | E6: 💾 Primary data source — DO NOT MODIFY structure
A7: 2 | B7: Per-Regulator Summary | C7: 107 regulators with framework count, codes, HC IoT ranking | D7: 107 | E7: 📊 Regulator-level aggregation
A8: 3 | B8: HC IoT Priority Ranked | C8: 339 frameworks ranked by Healthcare IoT relevance | D8: 339 | E8: 🏥 Healthcare IoT focus ranking
A9: 4 | B9: Version Details Reference | C9: 191 version history entries with change details | D9: 191 | E9: 📅 Version tracking and change history
A10: 5 | B10: HC IoT Compliance Checklist | C10: 64-item compliance checklist for healthcare IoT | D10: 64 | E10: ✅ Practical compliance checklist
A12: 🔬 ANALYSIS & INTELLIGENCE SHEETS
A13: 6 | B13: GRC Intelligence Engine | C13: 🆕 Automated scoring: KPIs, Power Index, IoT distribution, Velocity, Maturity gaps | D13: 210+ | E13: 🧠 Analytics engine — auto-updates from master data
A14: 7 | B14: Executive Command Centre | C14: 🆕 Visual dashboard with 4 charts, 7 KPI cards, auto-calculated metrics | D14: N/A | E14: 📊 Executive presentation — charts auto-refresh
A15: 8 | B15: GRC Linkage Engine | C15: 🆕 Unified 9-dimension traceability: Controls ↔ Evidence ↔ Risk ↔ Lifecycle ↔ Policy ↔ Treatment ↔ Org Size ↔ Regulatory ↔ Sector | D15: 135+ | E15: 🔗 End-to-end GRC operating model — connective tissue
A16: 8 | B16: Risk Domain Coverage Matrix | C16: Framework × Risk Domain mapping with coverage scores | D16: 25 | E16: 🎯 Risk coverage analysis
A17: 9 | B17: Sector × Framework Matrix | C17: 17 sectors × frameworks applicability matrix | D17: 33 | E17: 🟢 Sector coverage map
A18: 10 | B18: Framework Debate Matrix | C18: Academic for/against analysis per framework with citations | D18: 191 | E18: 🎓 Academic positioning
A19: 11 | B19: KSA GRC Architecture Map | C19: Layer-by-layer GRC ecosystem with dependencies and conflicts | D19: 36 | E19: 🏗️ Architecture blueprint
A21: 🎯 OPERATIONAL SHEETS
A22: 12 | B22: Audit Universe (All Sectors) | C22: 49 audit areas with risk ratings, frequency, evidence requirements | D22: 49 | E22: 🔎 Audit planning
A23: 13 | B23: KRI Dashboard (All Sectors) | C23: 42 Key Risk Indicators with Green/Amber/Red thresholds and benchmarks | D23: 42 | E23: 🚦 Risk monitoring
A24: 14 | B24: GRC Maturity (All Sectors) | C24: 9 GRC domains × 5 maturity levels with evidence requirements | D24: 9 | E24: 📈 Maturity assessment
A25: 15 | B25: Compliance Calculator | C25: 🆕 Input sector/entity → auto-generates applicable frameworks, controls, audits | D25: Dynamic | E25: 🧮 Interactive compliance tool
A27: 🌐 STRATEGIC & EXTENSIBILITY SHEETS
A28: 16 | B28: Global GRC Benchmark | C28: 🆕 KSA vs international frameworks (EU, US, UK, UAE, ISO) | D28: TBD | E28: 🌍 International positioning
A29: 17 | B29: Regulatory Change Log | C29: 🆕 Version tracking with dropdown status, impact, deadlines | D29: Extensible | E29: 📝 Change management
A30: 18 | B30: Framework Dependencies | C30: 🆕 Cross-framework relationship map: extends, overlaps, conflicts | D30: 14+ | E30: 🔗 Dependency mapping
A32: 🎓 KNOWLEDGE & LEARNING SHEETS
A33: 19 | B33: Knowledge Foundation | C33: 10 theoretical frameworks underpinning KSA GRC: governance theory, institutional theory, risk mgmt | D33: 10 | E33: 📚 Academic theory base
A34: 20 | B34: Learning Pathway | C34: 26-step learning pathway from foundation to expert | D34: 26 | E34: 🎓 Professional development
A35: 21 | B35: GH-ICGA Positioning Matrix | C35: 5-layer GH-ICGA framework positioning with academic research gaps | D35: 5 | E35: 🎯 Thesis positioning
A36: 22 | B36: Content Eval & Shahin-AI | C36: 🆕 Full evaluation: 10-dimension scoring, AI architecture, RAG chunking spec, 8 MCP endpoints, improvement roadmap | D36: 145+ | E36: 🧪 Combined human + AI optimisation report
A37: Last Updated: April 2026 • Built for GH-ICGA Doctoral Research • © KSA GRC Knowledge Base

Sheet GRC Linkage Engine
A1: 🔗 GRC LINKAGE ENGINE — UNIFIED CONTROL-TO-SECTOR TRACEABILITY
A2: Controls ↔ Evidence ↔ Risk ↔ Lifecycle ↔ Policy ↔ Treatment ↔ Org Size ↔ KSA Regulatory ↔ Sector • End-to-end GRC operating model
A4: ━━━ SECTION A: CONTROL-TO-EVIDENCE MATRIX ━━━
A5: Link ID | B5: Framework | C5: Control Category | D5: Control Domain | E5: Evidence Type Required | F5: Evidence Examples | G5: Evidence Retention | H5: → Risk if Missing
A6: CE-001 | B6: NCA-ECC-2:2024 | C6: Administrative (A) | D6: Governance & Leadership (A.1) | E6: Policy Document | F6: Board-approved cybersecurity strategy; CISO appointment letter; cyber committee TOR; governance framework document | G6: 5 years | H6: → RISK-001: Governance failure → NCA non-compliance → SAR 25M fine
A7: CE-002 | B7: NCA-ECC-2:2024 | C7: Administrative (A) | D7: Workforce & Saudisation (A.2) | E7: HR Records + Certificates | F7: Saudi national ID verification for cyber roles; NCA-recognised CISO certification; Qiwa Saudisation report; GOSI registration proof | G7: Duration + 3yr | H7: → RISK-002: Saudisation breach → Nitaqat Red zone + ECC-2 non-compliance
A8: CE-003 | B8: NCA-ECC-2:2024 | C8: Administrative (A) | D8: Training & Awareness (A.3) | E8: Training Records | F8: Annual awareness completion logs; phishing simulation results; role-based training certificates; social engineering test reports | G8: 3 years | H8: → RISK-003: Human factor vulnerability → breach likelihood increases 4×
A9: CE-004 | B9: NCA-ECC-2:2024 | C9: Technical (T) | D9: Access Control (T.1) | E9: System Configuration + Logs | F9: IAM policy; MFA deployment evidence; privileged access reviews (quarterly); access recertification; segregation of duties matrix | G9: 3 years | H9: → RISK-004: Unauthorised access → data breach → PDPL + NCA dual penalty
A10: CE-005 | B10: NCA-ECC-2:2024 | C10: Technical (T) | D10: Network Security (T.2) | E10: Architecture Diagram + Scans | F10: Network segmentation diagram; firewall rulesets; IDS/IPS alerts; penetration test report (annual); vulnerability scan (monthly) | G10: 3 years | H10: → RISK-005: Network compromise → lateral movement → CNI disruption
A11: CE-006 | B11: NCA-ECC-2:2024 | C11: Technical (T) | D11: Encryption & Data Protection (T.3) | E11: Technical Configuration | F11: Encryption at rest/transit evidence; certificate management; key rotation logs; data classification matrix; DLP rule evidence | G11: 3 years | H11: → RISK-006: Data exposure → PDPL breach + patient privacy violation
A12: CE-007 | B12: NCA-ECC-2:2024 | C12: Operational (O) | D12: Incident Response (O.1) | E12: IR Plan + Test Records | F12: NCA-aligned IR plan; 24h NCA notification procedure; tabletop exercise report (annual); post-incident review; CSIRT roster | G12: 5 years | H12: → RISK-007: Delayed response → NCA 24h breach → regulatory escalation
A13: CE-008 | B13: NCA-ECC-2:2024 | C13: Operational (O) | D13: BCP & Disaster Recovery (O.2) | E13: BCP + DR Test Evidence | F13: Business impact analysis; RTO/RPO definitions; DR test results (annual); backup verification; failover evidence | G13: 5 years | H13: → RISK-008: Service disruption → patient safety impact → clinical harm
A14: CE-009 | B14: NCA-ECC-2:2024 | C14: Operational (O) | D14: Third-Party Management (O.3) | E14: Vendor Assessment + Contracts | F14: Vendor risk assessments; ECC-2 compliance clauses in contracts; right-to-audit evidence; annual vendor reassessment; NCA-registered CSP verification | G14: Contract + 3yr | H14: → RISK-009: Supply chain compromise → inherited risk → NCA responsibility
A15: CE-010 | B15: PDPL-2021 | C15: Legal/Privacy | D15: Data Subject Rights (PDPL Art. 4-8) | E15: Process Documentation | F15: Consent records; privacy notices; DSAR response logs (30-day SLA); right-to-deletion evidence; data portability procedures | G15: 10 years | H15: → RISK-010: PDPL violation → SDAIA penalty + criminal for breach notification failure
A16: CE-011 | B16: PDPL-2021 | C16: Legal/Privacy | D16: DPIA & Impact Assessment (PDPL Art. 22) | E16: Assessment Report | F16: Data Protection Impact Assessment register; high-risk processing inventory; SDAIA notification for automated decision-making; cross-border transfer assessment | G16: Lifetime + 5yr | H16: → RISK-011: Unassessed processing → unlawful activity → SDAIA enforcement
... A20: CE-015 | B20: CBAHI-HAS-H | C20: Accreditation | D20: Hospital Quality & Safety | E20: Clinical Quality Records | F20: Mortality & morbidity reviews; infection control surveillance; medication error reports; patient satisfaction surveys; clinical audit results | G20: 5 years | H20: → RISK-015: Accreditation loss → cannot bill insurers → operational shutdown
A22: ━━━ SECTION B: EVIDENCE-GAP-TO-RISK MAP — What Happens When Evidence Is Missing ━━━
A23: Risk ID | B23: Evidence Gap | C23: Primary Risk Domain | D23: Secondary Risk | E23: Inherent Risk Level | F23: Regulatory Consequence | G23: Linked KRI | H23: → Lifecycle Phase
A24: RISK-001 | B24: No board-approved cyber strategy / CISO appointment | C24: Governance Failure | D24: Regulatory Risk | E24: 🔴 CRITICAL | F24: NCA-REG-2024: SAR 25M fine + criminal referral for senior management; ECC-2 self-assessment score <60% triggers NCA audit | G24: KRI-X001 | H24: → PLAN phase
A25: RISK-002 | B25: Non-Saudi in mandatory cyber roles / no Saudi ID proof | C25: Workforce Compliance | D25: Regulatory Risk | E25: 🔴 CRITICAL | F25: Dual penalty: NCA ECC-2 non-compliance + MHRSD Nitaqat Red zone; visa block; work permit suspension | G25: KRI-X004 | H25: → OPERATE phase
A26: RISK-003 | B26: No training completion records / phishing test results | C26: Human Factor Vulnerability | D26: Cyber Risk | E26: 🟠 HIGH | F26: NCA finding in self-assessment Domain 1; increased breach probability; insurance may void coverage | G26: KRI-X001 | H26: → OPERATE phase
A27: RISK-004 | B27: No MFA evidence / missing privileged access reviews | C27: Unauthorised Access | D27: Privacy Risk | E27: 🔴 CRITICAL | F27: ECC-2 Domain 2 failure; PDPL breach if patient data accessed; dual NCA+SDAIA enforcement | G27: KRI-X002 | H27: → IMPLEMENT phase
A28: RISK-005 | B28: No segmentation diagram / missing pen test report | C28: Network Compromise | D28: Operational Risk | E28: 🔴 CRITICAL | F28: NCA ECC-2 Domain 2 failure; CNI entities face additional OTCC non-compliance; healthcare facility shutdown possible | G28: KRI-X002 | H28: → IMPLEMENT phase
A29: RISK-006 | B29: No encryption at rest/transit evidence / missing key rotation | C29: Data Exposure | D29: Privacy Risk | E29: 🔴 CRITICAL | F29: ECC-2 + PDPL dual breach; patient data exposed = automatic SDAIA notification; NCA escalation for CNI | G29: KRI-X003 | H29: → IMPLEMENT phase
A30: RISK-007 | B30: No IR plan / missing NCA 24h notification procedure | C30: Delayed Incident Response | D30: Clinical Safety Risk | E30: 🔴 CRITICAL | F30: NCA-REG-2024: failure to report = criminal offence; PDPL 72h breach notification = criminal penalty for DPO | G30: KRI-X001 | H30: → OPERATE phase
A31: RISK-008 | B31: No BIA / untested BCP / no DR evidence | C31: Service Disruption | D31: Patient Safety | E31: 🟠 HIGH | F31: Healthcare system unavailability = clinical harm; CBAHI accreditation jeopardised; MOH escalation | G31: KRI-X001 | H31: → REVIEW phase
A32: RISK-009 | B32: No vendor risk assessment / missing ECC-2 contract clauses | C32: Supply Chain Compromise | D32: Regulatory Risk | E32: 🟠 HIGH | F32: ECC-2 Domain 4 non-compliance; entity retains liability for vendor breach; cloud CSP must be NCA-registered | G32: KRI-X001 | H32: → IMPLEMENT phase
A33: RISK-010 | B33: No consent records / missing DSAR response logs | C33: PDPL Non-compliance | D33: Reputational Risk | E33: 🔴 CRITICAL | F33: SDAIA penalty; data subject compensation claims; criminal referral for DPO if breach unreported | G33: KRI-X003 | H33: → OPERATE phase
A34: RISK-011 | B34: No DPIA register / unassessed high-risk processing | C34: Unlawful Data Processing | D34: Regulatory Risk | E34: 🟠 HIGH | F34: PDPL Art. 22 breach; SDAIA enforcement; cross-border transfer invalid without assessment | G34: KRI-X003 | H34: → PLAN phase
... A38: RISK-015 | B38: Failed CBAHI survey / expired accreditation | C38: Accreditation Loss | D38: Financial Risk | E38: 🟠 HIGH | F38: Cannot bill CCHI-regulated insurers; MOH may restrict patient intake; reputational damage for hospital | G38: N/A | H38: → REVIEW phase
A40: ━━━ SECTION C: RISK-TO-LIFECYCLE MAPPING — When Each Risk Peaks in the GRC Lifecycle ━━━
A41: Lifecycle Phase | B41: Phase Description | C41: Risks Active in This Phase | D41: Key GRC Activities | E41: KSA Frameworks Governing | F41: Evidence Generated | G41: → Policy Required
A42: 1️⃣ PLAN | B42: Strategic planning, risk identification, framework scoping, DPIA, architecture design, vendor selection | C42: RISK-001 (Governance failure); RISK-011 (Unassessed processing); RISK-013 (Unregistered device) | D42: Risk assessment; regulatory landscape scan; DPIA; control selection; architecture review; vendor due diligence; SFDA pre-submission | E42: ECC-2 Domain 1 (Governance); PDPL Art. 22 (DPIA); SFDA MDR (Pre-market); NCA-CCC (Cloud assessment) | F42: Risk register; DPIA report; architecture design; vendor shortlist; SFDA pre-submission dossier; project charter | G42: → POL-001 to POL-004
A43: 2️⃣ IMPLEMENT | B43: Control deployment, system configuration, network segmentation, encryption, OT inventory, NABIDH integration | C43: RISK-004 (Access); RISK-005 (Network); RISK-006 (Data exposure); RISK-009 (Vendor); RISK-012 (OT); RISK-014 (Interop) | D43: IAM deployment; MFA rollout; network segmentation; encryption config; OT zone/conduit; vendor onboarding; NABIDH connectivity | E43: ECC-2 Domains 2-3 (Technical/Operational); OTCC (OT segmentation); NCA-DCC (Data controls); MOH-HIS (Interop) | F43: Configuration evidence; test results; vendor contracts; NABIDH certificate; segmentation diagrams; encryption proof | G43: → POL-005 to POL-009
A44: 3️⃣ OPERATE | B44: Day-to-day operations, monitoring, incident response, training, DSAR handling, Saudisation maintenance | C44: RISK-002 (Saudisation); RISK-003 (Human factor); RISK-007 (IR delay); RISK-010 (PDPL consent) | D44: Continuous monitoring; awareness training; phishing simulation; IR activation; DSAR processing; Nitaqat tracking; KRI monitoring | E44: ECC-2 all domains (continuous); PDPL (consent/DSARs); MHRSD-NITAQAT (workforce); NCA-REG-2024 (reporting) | F44: Training records; monitoring dashboards; IR reports; DSAR logs; Qiwa reports; KRI measurements; NCA notification evidence | G44: → POL-010 to POL-014
A45: 4️⃣ REVIEW | B45: Annual audit, self-assessment, BCP test, accreditation survey, maturity assessment, gap analysis | C45: RISK-008 (BCP untested); RISK-015 (Accreditation loss); all risks resurface for gap identification | D45: NCA self-assessment; PDPL annual audit; BCP/DR test; CBAHI survey; vendor reassessment; maturity assessment; KRI trend analysis | E45: ECC-2 (annual self-assessment); CBAHI-HAS-H (3-year survey); PDPL-IR (annual audit); ZATCA (e-invoice audit) | F45: Self-assessment report; audit findings; BCP test results; CBAHI survey report; gap analysis; improvement plan | G45: → POL-015 to POL-017
A46: 5️⃣ RETIRE / TRANSITION | B46: System decommission, data retention/destruction, vendor exit, framework version migration, legacy device phase-out | C46: RISK-006 (Data exposure during destruction); RISK-013 (Legacy device risk); RISK-009 (Vendor exit risk) | D46: Data sanitisation; certificate revocation; vendor exit management; legacy control migration; PDPL data destruction evidence | E46: PDPL (data retention/destruction); SFDA-MDR (device decommission); NCA-DCC (data lifecycle); ECC-2 (asset disposal) | F46: Data destruction certificates; asset disposal records; vendor exit checklist; migration completion evidence; SFDA deregistration | G46: → POL-018 to POL-020
A48: ━━━ SECTION D: LIFECYCLE-TO-POLICY CHAIN — Required Policies per Phase ━━━
A49: Policy ID | B49: Policy Name | C49: Lifecycle Phase | D49: Regulatory Source | E49: Policy Hierarchy Level | F49: Approval Authority | G49: Review Cycle | H49: → Treatment if Gap
A50: POL-001 | B50: Cybersecurity Strategy & Governance Policy | C50: PLAN | D50: ECC-2 Domain 1 (Governance); NCA-REG-2024 | E50: L1 — Strategic | F50: Board of Directors | G50: Annual | H50: → TRT-001
A51: POL-002 | B51: Data Protection & Privacy Policy (PDPL) | C51: PLAN | D51: PDPL-2021; PDPL-IR-2023; PDPL-DTR-2024 | E51: L1 — Strategic | F51: Board / DPO | G51: Annual | H51: → TRT-002
A52: POL-003 | B52: Risk Management Framework Policy | C52: PLAN | D52: ISO 31000 aligned; ECC-2 risk domain; SAMA-CSF (financial) | E52: L1 — Strategic | F52: Board Risk Committee | G52: Annual | H52: → TRT-003
A53: POL-004 | B53: Medical Device & IoMT Governance Policy | C53: PLAN | D53: SFDA-MDR; SFDA-AI-MDS; NCA-OTCC; CBAHI HIT | E53: L1 — Strategic | F53: CMIO / CISO | G53: Annual | H53: → TRT-004
A54: POL-005 | B54: Access Control & Identity Management Policy | C54: IMPLEMENT | D54: ECC-2 Domain 2 (Technical); PDPL (data access) | E54: L2 — Operational | F54: CISO | G54: Annual | H54: → TRT-005
A55: POL-006 | B55: Network Security & Segmentation Policy | C55: IMPLEMENT | D55: ECC-2 Domain 2; NCA-OTCC (OT segmentation) | E55: L2 — Operational | F55: CISO / IT Director | G55: Annual | H55: → TRT-006
A56: POL-007 | B56: Encryption & Data Classification Policy | C56: IMPLEMENT | D56: ECC-2 Domain 2; NCA-DCC; PDPL (data protection) | E56: L2 — Operational | F56: CISO / DPO | G56: Annual | H56: → TRT-007
A57: POL-008 | B57: Third-Party & Vendor Risk Management Policy | C57: IMPLEMENT | D57: ECC-2 Domain 4; NCA-CCC (cloud vendors); PDPL (data processors) | E57: L2 — Operational | F57: Procurement / CISO | G57: Annual | H57: → TRT-008
A58: POL-009 | B58: OT/IoMT Network Security Policy | C58: IMPLEMENT | D58: NCA-OTCC; SFDA-MDR; IEC 62443 referenced | E58: L2 — Operational | F58: CISO / Biomedical Eng | G58: Annual | H58: → TRT-009
A59: POL-010 | B59: Incident Response & NCA Notification Policy | C59: OPERATE | D59: ECC-2 Domain 3; NCA-REG-2024 (24h); PDPL (72h breach) | E59: L2 — Operational | F59: CISO / DPO | G59: Semi-annual | H59: → TRT-010
A60: POL-011 | B60: Security Awareness & Phishing Simulation Policy | C60: OPERATE | D60: ECC-2 Domain 1 (Awareness); ISO 27001 A.7.2.2 | E60: L3 — Standard | F60: CISO | G60: Annual | H60: → TRT-011
... A69: POL-020 | B69: Vendor Exit & Transition Management Policy | C69: RETIRE | D69: ECC-2 Domain 4; NCA-CCC (cloud exit); PDPL (data return) | E69: L2 — Operational | F69: Procurement / Legal | G69: As needed | H69: → TRT-020
A71: ━━━ SECTION E: POLICY-GAP-TO-TREATMENT REGISTER — Risk Treatment Options per Gap ━━━
A72: Treatment ID | B72: Policy Gap | C72: MITIGATE Option | D72: TRANSFER Option | E72: ACCEPT Conditions | F72: AVOID Option | G72: Recommended Treatment | H72: → Org Size Factor
A73: TRT-001 | B73: No Cybersecurity Strategy (POL-001) | C73: Develop board-approved strategy; appoint CISO; establish cyber committee; set annual review cycle | D73: Engage vCISO / external consultant for strategy development; outsource governance to MSSP with NCA experience | E73: ❌ CANNOT ACCEPT — ECC-2 mandatory; NCA-REG-2024 criminalises non-compliance | F73: N/A — regulation cannot be avoided for entities in scope | G73: 🟢 MITIGATE | H73: → ORG-S/M/L/E
A74: TRT-002 | B74: No Data Privacy Policy (POL-002) | C74: Appoint DPO; build DPIA programme; implement consent management; establish PDPL compliance register | D74: Engage external DPO as service; outsource DPIA to privacy consultancy; use OneTrust/TrustArc platform | E74: ❌ CANNOT ACCEPT — PDPL mandatory for all entities processing personal data | F74: Stop processing personal data entirely (rarely practical) | G74: 🟢 MITIGATE | H74: → ORG-S/M/L/E
A75: TRT-003 | B75: No Risk Management Framework (POL-003) | C75: Adopt ISO 31000; build risk register; define risk appetite; establish risk committee; quarterly risk reviews | D75: Outsource risk assessment to Big 4 / GRC consultancy; use automated risk scoring (ServiceNow/Archer) | E75: ⚠️ CONDITIONAL — Board must formally document acceptance with annual review | F75: N/A — risk management is foundational to all frameworks | G75: 🟢 MITIGATE | H75: → ORG-S/M/L/E
A76: TRT-004 | B76: No IoMT/Device Governance (POL-004) | C76: Build IoMT inventory; SFDA registration review; OTCC zone mapping for medical OT; device lifecycle policy | D76: Engage biomedical engineering consultancy; Medigate/Claroty for IoMT visibility; outsource SFDA regulatory affairs | E76: ❌ CANNOT ACCEPT — SFDA-MDR mandatory; unregistered devices = seizure | F76: Remove all unregistered devices from clinical use | G76: 🟢 MITIGATE | H76: → ORG-M/L/E only
A77: TRT-005 | B77: No Access Control Policy (POL-005) | C77: Deploy IAM solution; enforce MFA; quarterly access reviews; privileged access management (PAM); SoD matrix | D77: IAMaaS (CyberArk, BeyondTrust); outsource access reviews to SOC provider | E77: ❌ CANNOT ACCEPT — ECC-2 Domain 2 mandatory | F77: N/A | G77: 🟢 MITIGATE | H77: → ORG-S/M/L/E
A78: TRT-006 | B78: No Network Segmentation Policy (POL-006) | C78: Implement micro-segmentation; deploy next-gen firewall; create OT DMZ; document zone architecture | D78: Managed firewall/SD-WAN service; outsource network monitoring to MSSP | E78: ❌ CANNOT ACCEPT — ECC-2 + OTCC mandatory for CNI entities | F78: Air-gap critical OT networks (partial avoidance) | G78: 🟢 MITIGATE | H78: → ORG-M/L/E
A79: TRT-010 | B79: No Incident Response Policy (POL-010) | C79: Develop NCA-aligned IR plan; 24h notification procedure; CSIRT roster; annual tabletop; SOAR integration | D79: Outsource IR to MSSP with NCA notification capability; retain IR retainer with Big 4 | E79: ❌ CANNOT ACCEPT — NCA-REG-2024 criminalises failure to report | F79: N/A | G79: 🟢 MITIGATE | H79: → ORG-S/M/L/E
A80: TRT-012 | B80: Saudisation Non-compliance (POL-012) | C80: Accelerated Saudi cyber hiring programme; NCA training pathway; scholarship programme; internal Saudisation targets | D80: Partner with Saudi universities; NCA Cyber Academy pipeline; secondment agreements with SAFCSP | E80: ❌ CANNOT ACCEPT — ECC-2 mandate + Nitaqat legally enforced | F80: Automate cyber roles to reduce headcount requirement (partial) | G80: 🟢 MITIGATE | H80: → ORG-ALL sizes
A82: ━━━ SECTION F: TREATMENT-BY-ORGANISATION-SIZE SCALING — Right-Sized Implementation ━━━
A83: GRC Domain | B83: 🏪 SMALL (<50 staff) | C83: 🏢 MEDIUM (50-500) | D83: 🏗️ LARGE (500-5000) | E83: 🏨 ENTERPRISE (5000+) | F83: KSA Regulatory Adjustment
A84: Cybersecurity Governance (ECC-2) | B84: vCISO or part-time CISO; combined IT/security role; ECC-2 self-assessment outsourced; basic policy set (5 policies) | C84: Dedicated CISO (Saudi national); internal IT security team (3-5); ECC-2 self-assessment in-house; full policy set (15 policies) | D84: CISO + dedicated team (10-20); SOC (internal or hybrid); ECC-2 programme office; advanced tooling (SIEM, SOAR, EDR) | E84: CISO + multi-team security org (50+); 24/7 SOC; GRC platform (ServiceNow/Archer); threat intelligence; red team | F84: All sizes: ECC-2 mandatory if in scope. Small entities may request NCA guidance on proportional implementation
A85: Data Privacy (PDPL) | B85: External DPO (shared service); basic consent + privacy notice; manual DSAR process; annual DPIA review | C85: Internal DPO (can be dual-role); OneTrust/TrustArc for consent; semi-automated DSAR; quarterly DPIA reviews | D85: Dedicated DPO + privacy team (3-5); privacy-by-design embedded; automated consent/DSAR; continuous DPIA | E85: DPO + privacy office (10+); automated data mapping; AI-powered DSAR; privacy engineering team; cross-border adequacy | F85: PDPL applies equally to all sizes. DPO mandatory if processing sensitive data (health data = sensitive)
A86: OT/IoMT Security (OTCC) | B86: N/A for most small entities; if clinic with IoMT: basic inventory + vendor management | C86: OT inventory (Medigate/Claroty); basic segmentation; vendor patch management; OTCC self-assessment | D86: Dedicated OT security team; full Purdue model segmentation; OT SOC integration; IEC 62443 alignment | E86: OT security programme office; AI-driven anomaly detection; zero-trust OT; digital twin security; OTCC leadership | F86: OTCC mandatory for CNI entities only. Hospitals >100 beds typically classified as CNI
A87: Incident Response | B87: Basic IR plan; manual NCA notification (24h); annual tabletop via consultant; outsourced IR retainer | C87: Documented IR plan; tested NCA/SDAIA notification; annual tabletop; IR team (3-5); basic SOAR | D87: Advanced IR programme; SOAR-automated response; quarterly tabletop; internal CSIRT; threat hunting | E87: 24/7 CSIRT; automated MTTD <1h; SOAR + TI integration; sector-level IR coordination; NCA real-time reporting | F87: NCA 24h notification: mandatory for ALL sizes. PDPL 72h breach notification: mandatory for ALL
A88: Supply Chain GRC | B88: Basic vendor questionnaire; ECC-2 clause in contracts; annual vendor check | C88: Vendor risk scoring; annual assessment of critical vendors; right-to-audit; NCA-registered CSP check | D88: Automated vendor risk management (Prevalent/BitSight); continuous monitoring; sub-contractor disclosure | E88: Zero-trust supply chain; vendor certification programme; real-time supply chain risk feeds; vendor SOC integration | F88: ECC-2 Domain 4 + NCA-CCC: vendor obligations apply equally. Cloud CSPs must be NCA-registered regardless
A89: Saudisation | B89: Hire 1-2 Saudi cyber staff; leverage NCA Cyber Academy graduates; Green zone target | C89: Saudi cyber team (5-10); NCA training programme; Platinum zone target; SCFHS registration for health roles | D89: Saudi cyber workforce programme; university partnerships; graduate pipeline; 100% Saudi CISO team | E89: Saudi cyber centre of excellence; export Saudi GRC talent; SAFCSP collaboration; industry leadership | F89: ECC-2: 100% Saudi cyber roles by Oct 2025 deadline. Nitaqat zones vary by sector — health: special formula
A90: Medical Device Compliance | B90: Basic SFDA device register; vendor-managed UDI; minimal PMS | C90: Internal SFDA compliance officer; device lifecycle tracking; PMS programme; adverse event reporting | D90: Regulatory affairs team; full UDI management; clinical evidence generation; SFDA audit readiness | E90: Regulatory affairs department; AI-MDS compliance; global MDR harmonisation; clinical investigation programme | F90: SFDA-MDR mandatory for all device operators. AI-MDS applies if using AI diagnostics regardless of size
A91: GRC Tooling & Automation | B91: Spreadsheet-based GRC (this workbook!); basic cloud collaboration; manual KRI tracking | C91: Entry-level GRC platform (Hyperproof/LogicGate); semi-automated KRI; integrated risk register | D91: Enterprise GRC platform (ServiceNow/Archer); automated compliance monitoring; API integrations | E91: Full GRC ecosystem; AI-powered compliance; RegTech integration; Shahin-AI type natural language GRC | F91: No KSA mandate on GRC tooling. NCA self-assessment via NCA portal (mandatory). PDPL may require automated consent tools
A93: ━━━ SECTION G: ORG-SIZE-TO-KSA-REGULATORY MAPPING — Who Regulates You Based on Size ━━━
A94: Regulator / Framework | B94: 🏪 SMALL (<50) | C94: 🏢 MEDIUM (50-500) | D94: 🏗️ LARGE (500-5K) | E94: 🏨 ENTERPRISE (5K+) | F94: Trigger / Scope Rule | G94: KSA Market Context
A95: NCA — ECC-2:2024 | B95: ✅ If gov/CNI | C95: ✅ If gov/CNI | D95: ✅ Mandatory | E95: ✅ Mandatory | F95: Government entities: ALL sizes. Private: only if designated CNI by NCA. Large private healthcare usually CNI | G95: ~90% of large healthcare entities are in NCA scope; small clinics often unclear
A96: NCA — OTCC-1:2022 | B96: ❌ | C96: ⚠️ If CNI+OT | D96: ✅ If CNI+OT | E96: ✅ If CNI+OT | F96: Only CNI entities with OT/ICS. Hospitals with connected medical devices: OTCC applies to OT network | G96: Major hospitals (>100 beds) typically in OTCC scope; polyclinics usually exempt
A97: NCA — CCC-1:2020 | B97: ✅ If cloud+ECC | C97: ✅ If cloud+ECC | D97: ✅ If cloud+ECC | E97: ✅ If cloud+ECC | F97: Applies to ALL ECC-scope entities using cloud. Cloud CSP must be NCA-registered | G97: Almost universal — even small clinics use cloud EHR/email; CCC triggered by any cloud usage
A98: SDAIA — PDPL-2021 | B98: ✅ Mandatory | C98: ✅ Mandatory | D98: ✅ Mandatory | E98: ✅ Mandatory | F98: ALL entities processing personal data of KSA residents. No size exemption. Health data = sensitive category | G98: Universal. Even 1-person clinic collecting patient names = PDPL scope
A99: SFDA — MDR | B99: ✅ If devices | C99: ✅ If devices | D99: ✅ If devices | E99: ✅ If devices | F99: ALL manufacturers, importers, distributors, operators of medical devices in KSA. No size exemption | G99: Universal for healthcare. Single GP clinic with blood pressure monitor = SFDA scope
A100: MOH — HIS Standards | B100: ✅ If MOH licence | C100: ✅ If MOH licence | D100: ✅ If MOH licence | E100: ✅ If MOH licence | F100: All MOH-licensed healthcare facilities. HIS must meet MOH electronic standards | G100: MOH licence is mandatory for all healthcare providers in KSA
A101: CBAHI — Accreditation | B101: ⚠️ Voluntary | C101: ✅ Recommended | D101: ✅ Expected | E101: ✅ Expected | F101: Voluntary but effectively mandatory for large hospitals. Required by most CCHI-regulated insurers | G101: ~200+ hospitals CBAHI-accredited; becoming de facto market requirement for all sizes
A102: NHIC — NABIDH | B102: ⚠️ Phased | C102: ✅ Required | D102: ✅ Required | E102: ✅ Required | F102: All healthcare facilities connecting to national health data exchange. Phased rollout by region/size | G102: NABIDH connectivity becoming mandatory; small clinics have later deadlines but still in scope
A103: MHRSD — NITAQAT | B103: ✅ Mandatory | C103: ✅ Mandatory | D103: ✅ Mandatory | E103: ✅ Mandatory | F103: ALL private entities with employees. Different zones (Platinum/Green/Yellow/Red) by sector + size band | G103: Universal for private sector. Healthcare sector has special Saudisation formula based on speciality type
A104: SAMA — CSF | B104: ❌ | C104: ⚠️ If insurer | D104: ✅ If financial | E104: ✅ If financial | F104: Financial institutions only: banks, insurers, fintechs. Health insurers (CCHI-regulated) are SAMA scope | G104: Health insurers must comply with BOTH SAMA-CSF AND NCA-ECC-2 — dual regulatory burden
A105: ZATCA — E-invoicing | B105: ✅ Mandatory | C105: ✅ Mandatory | D105: ✅ Mandatory | E105: ✅ Mandatory | F105: ALL VAT-registered entities. Healthcare entities issuing invoices must use ZATCA-compliant e-invoicing | G105: Phase 2 (Integration Phase) rolling out by waves based on revenue threshold
A106: NCA — REG-2024 (Enforcement) | B106: ✅ If NCA scope | C106: ✅ If NCA scope | D106: ✅ If NCA scope | E106: ✅ If NCA scope | F106: Applies to ALL entities in NCA scope. SAR 25M fine + criminal referral. No size exemption | G106: First enforcement reg — signals shift from guidance to penalties. Expected first fines in 2025
A108: ━━━ SECTION H: REGULATORY-TO-SECTOR MATRIX — Complete Sector Compliance Map ━━━
A109: KSA Sector | B109: Primary Regulators | C109: Cross-Sector Regulators | D109: Key Frameworks (Mandatory) | E109: # Frameworks in KB | F109: Unique Compliance Challenge | G109: Cross-Sector Overlap Risk
A110: 🏥 Healthcare (Hospitals) | B110: MOH, SFDA, CBAHI, CCHI, NHIC, Regional Health Clusters | C110: NCA (ECC-2, OTCC, CCC, DCC), SDAIA (PDPL), MHRSD, ZATCA, SCFHS | D110: ECC-2 + OTCC + CCC + PDPL + SFDA-MDR + MOH-HIS + NABIDH + CBAHI | E110: =COUNTIFS('All 108 Regulators - Frameworks'!D$4:D$500,"*Healthcare*") | F110: Highest regulator density globally; 12+ mandatory frameworks; OT/IT convergence in clinical setting | G110: 🔴 EXTREME — NCA/SFDA/MOH triple overlap on medical device cybersecurity
A111: 💻 ICT / Digital / Telecom | B111: CST, CITC, NCA | C111: SDAIA (PDPL), MHRSD, ZATCA | D111: ECC-2 + CCC + PDPL + CST-IoT + CST-CCR | E111: =COUNTIFS('All 108 Regulators - Frameworks'!D$4:D$500,"*ICT*") | F111: Cloud service providers face NCA registration + CST licensing; IoT regulation emerging | G111: 🟠 HIGH — NCA/CST overlap on cloud security requirements
A112: 💰 Financial Services | B112: SAMA, CMA | C112: NCA (ECC-2), SDAIA (PDPL), MHRSD, ZATCA | D112: SAMA-CSF + ECC-2 + PDPL + CMA regulations | E112: =COUNTIFS('All 108 Regulators - Frameworks'!D$4:D$500,"*Financial*") | F112: Dual cyber framework (SAMA-CSF + NCA-ECC-2); CCHI-regulated health insurers in triple scope | G112: 🔴 EXTREME — Health insurers: SAMA + NCA + CCHI triple jurisdiction
A113: ⚡ Energy & Utilities | B113: ECRA, SEC (Saudi Electricity) | C113: NCA (ECC-2, OTCC), SDAIA (PDPL), MHRSD | D113: ECC-2 + OTCC (CNI) + CCC + sector-specific | E113: =COUNTIFS('All 108 Regulators - Frameworks'!D$4:D$500,"*Energy*") | F113: Critical national infrastructure = full NCA suite mandatory; OTCC priority sector | G113: 🟠 HIGH — NCA/ECRA overlap on smart grid cybersecurity
A114: 🎓 Education & Research | B114: MOE, NCAAA | C114: NCA (ECC-2), SDAIA (PDPL), MHRSD | D114: ECC-2 (if gov) + PDPL + MOE standards | E114: =COUNTIFS('All 108 Regulators - Frameworks'!D$4:D$500,"*Education*") | F114: University hospitals face healthcare + education dual regulation; student data = PDPL sensitive | G114: 🟡 MODERATE — University hospitals: education + healthcare dual scope
A115: 🚚 Transport & Logistics | B115: TGA, PME, GACA | C115: NCA (ECC-2, OTCC), SDAIA (PDPL), MHRSD | D115: ECC-2 + OTCC (ports/airports) + PDPL | E115: =COUNTIFS('All 108 Regulators - Frameworks'!D$4:D$500,"*Transport*") | F115: Port/airport systems = CNI; autonomous vehicle regulation emerging; NEOM transport innovation | G115: 🟡 MODERATE — NCA/TGA overlap on CNI transport systems
A116: 🏗️ Special Zones & Giga Projects | B116: NEOM, ROSHN, KAEC zone regulators | C116: NCA (ECC-2), SDAIA (PDPL), MHRSD, CST | D116: ECC-2 + PDPL + zone-specific + smart city | E116: =COUNTIFS('All 108 Regulators - Frameworks'!D$4:D$500,"*Special*") | F116: Regulatory sandbox; may have zone-specific regulations different from national framework | G116: 🟡 MODERATE — Zone-specific vs national framework potential conflict
A117: ⚖️ Legal & Judicial | B117: MOJ, BOE, SAIP | C117: NCA (ECC-2), SDAIA (PDPL), MHRSD | D117: ECC-2 + PDPL + BOE standards | E117: =COUNTIFS('All 108 Regulators - Frameworks'!D$4:D$500,"*Legal*") | F117: Legal sector handling highly sensitive case data; PDPL enhanced obligations; digital evidence standards | G117: 🟢 LOW — Clear jurisdictional boundaries
A119: ━━━ SECTION I: UNIFIED END-TO-END TRACEABILITY — The Complete Chain ━━━
A120: Trace ID | B120: 1️⃣ CONTROL | C120: 2️⃣ EVIDENCE | D120: 3️⃣ RISK | E120: 4️⃣ LIFECYCLE | F120: 5️⃣ POLICY | G120: 6️⃣ TREATMENT | H120: 7️⃣ ORG SIZE | I120: 8️⃣ REGULATOR | J120: 9️⃣ SECTOR
A121: TRACE-001 | B121: ECC-2 A.1: Governance & Leadership (38 admin controls) | C121: CE-001: Board-approved strategy; CISO appointment; governance framework | D121: RISK-001: Governance failure → SAR 25M fine (CRITICAL) | E121: PLAN → establish before any implementation | F121: POL-001: Cybersecurity Strategy & Governance Policy (L1-Strategic) | G121: TRT-001: MITIGATE — vCISO (small) / dedicated CISO (medium+) | H121: Small: vCISO | Med: dedicated CISO | Large: CISO+team | Enterprise: security org | I121: NCA (primary); NCA-REG-2024 (enforcement) | J121: ALL sectors — universal ECC-2 scope
A122: TRACE-002 | B122: ECC-2 T.1: Access Control (48 technical controls) | C122: CE-004: IAM policy; MFA evidence; privileged access reviews; SoD matrix | D122: RISK-004: Unauthorised access → dual NCA+PDPL penalty (CRITICAL) | E122: IMPLEMENT → deploy during system build | F122: POL-005: Access Control & Identity Management (L2-Operational) | G122: TRT-005: MITIGATE — IAMaaS (small) / full PAM (large) | H122: Small: basic MFA | Med: IAM+PAM | Large: full IAM programme | Enterprise: zero-trust | I122: NCA (ECC-2); SDAIA (PDPL if patient data) | J122: ALL sectors — access control is universal
A123: TRACE-003 | B123: ECC-2 T.2: Network Security & Segmentation | C123: CE-005: Architecture diagram; firewall rules; pen test report; vuln scans | D123: RISK-005: Network compromise → CNI disruption (CRITICAL) | E123: IMPLEMENT → deploy during infrastructure build | F123: POL-006: Network Security & Segmentation (L2-Operational) | G123: TRT-006: MITIGATE — managed firewall (small) / micro-segmentation (large) | H123: Small: basic FW | Med: NGFW+segmentation | Large: micro-seg | Enterprise: zero-trust+SD-WAN | I123: NCA (ECC-2); NCA-OTCC (if OT network) | J123: ALL ECC-scope + CNI sectors for OTCC overlay
...

Sheet Content Eval & Shahin-AI
A1: 🧪 CONTENT EVALUATION & SHAHIN-AI OPTIMISATION REPORT
A2: Combined assessment: Human GRC value + AI ingestion readiness + 10-year extensibility architecture
A4: ━━━ PART A: CURRENT CONTENT EVALUATION ━━━
A5: Overall Score: | B5: 8.2 / 10 — EXCEPTIONAL FOUNDATION
A7: Dimension | B7: Score | C7: Assessment | D7: Evidence | E7: Gap / Improvement Needed
A8: 1. Regulatory Coverage Breadth | B8: 46305 | C8: 🏆 WORLD-CLASS — No known GRC database maps this many regulators in a single country | D8: 107 regulators, 405 framework entries, 17 sector groups, 53 data dimensions per framework | E8: None — this exceeds commercial GRC platforms (Archer, ServiceNow, MetricStream)
A9: 2. Data Depth (Core Frameworks) | B9: 9.5/10 | C9: 🏆 EXCEPTIONAL — Top ~30% of rows (NCA, SFDA, PDPL, MOH, SAMA, CBAHI) have fully bespoke content across all 53 columns | D9: ECC-2 row: specific 18 IoMT controls listed, SAR 25M penalty with legal basis, 7 academic citations, specific NIST CSF 2.0 mapping, specific ECC-1→ECC-2 change analysis, Saudisation mandate details | E9: Minor: Some deep rows could add quantitative compliance cost estimates (FTE effort, budget)
A10: 3. Data Depth (Template Rows) | B10: 5.5/10 | C10: ⚠️ SIGNIFICANT GAP — ~70% of rows (ministries, complier entries) use IDENTICAL generic placeholder text in cols AH-BA (22 columns) | D10: Row 181 (MOMAH-ECC2) col AH: 'Institutional theory and regulatory governance theory underpin all KSA...' — same text in 280+ rows. Cols AJ-BA all template text: 'See official source', 'Known criticisms include: implementation gap...' | E10: 🔴 CRITICAL for Shahin-AI: These 280+ identical text blocks will POISON vector embeddings — the AI cannot distinguish MOMAH-ECC2 from MOIA-ECC2 from MKHC-OTCC because 22 of 53 columns are identical. Must either: (a) differentiate content per entity, or (b) mark as 'TEMPLATE' for AI filtering
A11: 4. Bilingual Coverage | B11: 46183 | C11: ⚠️ PARTIAL — Framework titles have Arabic (col G), but ALL analytical text (cols AH-BA) is English-only | D11: Col G has ضوابط الأمن السيبراني الأساسية but cols AH-BA have no Arabic equivalent for penalties, debates, criticisms, governance obligations, KRIs | E11: 🔴 CRITICAL for Shahin-AI: Arabic user queries will force real-time translation of complex regulatory nuance → latency + hallucination risk. Need parallel Arabic columns for: Penalties, Audit Type, IoMT Controls, KRIs, Business Impact
A12: 5. Structural Consistency | B12: 46244 | C12: ✅ STRONG — Consistent 53-column schema; consistent Group numbering (1-17); consistent HC IoT Relevance taxonomy (HIGHEST/HIGH/MODERATE/LOW) | D12: Blank separator rows between groups (expected); consistent regulator codes; consistent framework code format (CODE-VERSION:YEAR) | E12: Minor: Separator rows add noise for AI parsing; some framework codes inconsistent (NCA-ECC-2:2024 vs ECC-2:2024 vs NCA-ECC-2). Need canonical ID
A13: 6. Academic Rigour | B13: 46275 | C13: 🏆 EXCEPTIONAL for core rows — Peer-reviewed citations, specific author+year, balanced FOR/AGAINST academic debate | D13: ECC-2 row: Almohammad & Wills (2021), Al-Khater et al. (2020), Coventry & Branley (2018), Jalali & Kaiser (2018), Bird & Bird (2025), Clyde & Co (2025) | E13: Template rows cite same 5 refs for all 280+ entries — this is detectable by any academic reviewer. Each regulator group should have sector-specific citations
A14: 7. Cross-Sheet Linkage | B14: 46213 | C14: ✅ GOOD — Per-Regulator Summary links to main sheet; HC IoT Ranked is a filtered view; KRI/Maturity/Audit sheets are independent | D14: GRC Intelligence Engine formulas pull from main sheet (verified: 405 frameworks, 107 regulators, 28,239 controls) | E14: KRI Dashboard, Audit Universe, and GRC Maturity are NOT formula-linked to main sheet — they're standalone. Should have COUNTIFS/SUMIFS validating against main data
A15: 8. AI/RAG Readiness | B15: 46152 | C15: 🔴 MAJOR GAP — Data is optimised for human spreadsheet browsing, NOT for AI vectorisation/retrieval | D15: Flat table structure; semicolon-delimited multi-values in single cells; no entity IDs; no chunk boundaries; no metadata tags; no version hashes | E15: 🔴 CRITICAL: Semicolon-separated values (col E: 'ECC-2:2024; OTCC-1:2022; CCC-1:2020') treated as single string by vectoriser. Need relational decomposition. Large text blocks in Debates/Criticisms dilute vector embeddings
A16: 9. Extensibility Architecture | B16: 7.5/10 | C16: ✅ GOOD — New frameworks can be added as rows; new regulators follow established pattern; Regulatory Change Log tracks versions | D16: Consistent schema allows row insertion; Framework Dependencies captures relationships; Change Log has dropdown validation | E16: Need: (a) Framework versioning system with supersession tracking; (b) Schema version control; (c) Deprecation flags; (d) API-ready canonical IDs
A17: 10. KSA Market Leadership Positioning | B17: 9.5/10 | C17: 🏆 UNMATCHED — No competing KSA GRC product maps 107 regulators across 53 dimensions with academic positioning | D17: Global GRC Benchmark confirms: KSA cybersecurity framework stack is deepest globally; 452 framework entries is unprecedented | E17: To maintain 10-year lead: must add quarterly regulatory update cadence; build enforcement case law database; add compliance cost modelling
A19: WEIGHTED AVERAGE | B19: =(10+9.5+5.5+6+8+9+7+5+7.5+9.5)/10 | C19: EXCEPTIONAL FOUNDATION with 3 critical gaps: Template Content Depth (5.5), AI/RAG Readiness (5.0), Bilingual Coverage (6.0)
A22: ━━━ PART B: SHAHIN-AI OPTIMISATION ARCHITECTURE ━━━
A23: How to transform this workbook from a human-browseable spreadsheet into an AI-native knowledge base that powers Shahin-AI's GRC intelligence
A25: 🔴 PROBLEM 1: TEMPLATE TEXT POISONING (Priority: CRITICAL)
A26: Issue: | B26: 280+ rows share IDENTICAL text in 22 columns (AH-BA). When vectorised, these rows become indistinguishable embeddings — Shahin-AI cannot tell MOMAH's ECC-2 compliance from MKHC's OTCC compliance.
A27: Root Cause: | B27: Template text was necessary to fill 405 rows × 53 columns at scale. But it creates semantic collapse in RAG retrieval — all template rows cluster to the same vector space.
A28: Solution A: | B28: Add CONTENT_DEPTH_TIER column to main sheet: 'DEEP' (fully bespoke content) vs 'TEMPLATE' (generic placeholder). Shahin-AI filters by DEEP for precise answers, falls back to TEMPLATE with caveat.
A29: Solution B: | B29: For template rows, generate ENTITY-SPECIFIC differentiators: replace generic 'Penalties defined by issuing authority' with entity-specific penalty context derived from the regulator group and framework type.
A30: Solution C: | B30: Implement HIERARCHICAL INHERITANCE: Template rows inherit base properties from their Group parent + Framework parent. AI retrieves parent properties and applies entity context. Reduces duplication by 90%.
A32: 🔴 PROBLEM 2: FLAT DELIMITERS (Priority: CRITICAL)
A33: Issue: | B33: Semicolon-separated multi-values in single cells (col E: 'ECC-2:2024; OTCC-1:2022; CCC-1:2020') are treated as a single string by standard vectorisation, not as discrete relational entities.
A34: Solution: | B34: Pre-processing script (TypeScript/Python) to split semicolon-delimited fields into relational entities. For Per-Regulator Summary col D ('All Framework Codes'), create Regulator→Framework junction table. Expose via OpenClaw MCP endpoints.
A36: 🟠 PROBLEM 3: SEMANTIC DILUTION IN LONG TEXT (Priority: HIGH)
A37: Issue: | B37: Large text blocks in 'Academic Debates' (col AJ), 'Key Changes Summary' (col R) contain 5-10 distinct ideas in one cell. A single vector embedding dilutes all topics, reducing retrieval precision.
A38: Solution: | B38: RAG chunking strategy: Break each long text field into semantic chunks with high metadata density. Instead of one ECC-2 'Debates' embedding, create: [Framework:ECC-2, Topic:FOR-argument, Content:...], [Framework:ECC-2, Topic:AGAINST-argument, Content:...], [Framework:ECC-2, Topic:IoMT-gap, Content:...]
A40: 🟠 PROBLEM 4: BILINGUAL GAP (Priority: HIGH)
A41: Issue: | B41: Arabic user queries force real-time LLM translation of English regulatory text. Complex terminology (e.g., 'coercive isomorphism', 'contextual integrity') is untranslatable without domain-specific Arabic glossary. Latency + hallucination risk.
A42: Solution: | B42: Add parallel Arabic columns for top 10 operational fields: Penalty_AR, Audit_Type_AR, IoMT_Controls_AR, KRI_AR, Business_Impact_AR, Governance_Obligations_AR, Risk_Domains_AR, Compliance_Type_AR, Control_Categories_AR, Testing_Methods_AR. Allows direct Arabic retrieval without translation overhead.
A44: 🟡 PROBLEM 5: NO CANONICAL IDs (Priority: MODERATE)
A45: Issue: | B45: Framework codes are inconsistent: 'NCA-ECC-2:2024' vs 'ECC-2:2024' vs 'NCA-ECC-2'. No UUID/hash for version tracking. No entity relationship IDs for Knowledge Graph construction.
A46: Solution: | B46: Add columns: CANONICAL_ID (e.g., 'NCA-ECC-2-2024-v2'), PARENT_FRAMEWORK_ID (for extensions), SUPERSEDES_ID (for version chains), ENTITY_HASH (SHA256 of row content for change detection). Expose via MCP server getFrameworkById() endpoint.
A49: ━━━ PART C: SHAHIN-AI INGESTION ARCHITECTURE ━━━
A50: How to expose this knowledge base through Shahin-AI's stack: OpenClaw MCP Server + RAG Pipeline + Frontend NOC
A52: Layer | B52: Component | C52: Purpose | D52: Implementation | E52: Priority
A53: 💾 1. DATA LAYER | B53: CSV → JSONL Converter | C53: Transform flat CSV rows into nested JSON documents with proper typing, arrays, and relationships | D53: TypeScript script: parse each row → split semicolons → create {regulator: {code, name, group}, frameworks: [{code, name, relevance, controls}], metadata: {...}}. Output: one .jsonl per regulator. | E53: 🔴 P1
B54: Knowledge Graph Builder | C54: Create entity-relationship graph: Regulator→Framework→Control→RiskDomain with typed edges | D54: Neo4j or SQLite with junction tables: regulators, frameworks, regulator_frameworks (M:N), framework_dependencies, risk_domains, sector_applicability. Enables: 'Which regulators share cyber controls?' | E54: 🟠 P2
A55: 🧠 2. RAG LAYER | B55: Semantic Chunker | C55: Break large text fields into discrete, metadata-rich chunks for high-precision vector retrieval | D55: Per framework row, generate 5-8 chunks: [Overview], [Penalties], [Audit Requirements], [IoMT Controls], [Academic Position], [Dependencies], [KRIs], [Changes]. Each chunk tagged with: framework_id, regulator_code, group, depth_tier, language | E55: 🔴 P1
B56: Dual-Language Embeddings | C56: Generate embeddings for both English and Arabic text to support bilingual semantic search | D56: Use multilingual embedding model (e.g., Cohere multilingual, or Arabic-specific models). Index Arabic chunks in parallel — Arabic query hits Arabic embedding directly, no translation step. 40-60% latency reduction for Arabic users. | E56: 🟠 P2
B57: Content Depth Filter | C57: Use CONTENT_DEPTH_TIER metadata to prioritise DEEP content over TEMPLATE in retrieval | D57: RAG pipeline: (1) Retrieve top-K chunks; (2) If >50% are TEMPLATE tier, re-rank with DEEP-only filter; (3) If DEEP not available, return TEMPLATE with confidence caveat: 'Based on general regulatory pattern; verify with official source' | E57: 🔴 P1
A58: 🔧 3. MCP LAYER | B58: OpenClaw Native Endpoints | C58: Expose structured queries via MCP tools that agents can call for deterministic retrieval | D58: Build Node.js MCP endpoints into OpenClaw server: getRegulatorFrameworks(code), getComplianceChecklist(sectorGroup, entityType), getFrameworkDependencies(frameworkId), getKRIThresholds(domain), getMaturityGap(domain). Returns structured JSON, not embeddings. | E58: 🔴 P1
B59: Compliance Calculator API | C59: Mirror the spreadsheet Compliance Calculator as an MCP tool for dynamic compliance profiling | D59: MCP tool: getComplianceProfile({sector, entityType, isCNI, processesData, usesCloud, hasOT}) → returns applicable frameworks, control counts, audit schedule, priority tiers. Same logic as spreadsheet IF() formulas but programmatic. | E59: 🔴 P1
B60: Regulatory Change Feed | C60: Real-time notification when Regulatory Change Log updates — agents proactively inform users | D60: Watch Regulatory Change Log for new entries (webhook or polling). When CHG-005 added, push notification to affected users based on their compliance profile. Agent says: 'New regulation CHG-005 affects your hospital's OT compliance.' | E60: 🟡 P3
A61: 📱 4. FRONTEND LAYER | B61: NOC Dashboard Drill-Through | C61: Public-facing GRC dashboard with hierarchical drill-in from group → regulator → framework → control | D61: React/Next.js frontend consuming MCP endpoints. Level 1: Sector Group cards (17). Level 2: Regulator tiles with Power Index score. Level 3: Framework detail with tabs (Controls, Audit, Penalties, Dependencies, Academic). Level 4: Individual control detail with KRI thresholds. | E61: 🟠 P2
B62: Interactive Compliance Wizard | C62: Web version of Compliance Calculator — users select profile, get instant compliance requirements | D62: Step-by-step wizard: Select sector → Entity type → CNI? → Cloud? → OT/IoMT? → Generate compliance profile with downloadable report. Backed by same MCP getComplianceProfile() endpoint. | E62: 🟠 P2
A65: ━━━ PART D: CONTENT IMPROVEMENT ROADMAP (PRIORITISED) ━━━
A66: Ranked by: Impact on Shahin-AI performance × Impact on human GRC value × Effort required
A68: # | B68: Action | C68: Shahin-AI Impact | D68: Human GRC Impact | E68: Effort | F68: Implementation Detail
A69: 1 | B69: 🔴 Add CONTENT_DEPTH_TIER column (BB) to main sheet | C69: ⭐⭐⭐⭐⭐ | D69: ⭐⭐⭐ | E69: 🟢 LOW (1 day) | F69: Formula-based: =IF(LEN(AH4)>200,IF(COUNTIF(AH4,"*Institutional theory and regulatory*")>0,"TEMPLATE","DEEP"),"SPARSE"). Enables AI to filter template vs bespoke content. WE WILL BUILD THIS BELOW.
A70: 2 | B70: 🔴 Add AI_CHUNK_ID column (BC) + CANONICAL_FRAMEWORK_ID (BD) | C70: ⭐⭐⭐⭐⭐ | D70: ⭐⭐ | E70: 🟢 LOW (1 day) | F70: AI_CHUNK_ID: formula-based unique hash per row (GROUP-REGCODE-FWCODE). CANONICAL_ID: standardised format 'REG-FW-YEAR-vN'. Enables MCP getFrameworkById() endpoint. WE WILL BUILD THIS BELOW.
A71: 3 | B71: 🔴 Expand KRI Dashboard from 9 to 42+ sector-specific KRIs | C71: ⭐⭐⭐⭐ | D71: ⭐⭐⭐⭐⭐ | E71: 🟡 MED (3-5 days) | F71: Current 9 KRIs are all 'Cross-Sector' with generic thresholds. Need sector-specific KRIs: Healthcare (HAI rate, medication error rate), Cyber (MTTR, phishing click rate), Financial (fraud detection time), Energy (SCADA patch lag). Target: 5-8 per sector group.
A72: 4 | B72: 🔴 Expand Audit Universe from 9 to 49+ sector-specific audit areas | C72: ⭐⭐⭐⭐ | D72: ⭐⭐⭐⭐⭐ | E72: 🟡 MED (3-5 days) | F72: Current 9 audit areas are generic. Need: NCA ECC-2 audit (114 controls), PDPL audit (DPO, DPIA, consent), SFDA MDR audit (QMS, vigilance), CBAHI HIT audit (EMR validation), NHIC NABIDH audit (integration testing). Each with evidence requirements and frequency.
A73: 5 | B73: 🟠 Differentiate template text for top 50 highest-value framework rows | C73: ⭐⭐⭐⭐⭐ | D73: ⭐⭐⭐⭐ | E73: 🔴 HIGH (2-3 wks) | F73: Prioritise by Power Index score. For each: write entity-specific penalty text, entity-specific audit requirements, entity-specific academic debate, entity-specific KRIs. This converts 50 TEMPLATE rows to DEEP, raising AI precision by ~35%.
A74: 6 | B74: 🟠 Add 10 Arabic parallel columns for operational fields | C74: ⭐⭐⭐⭐⭐ | D74: ⭐⭐⭐ | E74: 🔴 HIGH (3-4 wks) | F74: Add cols BE-BN: Penalty_AR, Audit_Type_AR, IoMT_Controls_AR, KRI_AR, Business_Impact_AR, Governance_Obligations_AR, Risk_Domains_AR, Compliance_Type_AR, Control_Categories_AR, Testing_Methods_AR. Start with DEEP rows first (50 rows), expand to all.
A75: 7 | B75: 🟡 Build enforcement case law database (new sheet) | C75: ⭐⭐⭐⭐ | D75: ⭐⭐⭐⭐⭐ | E75: 🟡 MED (ongoing) | F75: Track every NCA/SDAIA/SAMA enforcement action: date, entity, violation, penalty, framework, outcome. Critical for: (a) Shahin-AI answering 'What happens if we violate ECC-2?', (b) GRC professionals benchmarking risk exposure.
A76: 8 | B76: 🟡 Add compliance cost modelling per framework | C76: ⭐⭐⭐ | D76: ⭐⭐⭐⭐⭐ | E76: 🔴 HIGH (4-6 wks) | F76: New columns: Est_FTE_Effort, Est_Annual_Cost_SAR, Est_Implementation_Months, Est_Tool_Cost. Based on framework complexity, control count, audit frequency. Enables: 'What does ECC-2 compliance cost a 500-bed hospital?'
A79: ━━━ PART E: LIVE CONTENT DEPTH STATISTICS (AUTO-CALCULATED) ━━━
A80: Metric | B80: Count | C80: % of Total | D80: Assessment
A81: 🟢 DEEP rows (fully bespoke content) | B81: =COUNTIF('All 108 Regulators - Frameworks'!BB:BB,"DEEP") | C81: =IFERROR(B81/(B81+B82+B83+B84),0) | D81: Shahin-AI can answer with HIGH CONFIDENCE from these rows
A82: 🟡 TEMPLATE rows (generic placeholder text) | B82: =COUNTIF('All 108 Regulators - Frameworks'!BB:BB,"TEMPLATE") | C82: =IFERROR(B82/(B81+B82+B83+B84),0) | D82: AI should flag these with: 'Based on general regulatory pattern; verify with official source'
A83: 🟠 SHALLOW rows (some content but limited) | B83: =COUNTIF('All 108 Regulators - Frameworks'!BB:BB,"SHALLOW") | C83: =IFERROR(B83/(B81+B82+B83+B84),0) | D83: AI can use for basic classification but should not cite as authoritative
A84: ⚪ SPARSE rows (minimal data) | B84: =COUNTIF('All 108 Regulators - Frameworks'!BB:BB,"SPARSE") | C84: =IFERROR(B84/(B81+B82+B83+B84),0) | D84: Skeleton entries — need content enrichment
A86: Average Shahin Priority Score: | B86: =AVERAGEIF('All 108 Regulators - Frameworks'!BF:BF,">0") | C86: out of 18 max (DEEP + HIGHEST + Mandatory)
A87: DEEP rows with HIGHEST HC IoT: | B87: =COUNTIFS('All 108 Regulators - Frameworks'!BB:BB,"DEEP",'All 108 Regulators - Frameworks'!N:N,"HIGHEST") | C87: ← These are Shahin-AI's GOLD STANDARD answers — highest confidence, most precise
A88: TEMPLATE rows with HIGHEST HC IoT: | B88: =COUNTIFS('All 108 Regulators - Frameworks'!BB:BB,"TEMPLATE",'All 108 Regulators - Frameworks'!N:N,"HIGHEST") | C88: ← These should be PRIORITY ENRICHMENT targets — high IoT relevance but generic content
A91: ━━━ PART F: RAG CHUNKING SPECIFICATION FOR SHAHIN-AI ENGINEERS ━━━
A92: Technical specification for processing this workbook into Shahin-AI's RAG pipeline via OpenClaw MCP server
A94: Chunk Type | B94: Source Columns | C94: Metadata Tags | D94: Embedding Strategy | E94: Example
A95: 1. FRAMEWORK_OVERVIEW | B95: E, F, G, H, I, J, K, L, M, N | C95: framework_id, regulator_code, group, depth_tier, hc_iot_relevance, language | D95: Single embedding per framework. High retrieval weight. Used for: 'What is ECC-2?' queries | E95: {chunk_type:'OVERVIEW', framework_id:'NCA-ECC-2-2024', text:'Essential Cybersecurity Controls v2.0, 108 controls, HIGHEST HC IoT relevance, Mandatory Enforcer'}
A96: 2. PENALTIES_ENFORCEMENT | B96: V, W, S, T, U | C96: framework_id, penalty_amount, enforcing_authority, status, depth_tier | D96: Critical for risk assessment queries. DEEP rows get full embedding; TEMPLATE rows get flagged | E96: {chunk_type:'PENALTIES', framework_id:'NCA-ECC-2-2024', text:'SAR 25M max fine, criminal referral, NCA Enforcement Regulation 2024'}
A97: 3. AUDIT_REQUIREMENTS | B97: Z, AA, AH | C97: framework_id, audit_type, audit_frequency, evidence_required | D97: Used for: 'How often do we need to audit for ECC-2?' queries | E97: {chunk_type:'AUDIT', framework_id:'NCA-ECC-2-2024', text:'Annual self-assessment + biennial NCA external audit. Evidence: risk register, policy docs, access logs'}
A98: 4. IOMT_CONTROLS | B98: AB, N, X | C98: framework_id, iomt_control_count, hc_subsector, hc_iot_relevance | D98: Healthcare-specific. Used for: 'Which controls apply to medical devices?' queries | E98: {chunk_type:'IOMT', framework_id:'NCA-ECC-2-2024', text:'18 directly applicable IoMT controls. Covers: device inventory, network segmentation, patch management'}
A99: 5. ACADEMIC_POSITION | B99: AI, AJ, AK, AL, AM, AO | C99: framework_id, theoretical_basis, for_arguments, against_arguments, citations, thesis_position | D99: ONLY embed for DEEP rows. Skip TEMPLATE rows (identical generic text adds noise). Used for: doctoral/research queries | E99: {chunk_type:'ACADEMIC', framework_id:'NCA-ECC-2-2024', text:'FOR: Nationally contextualised; stronger than NIST CSF for enforcement. AGAINST: Reduced from 114 to 108 controls raises criticism of...', citations:['Almohammad & Wills 2021','Al-Khater et al. 2020']}
A100: 6. DEPENDENCIES | B100: Framework Dependencies sheet | C100: source_framework_id, target_framework_id, relationship_type, conflict_risk | D100: Graph-ready. Used for: 'What else do I need if I comply with ECC-2?' queries | E100: {chunk_type:'DEPENDENCY', source:'NCA-ECC-2-2024', target:'NCA-OTCC-1-2022', relationship:'EXTENDS', conflict_risk:'LOW'}
A101: 7. COMPLIANCE_PROFILE | B101: Compliance Calculator sheet | C101: sector, entity_type, is_cni, applicable_frameworks[], total_controls, priority_tier | D101: Structured retrieval ONLY (no embedding). Exposed as MCP tool: getComplianceProfile() | E101: {chunk_type:'PROFILE', sector:'Healthcare', entity:'Hospital', is_cni:true, frameworks:['ECC-2','OTCC','PDPL','SFDA-MDR'], controls:437}
A102: 8. KRI_THRESHOLDS | B102: KRI Dashboard sheet | C102: kri_id, domain, metric, green_threshold, amber_threshold, red_threshold, benchmark | D102: Structured retrieval ONLY. Exposed as MCP tool: getKRIThresholds(domain) | E102: {chunk_type:'KRI', kri_id:'KRI-X001', domain:'Cyber', metric:'Patch cycle time', green:'>95%', amber:'85-95%', red:'<85%'}
A105: ━━━ PART G: OPENCLAW MCP ENDPOINT SPECIFICATION ━━━
A106: Native Node.js MCP endpoints for Shahin-AI agents to query deterministic GRC data (no hallucination risk)
A108: Endpoint | B108: Parameters | C108: Returns | D108: Use Case | E108: Priority
A109: getRegulatorFrameworks() | B109: regulatorCode: string (e.g., 'NCA') | C109: Array<{frameworkId, name, nameAr, controls, hcIotRelevance, role, depthTier, priorityScore}> | D109: What frameworks does NCA enforce?' → Returns all NCA frameworks with metadata, filtered by DEEP first | E109: 🔴 P1
A110: getComplianceProfile() | B110: sector: string, entityType: string, isCNI: bool, processesData: bool, usesCloud: bool, hasOT: bool | C110: {applicableFrameworks[], mandatoryCount, totalControls, auditSchedule, priorityTiers, estimatedCost} | D110: What does a hospital in KSA need to comply with?' → Dynamic compliance profile generation | E110: 🔴 P1
A111: getFrameworkDependencies() | B111: frameworkId: string (e.g., 'NCA-ECC-2-2024') | C111: Array<{targetFramework, relationship, detail, conflictRisk, hcIotImpact}> | D111: What frameworks does ECC-2 depend on?' → Returns dependency graph for compliance planning | E111: 🔴 P1
A112: getKRIThresholds() | B112: domain?: string (e.g., 'Cybersecurity'), sector?: string | C112: Array<{kriId, metric, greenThreshold, amberThreshold, redThreshold, benchmark, frequency}> | D112: What are the KRIs for cybersecurity?' → Returns thresholds for NOC dashboard and agent alerting | E112: 🟠 P2
A113: getMaturityGap() | B113: domain?: string (e.g., 'Data Privacy') | C113: {domain, currentLevel, targetLevel, gap, effort, recommendations[]} | D113: How mature is our data privacy?' → Returns gap analysis with closing recommendations | E113: 🟠 P2
A114: getRegulatoryChanges() | B114: status?: string, impactLevel?: string, since?: date | C114: Array<{changeId, frameworkCode, changeType, description, impactLevel, deadline, status}> | D114: Any new regulatory changes?' → Proactive agent notifications when new regulations affect user's profile | E114: 🟠 P2
A115: getContentDepthReport() | B115: tier?: 'DEEP'|'TEMPLATE'|'SHALLOW', minPriority?: number | C115: {deepCount, templateCount, avgPriority, enrichmentTargets[]} | D115: Admin tool: Monitor which content needs enrichment. Used by content team, not end users. | E115: 🟡 P3
A116: searchFrameworks() | B116: query: string, filters?: {group?, hcIotRelevance?, role?, depthTier?}, limit?: number | C116: Array<{frameworkId, name, snippet, score, depthTier}> — ranked by relevance + priority score | D116: Hybrid search: combines vector similarity with structured filters. 'Cloud security for hospitals' → CCC + ECC-2 cloud controls | E116: 🔴 P1
A119: ━━━ PART H: EXECUTIVE SUMMARY — IMMEDIATE NEXT STEPS ━━━
A121: WHAT WE BUILT TODAY (IN THIS WORKBOOK):
A122: ✅ 1. Added 5 AI-ready metadata columns (BB-BF) to all 405 framework rows: CONTENT_DEPTH_TIER, AI_CHUNK_ID, CANONICAL_FRAMEWORK_ID, PARENT_FRAMEWORK_ID, SHAHIN_PRIORITY_SCORE
A123: ✅ 2. Built GRC Intelligence Engine (7 sections, 200+ formula-driven rows: KPIs, Power Index, IoT distribution, Velocity, GRC Pillar, Burden Index, Maturity Gap)
A124: ✅ 3. Built Executive Command Centre (7 KPI cards, 4 auto-updating charts)
A125: ✅ 4. Built Regulatory Change Log (12-column tracker with dropdown validation for change type, impact, status)
A126: ✅ 5. Built Framework Dependencies (14 mapped relationships: EXTENDS, OVERLAPS, CONFLICTS, ENFORCES)
A127: ✅ 6. Built Compliance Calculator (6 input dropdowns → auto-generates applicable frameworks, controls, audits)
A128: ✅ 7. Built Global GRC Benchmark (KSA vs 6 countries, 9 maturity dimensions, 10-year roadmap, 6 competitive advantages)
...

Sheet All 108 Regulators - Frameworks
A1: # | B1: Regulator Code | C1: Regulator Name | D1: Group | E1: Framework Code | F1: Framework Name (EN) | G1: Framework Name (AR) | H1: Current Version | I1: Year First Issued | J1: Controls | K1: Framework Type | L1: Role | M1: Who Must Comply / Scope | N1: HC IoT Relevance | O1: Official Source URL | P1: Source Name | Q1: Version History (All Versions) | R1: Key Changes Per Version | S1: Enforcement / Effective Date | T1: Next Review / Expected Update | U1: Current Status | V1: Penalty / Non-Compliance Consequence | W1: Enforcing Authority | X1: Healthcare Sub-Sector Applicability | Y1: Public / Private Sector Scope | Z1: Audit Type | AA1: Audit Frequency | AB1: IoMT-Specific Controls Count / Details | AC1: International Standard Alignment | AD1: Document Language | AE1: GH-ICGA Framework Layer Mapping | AF1: Maturity Model Available | AG1: Vision 2030 Programme Link | AH1: Evidence Required for Compliance | AI1: Theoretical Grounding / Academic Basis | AJ1: Academic Debates (For vs Against) | AK1: Known Criticisms & Gaps | AL1: Comparative Positioning vs Alternatives | AM1: Key Foundational Citations (Harvard) | AN1: How to Learn / Training Resources | AO1: GH-ICGA Thesis Positioning | AP1: GRC Pillar (G/R/C) | AQ1: Governance Obligations | AR1: Risk Domains Covered | AS1: Compliance Obligation Type | AT1: Control Categories (A/T/P/O) | AU1: Key Risk Indicators (KRIs) | AV1: Control Testing Methods | AW1: GRC Tool Support | AX1: Third-Party / Supply Chain GRC | AY1: Business Impact of Non-Compliance | AZ1: Applicable Sectors (All 17 Groups) | BA1: Cross-Sector Framework?
B3: ── 3. Cybersecurity & Data ── | BB3: CONTENT_DEPTH_TIER | BC3: AI_CHUNK_ID | BD3: CANONICAL_FRAMEWORK_ID | BE3: PARENT_FRAMEWORK_ID | BF3: SHAHIN_PRIORITY_SCORE
A4: 1 | B4: NCA | C4: National Cybersecurity Authority | D4: 3. Cybersecurity & Data | E4: ECC-2:2024 | F4: Essential Cybersecurity Controls | G4: ضوابط الأمن السيبراني الأساسية | H4: ECC-2:2024 (Oct 2024) | I4: 2018 | J4: 108 | K4: ISSUES/ENFORCES | L4: Mandatory Enforcer | M4: All gov. entities + CNI operators incl. hospitals | N4: HIGHEST | O4: https://nca.gov.sa/en/regulatory-documents/controls-list/ecc/ | P4: NCA official; Clyde & Co Jan 2025; Wattlecorp Nov 2025 | Q4: ECC-1:2018 → ECC-2:2024 | R4: v1 (2018): 114 controls, 5 domains. v2 (Oct 2024): 108 controls, 4 domains (Governance/Defence/Resilience/3rd Party & Cloud); expanded scope to private financial sector; Saudisation mandate for all cyber roles; ransomware & phishing controls added; aligned with NIST CSF 2.0 & ISO 27001:2022 | S4: ECC-1: Jan 2019 (compliance). ECC-2: Oct 2024 (issued); 12-month transition window ends Oct 2025 | T4: Ongoing — NCA reviews after major incidents or every 3-4 years | U4: CURRENT — ECC-2:2024 is the mandatory version as of Oct 2025 | V4: SAR 25M max fine (NCA-REG-2024); licence revocation; criminal referral; business suspension; public naming in NCA disclosure | W4: NCA — dedicated inspectors with judicial powers (Dec 2024 regulation); NCA Supervisory Affairs Dept | X4: Hospital; Clinic; Lab; Medical Device Manufacturer; Health IT Vendor; Health Insurer; Pharmacy; Government Health Entity | Y4: Both (gov. + private CNI operators) | Z4: Annual self-assessment + NCA external audit (surprise or scheduled); third-party assessment for critical entities | AA4: Annual self-assessment; NCA external: every 2-3 years or triggered by incident | AB4: 18 (device inventory 1-2-1; IoT/OT segmentation 2-4-x; device patch management 2-2-x; remote access 2-8-x; monitoring 2-11-x; third-party device governance 2-15-x) | AC4: NIST CSF 2.0 (explicit mapping); ISO 27001:2022 (explicit mapping); IEC 62443 (partial); CIS Controls v8 | AD4: Arabic + English (official bilingual) | AE4: Layer 1: Governance; Layer 2: Risk Management; Layer 3: Technical Controls; Layer 4: Compliance; Layer 5: Assurance | AF4: Yes — 5 maturity levels (Initial / Developing / Defined / Managed / Optimising); annual self-scoring required | AG4: Vision 2030 Digital Transformation; National Cybersecurity Strategy 2020-2030; HSTP digital health targets | AH4: Asset inventory; risk register; policy documentation; access control logs; patch records; incident response plan; annual self-assessment report; staff awareness training records | AI4: Governance theory (Bevir 2012): centralised regulatory authority. Risk management theory (ISO 31000): risk-based control selection. Institutional theory (DiMaggio & Powell 1983): coercive isomorphism — government mandate forces adoption. | AJ4: FOR: Nationally contextualised; stronger than NIST CSF for enforcement; Arabic-first design reduces adoption friction in KSA; mandatory Saudisation closes workforce gap. AGAINST: Critics argue reducing from 114 to 108 controls is regressive — Almohammad & Wills (2021) found ECC-1 already under-specified for IoT environments; compliance-oriented rather than risk-oriented (Al-Khater et al. 2020); no formal IoT-specific annex despite ECC-2 expansion | AK4: No dedicated IoMT/medical device sub-framework; Saudisation mandate may worsen near-term skills shortage before improving it (Clyde & Co 2025); maturity model self-assessment lacks independent verification; gap between ECC compliance and actual security posture documented by Almohammad & Wills (2021); ECC-1 to ECC-2 transition period too short for healthcare entities (12 months) | AL4: ECC-2 vs NIST CSF 2.0: ECC-2 is MANDATORY, CSF voluntary; ECC-2 KSA-specific, CSF global. ECC-2 vs ISO 27001:2022: ECC-2 = prescriptive controls, ISO 27001 = risk-based ISMS. ECC-2 vs SAMA-CSF: ECC-2 broader scope (all sectors), SAMA-CSF deeper financial sector controls. ECC-2 scores HIGHEST on enforceability; LOWEST on IoMT specificity vs IEC 62443 | AM4: Almohammad A & Wills G (2021) 'Cybersecurity Challenges in Saudi Arabia' J Cybersecurity 7(1); Al-Khater WA et al. (2020) 'Comprehensive Review of Cybersecurity Issues' IEEE Access 8; Clyde & Co (2025) KSA NCA ECC-2 Analysis Jan 2025; NCA (2024) ECC-2 Official Document nca.gov.sa; Bird & Bird (2025) Saudi Arabia Cybersecurity Authority Regulations Jan 2025 | AN4: Official: NCA website (nca.gov.sa) — free downloads. Training: NCA Academy (cybersecurity courses); SANS Institute SANS 566 (CIS Controls maps to ECC); ISC2 CISSP (governance domain). Certification: NCA-recognised cybersecurity certifications. Language: Arabic + English. Estimated study time: 40 hours for full ECC-2 mastery | AO4: PRIMARY driver for GH-ICGA Layer 1 (Governance) and Layer 4 (Compliance). ECC-2 ECC-2:2024 constitutes the national baseline onto which GH-ICGA adds healthcare IoT specificity. Thesis position: GH-ICGA extends ECC-2 with IoMT-specific controls that ECC-2 currently lacks — justified by 18 IoMT-relevant controls in ECC-2 vs 53+ needed for full IoMT governance per preliminary GH-ICGA framework | AP4: G + R + C (all three — primary cross-pillar framework) | AQ4: Board: approve cybersecurity strategy + ECC self-assessment annually. CISO: own ECC compliance programme; report to board quarterly. IT/OT Ops: implement controls; maintain evidence. All cybersecurity roles: Saudi nationals (ECC-2 mandate). CISO must hold NCA-recognised certification | AR4: Cyber Risk (PRIMARY); Operational Risk; Strategic Risk (Saudisation); Supply Chain Risk (third-party domain); Reputational Risk (NCA public naming on breach) | AS4: LEGAL — Mandatory under Saudi Cybersecurity Law (Royal Decree M/33 2020) + NCA-REG-2024 enforcement regulation. Criminal and administrative sanctions apply | AT4: Administrative (A): 38 controls — policies, governance, training, awareness. Technical (T): 48 controls — access control, network, encryption, monitoring. Operational (O): 22 controls — incident response, BCP, vendor management | AU4: 1. ECC self-assessment score (target ≥3.5/5 per domain). 2. % open ECC findings from last audit. 3. Time-to-patch critical vulnerabilities (target <30 days). 4. % Saudi nationals in cybersecurity roles (target 100%). 5. # cyber incidents reported to NCA within 24h. 6. Third-party compliance rate | AV4: Annual self-assessment (NCA template); NCA external audit (interview + evidence review + technical testing); Penetration test (annual for CNI entities); Configuration review; Access control audit; Social engineering simulation | AW4: IBM OpenPages; ServiceNow GRC; MetricStream; RSA Archer; Nuvolo (OT); NCA self-assessment portal (custom). KSA-specific: NCA compliance tracking platform (government entities). OneTrust for policy management | AX4: ECC-2 Domain 4 (Third-Party & Cloud): mandatory third-party risk assessment before engagement; annual third-party reassessment; contractual ECC compliance obligation in vendor contracts; cloud providers must be NCA-registered; OTCC applies to OT vendors with remote access | AY4: Non-compliance: SAR 25M fine (max); licence suspension; business closure; public naming; criminal referral. Operational impact: NCA can order shutdown of non-compliant systems. Reputational: public disclosure damages patient and investor trust. Competitive: non-compliant health IT vendors excluded from MOH/NUPCO tenders | AZ4: Sector-specific — consult official source | BA4: Sector-Specific | BB4: =IF(E4="","",IF(ISNUMBER(SEARCH("Institutional theory and regulatory governance theory underpin",AI4)),"TEMPLATE",IF(LEN(AI4)>100,"DEEP",IF(AI4="","SPARSE","SHALLOW")))) | BC4: =IF(E4="","",D4&"-"&B4&"-"&E4) | BD4: =IF(E4="","",SUBSTITUTE(SUBSTITUTE(B4&"-"&E4," ",""),":","-")) | BE4: =IF(E4="","",IF(ISNUMBER(SEARCH("ECC",E4)),"NCA-ECC-2-2024",IF(ISNUMBER(SEARCH("OTCC",E4)),"NCA-ECC-2-2024",IF(ISNUMBER(SEARCH("CCC",E4)),"NCA-ECC-2-2024",IF(ISNUMBER(SEARCH("DCC",E4)),"NCA-ECC-2-2024",IF(ISNUMBER(SEARCH("CSCC",E4)),"NCA-ECC-2-2024",IF(ISNUMBER(SEARCH("PDPL-IR",E4)),"PDPL-2021",IF(ISNUMBER(SEARCH("PDPL-DTR",E4)),"PDPL-2021","NONE")))))))) | BF4: =IF(E4="","",IF(BB4="DEEP",10,IF(BB4="SHALLOW",5,IF(BB4="TEMPLATE",3,1)))+IF(N4="HIGHEST",5,IF(N4="HIGH",3,IF(N4="MODERATE",1,0)))+IF(ISNUMBER(SEARCH("Mandatory",L4)),3,0))
A5: 2 | B5: NCA | C5: National Cybersecurity Authority | D5: 3. Cybersecurity & Data | E5: OTCC-1:2022 | F5: OT Cybersecurity Controls | G5: ضوابط الأمن السيبراني للتقنيات التشغيلية | H5: OTCC-1:2022 | I5: 2022 | J5: 53 | K5: ISSUES/ENFORCES | L5: Mandatory Enforcer | M5: OT/ICS/SCADA incl. medical device networks | N5: HIGHEST | O5: https://nca.gov.sa/otcc_en.pdf | P5: NCA OTCC PDF; Resecurity | Q5: OTCC-1:2022 (First issue) | R5: First dedicated OT/ICS cybersecurity standard for KSA. 53 controls across 4 pillars: OT Governance, OT Defence, OT Resilience, OT Operations. Extends ECC-1:2018 with ICS/SCADA-specific requirements. References IEC 62443 series and NIST SP 800-82. Covers medical device OT networks in hospitals as CNI | S5: Issued: 2022. Compliance mandatory for CNI OT operators | T5: Review expected when ECC-3 released or after 5 years | U5: CURRENT — first and only version | V5: SAR 25M max (NCA-REG-2024 applies); operational shutdown of non-compliant OT systems; CNI operator licence at risk | W5: NCA — OT/ICS specialist inspectors; coordinates with sector regulators (MOH, ECRA, KACARE) for CNI OT audits | X5: Hospital (medical device OT networks); Medical Device Manufacturer; Pharmacy (automated dispensing); Lab (automated systems); Health IT Vendor (OT integration) | Y5: Both (all CNI operators — hospitals qualify as CNI) | Z5: NCA OT assessment; sector-specific OT audit; ICS security assessment by accredited third party | AA5: Biennial NCA assessment; annual internal OT security review | AB5: 53 of 53 — entire framework is OT/ICS applicable; directly covers medical device networks (2-4-x network segmentation; 2-6-x remote access; 2-9-x patch management for OT) | AC5: IEC 62443 (explicit reference); NIST SP 800-82 Rev 3; ISA/IEC 62443-2-1; ISO 27001:2022 (partial) | AD5: Arabic + English (official bilingual) | AE5: Layer 3: Technical Controls (primary); Layer 2: Risk Management; Layer 4: Compliance | AF5: Yes — aligned with IEC 62443 Security Levels (SL1-SL4); OTCC maps to SL2 minimum for healthcare CNI | AG5: National Cybersecurity Strategy; Vision 2030 Healthcare Digital Transformation; HSTP connected medical device targets | AH5: OT asset inventory; network segmentation diagrams; OT patch logs; remote access logs; OT incident response plan; ICS risk assessment report; vendor access audit logs | AI5: Socio-technical systems theory (Trist 1981): OT/IT convergence requires integrated governance. Defence-in-depth (NIST): layered security for critical systems. Critical infrastructure protection theory: availability > confidentiality in OT environments. | AJ5: FOR: First KSA standard addressing ICS/SCADA — fills critical gap identified in Nurse et al. (2017) for CNI sectors; aligns with IEC 62443 international benchmark; hospital OT networks explicitly in scope. AGAINST: Medical IoT falls between OTCC (OT-centric) and ECC-2 (IT-centric) — Coventry & Branley (2018) argue medical devices need dedicated classification not forced into OT/IT binary; OTCC written for industrial OT, clinical environment nuances absent | AK5: Clinical IoMT context absent — infusion pumps and ventilators behave differently from SCADA; no clinical engineering expertise incorporated in drafting; 53 controls insufficient for complex hospital OT topology documented by Jalali & Kaiser (2018); conflict between availability-first OT principle and confidentiality-first healthcare requirement unresolved | AL5: OTCC vs IEC 62443: OTCC mandatory in KSA; IEC 62443 voluntary but globally recognised — OTCC maps to IEC 62443-2-1 security management but lacks 62443-4-2 component-level detail. OTCC vs NIST SP 800-82r3: OTCC simpler (53 controls); NIST 800-82 more comprehensive but advisory. OTCC + SFDA-MDR combined = closest to full IoMT coverage | AM5: Coventry L & Branley D (2018) 'Cybersecurity in Healthcare' BMJ 2018; Jalali MS & Kaiser JP (2018) 'Cybersecurity in Hospitals' JMIR 20(5); Nurse JRC et al. (2017) 'Security Risk Assessment in IoT' IEEE IoT J; NCA (2022) OTCC-1:2022 nca.gov.sa/otcc_en.pdf; ISA/IEC 62443-2-1 (2009) Security Management System for IACS | AN5: Official: OTCC PDF (nca.gov.sa). Training: SANS ICS515 (ICS Active Defence); ISA/IEC 62443 Cybersecurity Certificate (ISCI). Vendors: Claroty, Nozomi Networks, Dragos publish OTCC compliance guides. Estimated: 60 hours (requires ICS/SCADA foundation knowledge first) | AO5: GH-ICGA Layer 3 (Technical Controls) — directly informs IoMT technical control set in preliminary GH-ICGA. Key thesis argument: OTCC covers general OT but misses clinical IoMT specificity — GH-ICGA Layer 3 fills this gap by adding device-specific clinical safety + cybersecurity controls. Referenced in thesis RQ2 on technical governance gaps | AP5: G + C (Governance + Compliance — standard regulatory framework positioning) | AQ5: Senior management: accountability for framework compliance. Designated compliance officer: monitor requirements. All staff: awareness of applicable obligations | AR5: Regulatory Risk; Operational Risk; Reputational Risk — specific domains determined by framework scope | AS5: See official source — legal obligation, regulatory requirement, or voluntary standard as applicable | AT5: Administrative; Technical; Operational — specific distribution determined by framework content | AU5: 1. Compliance status (compliant/non-compliant). 2. # open findings from last assessment. 3. % controls implemented. 4. Time to remediate findings. 5. Incident rate in framework scope area | AV5: Self-assessment; internal audit; external assessment as specified by issuing authority | AW5: ServiceNow GRC; IBM OpenPages; RSA Archer; MetricStream — all major GRC platforms support custom framework import. Contact vendor for framework-specific module | AX5: Third parties in scope must demonstrate equivalent compliance. Contractual compliance obligations; right-to-audit clauses; annual third-party assessment | AY5: Non-compliance: regulatory action by issuing authority; fines and penalties as specified; operational and reputational consequences | AZ5: Sector-specific — consult official source | BA5: Sector-Specific | BB5: =IF(E5="","",IF(ISNUMBER(SEARCH("Institutional theory and regulatory governance theory underpin",AI5)),"TEMPLATE",IF(LEN(AI5)>100,"DEEP",IF(AI5="","SPARSE","SHALLOW")))) | BC5: =IF(E5="","",D5&"-"&B5&"-"&E5) | BD5: =IF(E5="","",SUBSTITUTE(SUBSTITUTE(B5&"-"&E5," ",""),":","-")) | BE5: =IF(E5="","",IF(ISNUMBER(SEARCH("ECC",E5)),"NCA-ECC-2-2024",IF(ISNUMBER(SEARCH("OTCC",E5)),"NCA-ECC-2-2024",IF(ISNUMBER(SEARCH("CCC",E5)),"NCA-ECC-2-2024",IF(ISNUMBER(SEARCH("DCC",E5)),"NCA-ECC-2-2024",IF(ISNUMBER(SEARCH("CSCC",E5)),"NCA-ECC-2-2024",IF(ISNUMBER(SEARCH("PDPL-IR",E5)),"PDPL-2021",IF(ISNUMBER(SEARCH("PDPL-DTR",E5)),"PDPL-2021","NONE")))))))) | BF5: =IF(E5="","",IF(BB5="DEEP",10,IF(BB5="SHALLOW",5,IF(BB5="TEMPLATE",3,1)))+IF(N5="HIGHEST",5,IF(N5="HIGH",3,IF(N5="MODERATE",1,0)))+IF(ISNUMBER(SEARCH("Mandatory",L5)),3,0))
A6: 3 | B6: NCA | C6: National Cybersecurity Authority | D6: 3. Cybersecurity & Data | E6: CCC-1:2020 | F6: Cloud Cybersecurity Controls | G6: ضوابط الأمن السيبراني للحوسبة السحابية | H6: CCC-1:2020 | I6: 2020 | J6: 67 | K6: ISSUES/ENFORCES | L6: Mandatory Enforcer | M6: Cloud service providers and tenants — health cloud platforms | N6: HIGH | O6: https://nca.gov.sa/ccc-en.pdf | P6: NCA CCC PDF; Entrust Nov 2025 | Q6: CCC-1:2020 (First issue); CCC-2 consultation noted 2024/2025 | R6: v1 (2020): 67 controls, 4 domains, 24 sub-domains. Covers CSP and CST obligations. Extends ECC-1:2018 for cloud environments. CSTs must comply with both ECC and CCC. CCC-2 draft noted in 2024/2025 adding edge computing and data localisation controls | S6: CCC-1:2020 mandatory for cloud users/providers since 2020. CCC-2 under consultation 2024-2025 | T6: CCC-2 expected to replace CCC-1 post-consultation | U6: CURRENT — CCC-1:2020. CCC-2 in consultation | V6: SAR 25M max (NCA-REG-2024); cloud service suspension; loss of CSP licence; CST cloud provider licence revoked | W6: NCA (primary cybersecurity oversight); CST (cloud provider licensing); DGA (government cloud governance) | X6: Health IT Vendor (CSP/CST); Hospital (cloud EHR/NABIDH); Health Insurer (cloud claims systems); Government Health Entity | Y6: Both (cloud service providers anywhere + all cloud tenants in KSA) | Z6: Annual CSP self-assessment; NCA cloud audit; CST licensing audit; DGA cloud first policy compliance check | AA6: Annual; CSP external audit every 2 years | AB6: 12 (cloud-hosted IoMT platform controls: data segregation; API security; access management; logging; encryption; incident notification) | AC6: ISO 27017:2015; ISO 27018:2019; ISO 27001:2022; CSA CCM (Cloud Controls Matrix) v4; NIST SP 800-144 | AD6: Arabic + English (official bilingual) | AE6: Layer 3: Technical Controls; Layer 4: Compliance; Layer 2: Risk Management | AF6: Yes — 4 maturity levels for CSPs and CSTs separately | AG6: Cloud First Policy; Vision 2030 Digital Economy; Government Cloud (G-Cloud) initiative | AH6: Cloud architecture diagrams; data classification records; access logs; encryption certificates; CSP audit reports; incident response plan; data residency evidence | AI6: Shared responsibility model (Cloud Security Alliance): CSP vs CST obligation split. Cloud-specific risk theory: multi-tenancy, data sovereignty, supply chain risk. Regulatory theory: technology-specific regulation vs principle-based. | AJ6: FOR: Addresses real gap in ECC-1 for cloud-hosted health systems; CSP+CST dual obligation model mirrors EU NIS2 approach; mandatory for health cloud deployment. AGAINST: CCC-1 pre-dates major health cloud adoption acceleration — rapidly becoming outdated; Alassaf et al. (2019) argue cloud health data sovereignty requirements create innovation friction; CCC-2 consultation process too slow relative to cloud technology evolution | AK6: CCC-1 does not address edge computing (critical for real-time IoMT); generative AI/ML workloads in health cloud not covered; sovereign cloud zone regulations (CST 2023) create regulatory overlap with CCC; NABIDH cloud hosting requirements not explicitly aligned with CCC controls | AL6: CCC vs ISO 27017: CCC mandatory in KSA; ISO 27017 voluntary global standard. CCC maps to CSA CCM v4 (Cloud Controls Matrix) but is simpler. CCC vs SAMA Cloud Policy: CCC = technical security; SAMA = financial sector data sovereignty. Together: CCC + CST-CCR + NCA-ECC = full cloud governance for health entities | AM6: Alassaf N et al. (2019) 'Cloud Computing Challenges in Healthcare' IEEE ICCES; CSA (2021) Cloud Controls Matrix v4 cloudsecurityalliance.org; NCA (2020) CCC-1:2020 nca.gov.sa/ccc-en.pdf; Alhenaki L et al. (2019) 'Security of Cloud Computing' IJACSA 10(7); Alouffi B et al. (2021) 'Systematic Literature Review on Cloud Security' IEEE Access 9 | AN6: Official: NCA CCC PDF. Training: AWS Security Specialty; Google Cloud Professional Security Engineer; Azure Security Technologies. CSA Certificate of Cloud Security Knowledge (CCSK). Estimated: 35 hours | AO6: GH-ICGA Layer 3 (Technical) + Layer 4 (Compliance) — cloud security controls inform GH-ICGA cloud-hosted IoMT governance. Thesis gap: GH-ICGA must address how CCC applies when IoMT data streams to cloud — Layer 3 IoMT Technical Controls include cloud transmission requirements | AP6: R + C (cloud-specific risk and compliance) | AQ6: CTO/Cloud Owner: responsible for CCC compliance. Cloud Governance Committee: approve cloud adoption (Cloud First Policy pre-approval). CISO: ensure CSP selection meets CCC requirements. CSP relationship owner: maintain contractual CCC compliance | AR6: Cyber Risk (cloud-specific); Data Sovereignty Risk; Supply Chain Risk (CSP); Operational Risk (cloud outage); Regulatory Risk (data localisation) | AS6: LEGAL — Mandatory for all ECC-scope entities using cloud + all CSPs operating in KSA. Integrated with NCA-ECC-2 compliance. NCA-REG-2024 enforcement applies | AT6: Technical: 50 controls — data encryption; access management; API security; network controls; logging. Administrative: 10 controls — CSP assessment; cloud governance; contract management. Operational: 7 controls — cloud incident response; CSP SLA management | AU6: 1. % cloud workloads with encryption at rest and in transit. 2. # CSP compliance assessments completed (target: all critical CSPs annually). 3. Cloud incident response time (target <1h detection, <4h notification). 4. % data classified and labelled in cloud. 5. CSP CCC compliance score | AV6: CSP CCC compliance assessment (annual); cloud configuration review (CSPM tools); cloud penetration test; data residency verification; access management audit; API security scan | AW6: Palo Alto Prisma Cloud; Microsoft Defender for Cloud; AWS Security Hub; Google Chronicle; Wiz; CSPM (Cloud Security Posture Management) tools. For KSA: cloud brokers with local data centre: STC Cloud; Mobily Cloud; Oracle KSA; AWS Bahrain region | AX6: All CSPs: must demonstrate NCA CCC compliance; data residency within KSA (government data); PDPL-DTR-2024 cross-border assessment; annual CSP security report; right-to-audit clause; incident notification within 4 hours; subprocessor disclosure | AY6: Non-compliance: NCA audit finding; SAR 25M fine; cloud service suspension by CST. Data breach in cloud: PDPL + CCC dual penalties; CSP liability; patient data exposure | AZ6: Sector-specific — consult official source | BA6: Sector-Specific | BB6: =IF(E6="","",IF(ISNUMBER(SEARCH("Institutional theory and regulatory governance theory underpin",AI6)),"TEMPLATE",IF(LEN(AI6)>100,"DEEP",IF(AI6="","SPARSE","SHALLOW")))) | BC6: =IF(E6="","",D6&"-"&B6&"-"&E6) | BD6: =IF(E6="","",SUBSTITUTE(SUBSTITUTE(B6&"-"&E6," ",""),":","-")) | BE6: =IF(E6="","",IF(ISNUMBER(SEARCH("ECC",E6)),"NCA-ECC-2-2024",IF(ISNUMBER(SEARCH("OTCC",E6)),"NCA-ECC-2-2024",IF(ISNUMBER(SEARCH("CCC",E6)),"NCA-ECC-2-2024",IF(ISNUMBER(SEARCH("DCC",E6)),"NCA-ECC-2-2024",IF(ISNUMBER(SEARCH("CSCC",E6)),"NCA-ECC-2-2024",IF(ISNUMBER(SEARCH("PDPL-IR",E6)),"PDPL-2021",IF(ISNUMBER(SEARCH("PDPL-DTR",E6)),"PDPL-2021","NONE")))))))) | BF6: =IF(E6="","",IF(BB6="DEEP",10,IF(BB6="SHALLOW",5,IF(BB6="TEMPLATE",3,1)))+IF(N6="HIGHEST",5,IF(N6="HIGH",3,IF(N6="MODERATE",1,0)))+IF(ISNUMBER(SEARCH("Mandatory",L6)),3,0))
A7: 4 | B7: NCA | C7: National Cybersecurity Authority | D7: 3. Cybersecurity & Data | E7: DCC-1:2022 | F7: Data Cybersecurity Controls | G7: ضوابط أمن البيانات | H7: DCC-1:2022 | I7: 2022 | J7: 40 | K7: ISSUES/ENFORCES | L7: Mandatory Enforcer | M7: All ECC-scope entities — patient data lifecycle | N7: HIGH | O7: https://nca.gov.sa/ | P7: Resecurity; NCA official | Q7: DCC-1:2022 (First issue) | R7: First dedicated data cybersecurity controls from NCA. 40 controls across 3 domains: Data Governance, Data Protection, Data Lifecycle Management. Covers classification, labelling, handling, retention, and destruction. Aligns with NDMO Data Classification Policy and PDPL requirements | S7: Issued: 2022. Mandatory for all ECC-scope entities | T7: Review expected 2025-2026 | U7: CURRENT — first and only version | V7: SAR 25M max (NCA-REG-2024); PDPL penalties also applicable for personal data; data processing suspension | W7: NCA (technical data security); SDAIA/NDMO (personal data governance overlap) | X7: Hospital; Lab; Health IT Vendor; Health Insurer; Government Health Entity (all data processors) | Y7: Both | Z7: NCA annual self-assessment; may be assessed jointly with ECC audit | AA7: Annual (integrated with ECC self-assessment cycle) | AB7: 15 (IoMT data lifecycle: collection minimisation; storage encryption; transmission security; retention and secure disposal of device-generated data) | AC7: ISO 27001:2022 Annex A (data protection controls); NIST SP 800-53r5 (data protection family); GDPR (partial reference) | AD7: Arabic + English | AE7: Layer 3: Technical Controls; Layer 4: Compliance | AF7: Yes — 4 maturity levels aligned with ECC maturity model | AG7: National Data Strategy; PDPL implementation support; Vision 2030 digital trust | AH7: Data classification register; encryption implementation evidence; data retention policy; secure disposal records; data flow maps | AI7: Institutional theory and regulatory governance theory underpin all KSA regulatory frameworks. Specific theoretical basis varies by framework — consult academic literature via Google Scholar using framework name as search term. | AJ7: Academic debate varies by framework maturity and international adoption. For KSA-specific debate, consult: Almohammad & Wills (2021) J Cybersecurity; Al-Khater et al. (2020) IEEE Access; Baker McKenzie KSA regulatory updates. | AK7: Known criticisms include: implementation gap between standards and practice; resource constraints for smaller healthcare entities; rapid technology evolution outpacing regulation. Consult framework evaluation literature for specifics. | AL7: Framework comparison requires contextual analysis. Key comparators: NIST CSF 2.0 (international benchmark), ISO 27001 (certifiable standard), ECC-2 (KSA mandatory baseline). See main database for cross-framework mapping. | AM7: Key foundational references: Almohammad A & Wills G (2021) J Cybersecurity; NIST (2024) CSF 2.0; ISO (2022) 27001; NCA official documents (nca.gov.sa); Baker McKenzie Global Data & Cyber Handbook 2025. Consult SFDA, MOH, and NCA websites for framework-specific official citations. | AN7: Official: Consult the official source URL in the database for the primary document. Training: ISACA, ISC2, RAPS, IAPP, and HIMSS offer professional development covering most regulatory domains. Estimated hours vary by framework complexity. | AO7: Relevance to GH-ICGA framework varies by layer — see GH-ICGA Layer Mapping column. All KSA mandatory frameworks are compliance inputs to GH-ICGA Layer 4. Frameworks with IoMT-specific provisions directly inform Layers 2 and 3. | AP7: G + C (Governance + Compliance — standard regulatory framework positioning) | AQ7: Senior management: accountability for framework compliance. Designated compliance officer: monitor requirements. All staff: awareness of applicable obligations | AR7: Regulatory Risk; Operational Risk; Reputational Risk — specific domains determined by framework scope | AS7: See official source — legal obligation, regulatory requirement, or voluntary standard as applicable | AT7: Administrative; Technical; Operational — specific distribution determined by framework content | AU7: 1. Compliance status (compliant/non-compliant). 2. # open findings from last assessment. 3. % controls implemented. 4. Time to remediate findings. 5. Incident rate in framework scope area | AV7: Self-assessment; internal audit; external assessment as specified by issuing authority | AW7: ServiceNow GRC; IBM OpenPages; RSA Archer; MetricStream — all major GRC platforms support custom framework import. Contact vendor for framework-specific module | AX7: Third parties in scope must demonstrate equivalent compliance. Contractual compliance obligations; right-to-audit clauses; annual third-party assessment | AY7: Non-compliance: regulatory action by issuing authority; fines and penalties as specified; operational and reputational consequences | AZ7: Sector-specific — consult official source | BA7: Sector-Specific | BB7: =IF(E7="","",IF(ISNUMBER(SEARCH("Institutional theory and regulatory governance theory underpin",AI7)),"TEMPLATE",IF(LEN(AI7)>100,"DEEP",IF(AI7="","SPARSE","SHALLOW")))) | BC7: =IF(E7="","",D7&"-"&B7&"-"&E7) | BD7: =IF(E7="","",SUBSTITUTE(SUBSTITUTE(B7&"-"&E7," ",""),":","-")) | BE7: =IF(E7="","",IF(ISNUMBER(SEARCH("ECC",E7)),"NCA-ECC-2-2024",IF(ISNUMBER(SEARCH("OTCC",E7)),"NCA-ECC-2-2024",IF(ISNUMBER(SEARCH("CCC",E7)),"NCA-ECC-2-2024",IF(ISNUMBER(SEARCH("DCC",E7)),"NCA-ECC-2-2024",IF(ISNUMBER(SEARCH("CSCC",E7)),"NCA-ECC-2-2024",IF(ISNUMBER(SEARCH("PDPL-IR",E7)),"PDPL-2021",IF(ISNUMBER(SEARCH("PDPL-DTR",E7)),"PDPL-2021","NONE")))))))) | BF7: =IF(E7="","",IF(BB7="DEEP",10,IF(BB7="SHALLOW",5,IF(BB7="TEMPLATE",3,1)))+IF(N7="HIGHEST",5,IF(N7="HIGH",3,IF(N7="MODERATE",1,0)))+IF(ISNUMBER(SEARCH("Mandatory",L7)),3,0))
A8: 5 | B8: NCA | C8: National Cybersecurity Authority | D8: 3. Cybersecurity & Data | E8: CSCC-1:2019 | F8: Critical Systems Cybersecurity Controls | G8: ضوابط الأمن السيبراني للأنظمة الحساسة | H8: CSCC-1:2019 | I8: 2019 | J8: 35 | K8: ISSUES/ENFORCES | L8: Mandatory Enforcer | M8: Critical national system operators incl. hospitals as CNI | N8: HIGH | O8: https://nca.gov.sa/en/regulatory-documents/controls-list/cscc/ | P8: NCA CSCC official | Q8: CSCC-1:2019 (First issue) | R8: 32 main controls / 73 sub-controls extending ECC for critical systems. Covers mission-critical systems, availability requirements, integrity controls, access control for critical systems. Hospital core infrastructure (EMR servers, imaging systems, life support networks) qualifies | S8: Issued: 2019. Mandatory for entities with critical national systems | T8: Review expected 2025 | U8: CURRENT — first and only version; update expected | V8: SAR 25M max (NCA-REG-2024); critical system shutdown authority; escalated penalties for CNI operators | W8: NCA — critical infrastructure protection division; sector regulators (MOH for hospital critical systems) | X8: Hospital (core IT: EMR servers, life support, ICU systems); Government Health Entity; Health IT Vendor (critical system developers) | Y8: Both (entities with critical national systems) | Z8: NCA critical systems audit; specialised third-party assessment | AA8: Annual internal; NCA external: biennial | AB8: 10 (critical system availability; failover; integrity monitoring; privileged access to critical medical systems; change management for life-critical systems) | AC8: NIST SP 800-53r5 (availability controls); IEC 62443-3-3; ISO 27001:2022 | AD8: Arabic + English | AE8: Layer 3: Technical Controls; Layer 2: Risk Management | AF8: Yes — complements ECC 5-level maturity model | AG8: National Critical Infrastructure Protection Programme (CNIP); National Cybersecurity Strategy | AH8: Critical system register; BIA (Business Impact Analysis); availability test records; privileged access audit; change management logs | AI8: Institutional theory and regulatory governance theory underpin all KSA regulatory frameworks. Specific theoretical basis varies by framework — consult academic literature via Google Scholar using framework name as search term. | AJ8: Academic debate varies by framework maturity and international adoption. For KSA-specific debate, consult: Almohammad & Wills (2021) J Cybersecurity; Al-Khater et al. (2020) IEEE Access; Baker McKenzie KSA regulatory updates. | AK8: Known criticisms include: implementation gap between standards and practice; resource constraints for smaller healthcare entities; rapid technology evolution outpacing regulation. Consult framework evaluation literature for specifics. | AL8: Framework comparison requires contextual analysis. Key comparators: NIST CSF 2.0 (international benchmark), ISO 27001 (certifiable standard), ECC-2 (KSA mandatory baseline). See main database for cross-framework mapping. | AM8: Key foundational references: Almohammad A & Wills G (2021) J Cybersecurity; NIST (2024) CSF 2.0; ISO (2022) 27001; NCA official documents (nca.gov.sa); Baker McKenzie Global Data & Cyber Handbook 2025. Consult SFDA, MOH, and NCA websites for framework-specific official citations. | AN8: Official: Consult the official source URL in the database for the primary document. Training: ISACA, ISC2, RAPS, IAPP, and HIMSS offer professional development covering most regulatory domains. Estimated hours vary by framework complexity. | AO8: Relevance to GH-ICGA framework varies by layer — see GH-ICGA Layer Mapping column. All KSA mandatory frameworks are compliance inputs to GH-ICGA Layer 4. Frameworks with IoMT-specific provisions directly inform Layers 2 and 3. | AP8: G + C (Governance + Compliance — standard regulatory framework positioning) | AQ8: Senior management: accountability for framework compliance. Designated compliance officer: monitor requirements. All staff: awareness of applicable obligations | AR8: Regulatory Risk; Operational Risk; Reputational Risk — specific domains determined by framework scope | AS8: See official source — legal obligation, regulatory requirement, or voluntary standard as applicable | AT8: Administrative; Technical; Operational — specific distribution determined by framework content | AU8: 1. Compliance status (compliant/non-compliant). 2. # open findings from last assessment. 3. % controls implemented. 4. Time to remediate findings. 5. Incident rate in framework scope area | AV8: Self-assessment; internal audit; external assessment as specified by issuing authority | AW8: ServiceNow GRC; IBM OpenPages; RSA Archer; MetricStream — all major GRC platforms support custom framework import. Contact vendor for framework-specific module | AX8: Third parties in scope must demonstrate equivalent compliance. Contractual compliance obligations; right-to-audit clauses; annual third-party assessment | AY8: Non-compliance: regulatory action by issuing authority; fines and penalties as specified; operational and reputational consequences | AZ8: Sector-specific — consult official source | BA8: Sector-Specific | BB8: =IF(E8="","",IF(ISNUMBER(SEARCH("Institutional theory and regulatory governance theory underpin",AI8)),"TEMPLATE",IF(LEN(AI8)>100,"DEEP",IF(AI8="","SPARSE","SHALLOW")))) | BC8: =IF(E8="","",D8&"-"&B8&"-"&E8) | BD8: =IF(E8="","",SUBSTITUTE(SUBSTITUTE(B8&"-"&E8," ",""),":","-")) | BE8: =IF(E8="","",IF(ISNUMBER(SEARCH("ECC",E8)),"NCA-ECC-2-2024",IF(ISNUMBER(SEARCH("OTCC",E8)),"NCA-ECC-2-2024",IF(ISNUMBER(SEARCH("CCC",E8)),"NCA-ECC-2-2024",IF(ISNUMBER(SEARCH("DCC",E8)),"NCA-ECC-2-2024",IF(ISNUMBER(SEARCH("CSCC",E8)),"NCA-ECC-2-2024",IF(ISNUMBER(SEARCH("PDPL-IR",E8)),"PDPL-2021",IF(ISNUMBER(SEARCH("PDPL-DTR",E8)),"PDPL-2021","NONE")))))))) | BF8: =IF(E8="","",IF(BB8="DEEP",10,IF(BB8="SHALLOW",5,IF(BB8="TEMPLATE",3,1)))+IF(N8="HIGHEST",5,IF(N8="HIGH",3,IF(N8="MODERATE",1,0)))+IF(ISNUMBER(SEARCH("Mandatory",L8)),3,0))
A9: 6 | B9: NCA | C9: National Cybersecurity Authority | D9: 3. Cybersecurity & Data | E9: TCC-1:2021 | F9: Telework Cybersecurity Controls | G9: ضوابط الأمن السيبراني للعمل عن بعد | H9: TCC-1:2021 | I9: 2021 | J9: 28 | K9: ISSUES/ENFORCES | L9: Mandatory Enforcer | M9: All ECC-scope entities with remote workers — telehealth clinicians | N9: MODERATE | O9: https://nca.gov.sa/en/regulatory-documents/controls-list/tcc/ | P9: NCA TCC official | Q9: TCC-1:2021 (First issue) | R9: 21 main controls / 42 sub-controls across 3 domains: Telework Governance, Telework Security, Telework Monitoring. Covers secure VPN, MFA, endpoint security, BYOD policy, remote access to clinical systems. Healthcare application: telehealth clinicians accessing patient records remotely | S9: Issued: 2021. Mandatory for ECC-scope entities with remote workers | T9: Review expected 2025-2026 | U9: CURRENT — first and only version | V9: SAR 25M max (NCA-REG-2024); may be assessed as ECC non-compliance | W9: NCA — assessed as part of ECC compliance audit | X9: Hospital; Clinic; Health IT Vendor; Health Insurer; Government Health Entity (all entities with remote workers) | Y9: Both | Z9: Annual self-assessment (integrated with ECC); spot check during NCA audit | AA9: Annual | AB9: 5 (secure remote access to clinical systems; remote device management; VPN requirements for IoMT monitoring platforms) | AC9: NIST SP 800-114; ISO 27001:2022; CIS Benchmark for remote access | AD9: Arabic + English | AE9: Layer 3: Technical Controls | AF9: Aligned with ECC 5-level model | AG9: National Telework Programme; Healthcare Digital Transformation (telehealth staff) | AH9: VPN configuration evidence; remote access policy; endpoint security records; MFA implementation evidence; remote worker awareness training records | AI9: Institutional theory and regulatory governance theory underpin all KSA regulatory frameworks. Specific theoretical basis varies by framework — consult academic literature via Google Scholar using framework name as search term. | AJ9: Academic debate varies by framework maturity and international adoption. For KSA-specific debate, consult: Almohammad & Wills (2021) J Cybersecurity; Al-Khater et al. (2020) IEEE Access; Baker McKenzie KSA regulatory updates. | AK9: Known criticisms include: implementation gap between standards and practice; resource constraints for smaller healthcare entities; rapid technology evolution outpacing regulation. Consult framework evaluation literature for specifics. | AL9: Framework comparison requires contextual analysis. Key comparators: NIST CSF 2.0 (international benchmark), ISO 27001 (certifiable standard), ECC-2 (KSA mandatory baseline). See main database for cross-framework mapping. | AM9: Key foundational references: Almohammad A & Wills G (2021) J Cybersecurity; NIST (2024) CSF 2.0; ISO (2022) 27001; NCA official documents (nca.gov.sa); Baker McKenzie Global Data & Cyber Handbook 2025. Consult SFDA, MOH, and NCA websites for framework-specific official citations. | AN9: Official: Consult the official source URL in the database for the primary document. Training: ISACA, ISC2, RAPS, IAPP, and HIMSS offer professional development covering most regulatory domains. Estimated hours vary by framework complexity. | AO9: Relevance to GH-ICGA framework varies by layer — see GH-ICGA Layer Mapping column. All KSA mandatory frameworks are compliance inputs to GH-ICGA Layer 4. Frameworks with IoMT-specific provisions directly inform Layers 2 and 3. | AP9: G + C (Governance + Compliance — standard regulatory framework positioning) | AQ9: Senior management: accountability for framework compliance. Designated compliance officer: monitor requirements. All staff: awareness of applicable obligations | AR9: Regulatory Risk; Operational Risk; Reputational Risk — specific domains determined by framework scope | AS9: See official source — legal obligation, regulatory requirement, or voluntary standard as applicable | AT9: Administrative; Technical; Operational — specific distribution determined by framework content | AU9: 1. Compliance status (compliant/non-compliant). 2. # open findings from last assessment. 3. % controls implemented. 4. Time to remediate findings. 5. Incident rate in framework scope area | AV9: Self-assessment; internal audit; external assessment as specified by issuing authority | AW9: ServiceNow GRC; IBM OpenPages; RSA Archer; MetricStream — all major GRC platforms support custom framework import. Contact vendor for framework-specific module | AX9: Third parties in scope must demonstrate equivalent compliance. Contractual compliance obligations; right-to-audit clauses; annual third-party assessment | AY9: Non-compliance: regulatory action by issuing authority; fines and penalties as specified; operational and reputational consequences | AZ9: Sector-specific — consult official source | BA9: Sector-Specific | BB9: =IF(E9="","",IF(ISNUMBER(SEARCH("Institutional theory and regulatory governance theory underpin",AI9)),"TEMPLATE",IF(LEN(AI9)>100,"DEEP",IF(AI9="","SPARSE","SHALLOW")))) | BC9: =IF(E9="","",D9&"-"&B9&"-"&E9) | BD9: =IF(E9="","",SUBSTITUTE(SUBSTITUTE(B9&"-"&E9," ",""),":","-")) | BE9: =IF(E9="","",IF(ISNUMBER(SEARCH("ECC",E9)),"NCA-ECC-2-2024",IF(ISNUMBER(SEARCH("OTCC",E9)),"NCA-ECC-2-2024",IF(ISNUMBER(SEARCH("CCC",E9)),"NCA-ECC-2-2024",IF(ISNUMBER(SEARCH("DCC",E9)),"NCA-ECC-2-2024",IF(ISNUMBER(SEARCH("CSCC",E9)),"NCA-ECC-2-2024",IF(ISNUMBER(SEARCH("PDPL-IR",E9)),"PDPL-2021",IF(ISNUMBER(SEARCH("PDPL-DTR",E9)),"PDPL-2021","NONE")))))))) | BF9: =IF(E9="","",IF(BB9="DEEP",10,IF(BB9="SHALLOW",5,IF(BB9="TEMPLATE",3,1)))+IF(N9="HIGHEST",5,IF(N9="HIGH",3,IF(N9="MODERATE",1,0)))+IF(ISNUMBER(SEARCH("Mandatory",L9)),3,0))
A10: 7 | B10: NCA | C10: National Cybersecurity Authority | D10: 3. Cybersecurity & Data | E10: OSMACC-1:2021 | F10: Social Media Cybersecurity Controls | G10: ضوابط الأمن السيبراني لحسابات التواصل | H10: OSMACC-1:2021 | I10: 2021 | J10: 18 | K10: ISSUES/ENFORCES | L10: Mandatory Enforcer | M10: All NCA-scope entities with social media accounts | N10: LOW | O10: https://nca.gov.sa/en/regulatory-documents/controls-list/osmacc/ | P10: NCA OSMACC official | Q10: OSMACC-1:2021 (First issue) | R10: 18 controls for official social media account security. Covers MFA, account monitoring, content approval workflows, incident response for account compromise. Healthcare application: hospital official accounts, MOH social media security | S10: Issued: 2021 | T10: Review 2025 | U10: CURRENT — first and only version | V10: Penalties defined by issuing authority; consult official source. NCA ECC-2 penalties apply if relevant | W10: Issuing authority and/or designated inspection department | X10: As specified in framework scope — consult official document | Y10: Both (unless specified otherwise in official document) | Z10: As defined by issuing authority | AA10: As defined by issuing authority | AB10: To be determined from framework text — see official source | AC10: See framework preamble for international standard references | AD10: Arabic (primary in KSA); English may be available | AE10: Mapped to relevant GH-ICGA layer — requires manual assessment | AF10: See official framework for maturity model details | AG10: Aligned with relevant Vision 2030 programme — see framework context | AH10: As specified in framework compliance requirements | AI10: Institutional theory and regulatory governance theory underpin all KSA regulatory frameworks. Specific theoretical basis varies by framework — consult academic literature via Google Scholar using framework name as search term. | AJ10: Academic debate varies by framework maturity and international adoption. For KSA-specific debate, consult: Almohammad & Wills (2021) J Cybersecurity; Al-Khater et al. (2020) IEEE Access; Baker McKenzie KSA regulatory updates. | AK10: Known criticisms include: implementation gap between standards and practice; resource constraints for smaller healthcare entities; rapid technology evolution outpacing regulation. Consult framework evaluation literature for specifics. | AL10: Framework comparison requires contextual analysis. Key comparators: NIST CSF 2.0 (international benchmark), ISO 27001 (certifiable standard), ECC-2 (KSA mandatory baseline). See main database for cross-framework mapping. | AM10: Key foundational references: Almohammad A & Wills G (2021) J Cybersecurity; NIST (2024) CSF 2.0; ISO (2022) 27001; NCA official documents (nca.gov.sa); Baker McKenzie Global Data & Cyber Handbook 2025. Consult SFDA, MOH, and NCA websites for framework-specific official citations. | AN10: Official: Consult the official source URL in the database for the primary document. Training: ISACA, ISC2, RAPS, IAPP, and HIMSS offer professional development covering most regulatory domains. Estimated hours vary by framework complexity. | AO10: Relevance to GH-ICGA framework varies by layer — see GH-ICGA Layer Mapping column. All KSA mandatory frameworks are compliance inputs to GH-ICGA Layer 4. Frameworks with IoMT-specific provisions directly inform Layers 2 and 3. | AP10: G + C (Governance + Compliance — standard regulatory framework positioning) | AQ10: Senior management: accountability for framework compliance. Designated compliance officer: monitor requirements. All staff: awareness of applicable obligations | AR10: Regulatory Risk; Operational Risk; Reputational Risk — specific domains determined by framework scope | AS10: See official source — legal obligation, regulatory requirement, or voluntary standard as applicable | AT10: Administrative; Technical; Operational — specific distribution determined by framework content | AU10: 1. Compliance status (compliant/non-compliant). 2. # open findings from last assessment. 3. % controls implemented. 4. Time to remediate findings. 5. Incident rate in framework scope area | AV10: Self-assessment; internal audit; external assessment as specified by issuing authority | AW10: ServiceNow GRC; IBM OpenPages; RSA Archer; MetricStream — all major GRC platforms support custom framework import. Contact vendor for framework-specific module | AX10: Third parties in scope must demonstrate equivalent compliance. Contractual compliance obligations; right-to-audit clauses; annual third-party assessment | AY10: Non-compliance: regulatory action by issuing authority; fines and penalties as specified; operational and reputational consequences | AZ10: Sector-specific — consult official source | BA10: Sector-Specific | BB10: =IF(E10="","",IF(ISNUMBER(SEARCH("Institutional theory and regulatory governance theory underpin",AI10)),"TEMPLATE",IF(LEN(AI10)>100,"DEEP",IF(AI10="","SPARSE","SHALLOW")))) | BC10: =IF(E10="","",D10&"-"&B10&"-"&E10) | BD10: =IF(E10="","",SUBSTITUTE(SUBSTITUTE(B10&"-"&E10," ",""),":","-")) | BE10: =IF(E10="","",IF(ISNUMBER(SEARCH("ECC",E10)),"NCA-ECC-2-2024",IF(ISNUMBER(SEARCH("OTCC",E10)),"NCA-ECC-2-2024",IF(ISNUMBER(SEARCH("CCC",E10)),"NCA-ECC-2-2024",IF(ISNUMBER(SEARCH("DCC",E10)),"NCA-ECC-2-2024",IF(ISNUMBER(SEARCH("CSCC",E10)),"NCA-ECC-2-2024",IF(ISNUMBER(SEARCH("PDPL-IR",E10)),"PDPL-2021",IF(ISNUMBER(SEARCH("PDPL-DTR",E10)),"PDPL-2021","NONE")))))))) | BF10: =IF(E10="","",IF(BB10="DEEP",10,IF(BB10="SHALLOW",5,IF(BB10="TEMPLATE",3,1)))+IF(N10="HIGHEST",5,IF(N10="HIGH",3,IF(N10="MODERATE",1,0)))+IF(ISNUMBER(SEARCH("Mandatory",L10)),3,0))
A11: 8 | B11: NCA | C11: National Cybersecurity Authority | D11: 3. Cybersecurity & Data | E11: NCS-1:2020 | F11: National Cryptographic Standards | G11: المعايير الوطنية للتشفير | H11: NCS-1:2020 | I11: 2020 | J11: 22 | K11: ISSUES/ENFORCES | L11: Mandatory Enforcer | M11: All ECC-scope entities — patient data encryption | N11: HIGH | O11: https://nca.gov.sa/en/regulatory-documents/frameworks-and-standard-list/ncs/ | P11: NCA NCS official; Entrust | Q11: NCS-1:2020 (First issue); quantum-safe update under consideration | R11: 22 cryptographic requirements. Covers approved algorithms (AES-256, RSA-2048+, SHA-256+), key management, PKI requirements, TLS version requirements. Healthcare: patient data encryption at rest and in transit, digital signatures on clinical records | S11: Issued: 2020. Mandatory for all ECC-scope entities | T11: Quantum-safe cryptography update under consideration post-2025 | U11: CURRENT — NCS-1:2020. Quantum migration guidance expected | V11: Penalties defined by issuing authority; consult official source. NCA ECC-2 penalties apply if relevant | W11: Issuing authority and/or designated inspection department | X11: As specified in framework scope — consult official document | Y11: Both (unless specified otherwise in official document) | Z11: As defined by issuing authority | AA11: As defined by issuing authority | AB11: To be determined from framework text — see official source | AC11: See framework preamble for international standard references | AD11: Arabic (primary in KSA); English may be available | AE11: Mapped to relevant GH-ICGA layer — requires manual assessment | AF11: See official framework for maturity model details | AG11: Aligned with relevant Vision 2030 programme — see framework context | AH11: As specified in framework compliance requirements | AI11: Institutional theory and regulatory governance theory underpin all KSA regulatory frameworks. Specific theoretical basis varies by framework — consult academic literature via Google Scholar using framework name as search term. | AJ11: Academic debate varies by framework maturity and international adoption. For KSA-specific debate, consult: Almohammad & Wills (2021) J Cybersecurity; Al-Khater et al. (2020) IEEE Access; Baker McKenzie KSA regulatory updates. | AK11: Known criticisms include: implementation gap between standards and practice; resource constraints for smaller healthcare entities; rapid technology evolution outpacing regulation. Consult framework evaluation literature for specifics. | AL11: Framework comparison requires contextual analysis. Key comparators: NIST CSF 2.0 (international benchmark), ISO 27001 (certifiable standard), ECC-2 (KSA mandatory baseline). See main database for cross-framework mapping. | AM11: Key foundational references: Almohammad A & Wills G (2021) J Cybersecurity; NIST (2024) CSF 2.0; ISO (2022) 27001; NCA official documents (nca.gov.sa); Baker McKenzie Global Data & Cyber Handbook 2025. Consult SFDA, MOH, and NCA websites for framework-specific official citations. | AN11: Official: Consult the official source URL in the database for the primary document. Training: ISACA, ISC2, RAPS, IAPP, and HIMSS offer professional development covering most regulatory domains. Estimated hours vary by framework complexity. | AO11: Relevance to GH-ICGA framework varies by layer — see GH-ICGA Layer Mapping column. All KSA mandatory frameworks are compliance inputs to GH-ICGA Layer 4. Frameworks with IoMT-specific provisions directly inform Layers 2 and 3. | AP11: G + C (Governance + Compliance — standard regulatory framework positioning) | AQ11: Senior management: accountability for framework compliance. Designated compliance officer: monitor requirements. All staff: awareness of applicable obligations | AR11: Regulatory Risk; Operational Risk; Reputational Risk — specific domains determined by framework scope | AS11: See official source — legal obligation, regulatory requirement, or voluntary standard as applicable | AT11: Administrative; Technical; Operational — specific distribution determined by framework content | AU11: 1. Compliance status (compliant/non-compliant). 2. # open findings from last assessment. 3. % controls implemented. 4. Time to remediate findings. 5. Incident rate in framework scope area | AV11: Self-assessment; internal audit; external assessment as specified by issuing authority | AW11: ServiceNow GRC; IBM OpenPages; RSA Archer; MetricStream — all major GRC platforms support custom framework import. Contact vendor for framework-specific module | AX11: Third parties in scope must demonstrate equivalent compliance. Contractual compliance obligations; right-to-audit clauses; annual third-party assessment | AY11: Non-compliance: regulatory action by issuing authority; fines and penalties as specified; operational and reputational consequences | AZ11: Sector-specific — consult official source | BA11: Sector-Specific | BB11: =IF(E11="","",IF(ISNUMBER(SEARCH("Institutional theory and regulatory governance theory underpin",AI11)),"TEMPLATE",IF(LEN(AI11)>100,"DEEP",IF(AI11="","SPARSE","SHALLOW")))) | BC11: =IF(E11="","",D11&"-"&B11&"-"&E11) | BD11: =IF(E11="","",SUBSTITUTE(SUBSTITUTE(B11&"-"&E11," ",""),":","-")) | BE11: =IF(E11="","",IF(ISNUMBER(SEARCH("ECC",E11)),"NCA-ECC-2-2024",IF(ISNUMBER(SEARCH("OTCC",E11)),"NCA-ECC-2-2024",IF(ISNUMBER(SEARCH("CCC",E11)),"NCA-ECC-2-2024",IF(ISNUMBER(SEARCH("DCC",E11)),"NCA-ECC-2-2024",IF(ISNUMBER(SEARCH("CSCC",E11)),"NCA-ECC-2-2024",IF(ISNUMBER(SEARCH("PDPL-IR",E11)),"PDPL-2021",IF(ISNUMBER(SEARCH("PDPL-DTR",E11)),"PDPL-2021","NONE")))))))) | BF11: =IF(E11="","",IF(BB11="DEEP",10,IF(BB11="SHALLOW",5,IF(BB11="TEMPLATE",3,1)))+IF(N11="HIGHEST",5,IF(N11="HIGH",3,IF(N11="MODERATE",1,0)))+IF(ISNUMBER(SEARCH("Mandatory",L11)),3,0))
A12: 9 | B12: NCA | C12: National Cybersecurity Authority | D12: 3. Cybersecurity & Data | E12: SCyWF | F12: Saudi Cybersecurity Workforce Framework | G12: الإطار السعودي للكوادر السيبرانية | H12: SCyWF updated 2024 | I12: 2022 | J12: N/A | K12: ISSUES/ENFORCES | L12: Mandatory Enforcer | M12: All NCA-scope entities — cyber roles must be Saudi nationals (ECC-2) | N12: HIGH | O12: https://nca.gov.sa/en/regulatory-documents/frameworks-and-standard-list/scywf/ | P12: NCA SCyWF; Clyde & Co Jan 2025 | Q12: SCyWF v1 2022 → updated 2024 with ECC-2 Saudisation mandate | R12: National taxonomy of cybersecurity roles and competency levels. Updated 2024 to add mandatory Saudisation: all cybersecurity positions in ECC-scope entities must be full-time qualified Saudi nationals (ECC-2 Section 1-1-3). Healthcare CISO and SOC analyst roles affected directly | S12: v1 issued 2022. Saudisation mandate: Oct 2024 (ECC-2). Compliance window: Oct 2025 | T12: Annual review with job market changes | U12: CURRENT — updated 2024 | V12: Penalties defined by issuing authority; consult official source. NCA ECC-2 penalties apply if relevant | W12: Issuing authority and/or designated inspection department | X12: As specified in framework scope — consult official document | Y12: Both (unless specified otherwise in official document) | Z12: As defined by issuing authority | AA12: As defined by issuing authority | AB12: To be determined from framework text — see official source | AC12: See framework preamble for international standard references | AD12: Arabic (primary in KSA); English may be available | AE12: Mapped to relevant GH-ICGA layer — requires manual assessment | AF12: See official framework for maturity model details | AG12: Aligned with relevant Vision 2030 programme — see framework context | AH12: As specified in framework compliance requirements | AI12: Institutional theory and regulatory governance theory underpin all KSA regulatory frameworks. Specific theoretical basis varies by framework — consult academic literature via Google Scholar using framework name as search term. | AJ12: Academic debate varies by framework maturity and international adoption. For KSA-specific debate, consult: Almohammad & Wills (2021) J Cybersecurity; Al-Khater et al. (2020) IEEE Access; Baker McKenzie KSA regulatory updates. | AK12: Known criticisms include: implementation gap between standards and practice; resource constraints for smaller healthcare entities; rapid technology evolution outpacing regulation. Consult framework evaluation literature for specifics. | AL12: Framework comparison requires contextual analysis. Key comparators: NIST CSF 2.0 (international benchmark), ISO 27001 (certifiable standard), ECC-2 (KSA mandatory baseline). See main database for cross-framework mapping. | AM12: Key foundational references: Almohammad A & Wills G (2021) J Cybersecurity; NIST (2024) CSF 2.0; ISO (2022) 27001; NCA official documents (nca.gov.sa); Baker McKenzie Global Data & Cyber Handbook 2025. Consult SFDA, MOH, and NCA websites for framework-specific official citations. | AN12: Official: Consult the official source URL in the database for the primary document. Training: ISACA, ISC2, RAPS, IAPP, and HIMSS offer professional development covering most regulatory domains. Estimated hours vary by framework complexity. | AO12: Relevance to GH-ICGA framework varies by layer — see GH-ICGA Layer Mapping column. All KSA mandatory frameworks are compliance inputs to GH-ICGA Layer 4. Frameworks with IoMT-specific provisions directly inform Layers 2 and 3. | AP12: G + C (Governance + Compliance — standard regulatory framework positioning) | AQ12: Senior management: accountability for framework compliance. Designated compliance officer: monitor requirements. All staff: awareness of applicable obligations | AR12: Regulatory Risk; Operational Risk; Reputational Risk — specific domains determined by framework scope | AS12: See official source — legal obligation, regulatory requirement, or voluntary standard as applicable | AT12: Administrative; Technical; Operational — specific distribution determined by framework content | AU12: 1. Compliance status (compliant/non-compliant). 2. # open findings from last assessment. 3. % controls implemented. 4. Time to remediate findings. 5. Incident rate in framework scope area | AV12: Self-assessment; internal audit; external assessment as specified by issuing authority | AW12: ServiceNow GRC; IBM OpenPages; RSA Archer; MetricStream — all major GRC platforms support custom framework import. Contact vendor for framework-specific module | AX12: Third parties in scope must demonstrate equivalent compliance. Contractual compliance obligations; right-to-audit clauses; annual third-party assessment | AY12: Non-compliance: regulatory action by issuing authority; fines and penalties as specified; operational and reputational consequences | AZ12: ALL 17 SECTORS — entities with cybersecurity roles | BA12: YES — ALL SECTORS | BB12: =IF(E12="","",IF(ISNUMBER(SEARCH("Institutional theory and regulatory governance theory underpin",AI12)),"TEMPLATE",IF(LEN(AI12)>100,"DEEP",IF(AI12="","SPARSE","SHALLOW")))) | BC12: =IF(E12="","",D12&"-"&B12&"-"&E12) | BD12: =IF(E12="","",SUBSTITUTE(SUBSTITUTE(B12&"-"&E12," ",""),":","-")) | BE12: =IF(E12="","",IF(ISNUMBER(SEARCH("ECC",E12)),"NCA-ECC-2-2024",IF(ISNUMBER(SEARCH("OTCC",E12)),"NCA-ECC-2-2024",IF(ISNUMBER(SEARCH("CCC",E12)),"NCA-ECC-2-2024",IF(ISNUMBER(SEARCH("DCC",E12)),"NCA-ECC-2-2024",IF(ISNUMBER(SEARCH("CSCC",E12)),"NCA-ECC-2-2024",IF(ISNUMBER(SEARCH("PDPL-IR",E12)),"PDPL-2021",IF(ISNUMBER(SEARCH("PDPL-DTR",E12)),"PDPL-2021","NONE")))))))) | BF12: =IF(E12="","",IF(BB12="DEEP",10,IF(BB12="SHALLOW",5,IF(BB12="TEMPLATE",3,1)))+IF(N12="HIGHEST",5,IF(N12="HIGH",3,IF(N12="MODERATE",1,0)))+IF(ISNUMBER(SEARCH("Mandatory",L12)),3,0))
A13: 10 | B13: NCA | C13: National Cybersecurity Authority | D13: 3. Cybersecurity & Data | E13: SCyber-Edu | F13: Saudi Cybersecurity Higher Education Framework | G13: الإطار السعودي للتعليم العالي في الأمن السيبراني | H13: SCyber-Edu-1:2022 | I13: 2022 | J13: N/A | K13: ISSUES/ENFORCES | L13: Mandatory Enforcer | M13: Universities offering cybersecurity programmes | N13: LOW | O13: https://nca.gov.sa/en/regulatory-documents/frameworks-and-standard-list/scyberedu/ | P13: NCA SCyber-Edu | Q13: SCyber-Edu v1 2022 (First issue) | R13: Curriculum framework for university-level cybersecurity programmes. Defines core competencies, elective tracks, lab requirements. Aligned with SCyWF role taxonomy. Supports national pipeline for Saudi cybersecurity professionals required by NCA frameworks | S13: Issued: 2022 | T13: Review every 3 years | U13: CURRENT — first version | V13: Penalties defined by issuing authority; consult official source. NCA ECC-2 penalties apply if relevant | W13: Issuing authority and/or designated inspection department | X13: As specified in framework scope — consult official document | Y13: Both (unless specified otherwise in official document) | Z13: As defined by issuing authority | AA13: As defined by issuing authority | AB13: To be determined from framework text — see official source | AC13: See framework preamble for international standard references | AD13: Arabic (primary in KSA); English may be available | AE13: Mapped to relevant GH-ICGA layer — requires manual assessment | AF13: See official framework for maturity model details | AG13: Aligned with relevant Vision 2030 programme — see framework context | AH13: As specified in framework compliance requirements | AI13: Institutional theory and regulatory governance theory underpin all KSA regulatory frameworks. Specific theoretical basis varies by framework — consult academic literature via Google Scholar using framework name as search term. | AJ13: Academic debate varies by framework maturity and international adoption. For KSA-specific debate, consult: Almohammad & Wills (2021) J Cybersecurity; Al-Khater et al. (2020) IEEE Access; Baker McKenzie KSA regulatory updates. | AK13: Known criticisms include: implementation gap between standards and practice; resource constraints for smaller healthcare entities; rapid technology evolution outpacing regulation. Consult framework evaluation literature for specifics. | AL13: Framework comparison requires contextual analysis. Key comparators: NIST CSF 2.0 (international benchmark), ISO 27001 (certifiable standard), ECC-2 (KSA mandatory baseline). See main database for cross-framework mapping. | AM13: Key foundational references: Almohammad A & Wills G (2021) J Cybersecurity; NIST (2024) CSF 2.0; ISO (2022) 27001; NCA official documents (nca.gov.sa); Baker McKenzie Global Data & Cyber Handbook 2025. Consult SFDA, MOH, and NCA websites for framework-specific official citations. | AN13: Official: Consult the official source URL in the database for the primary document. Training: ISACA, ISC2, RAPS, IAPP, and HIMSS offer professional development covering most regulatory domains. Estimated hours vary by framework complexity. | AO13: Relevance to GH-ICGA framework varies by layer — see GH-ICGA Layer Mapping column. All KSA mandatory frameworks are compliance inputs to GH-ICGA Layer 4. Frameworks with IoMT-specific provisions directly inform Layers 2 and 3. | AP13: G + C (Governance + Compliance — standard regulatory framework positioning) | AQ13: Senior management: accountability for framework compliance. Designated compliance officer: monitor requirements. All staff: awareness of applicable obligations | AR13: Regulatory Risk; Operational Risk; Reputational Risk — specific domains determined by framework scope | AS13: See official source — legal obligation, regulatory requirement, or voluntary standard as applicable | AT13: Administrative; Technical; Operational — specific distribution determined by framework content | AU13: 1. Compliance status (compliant/non-compliant). 2. # open findings from last assessment. 3. % controls implemented. 4. Time to remediate findings. 5. Incident rate in framework scope area | AV13: Self-assessment; internal audit; external assessment as specified by issuing authority | AW13: ServiceNow GRC; IBM OpenPages; RSA Archer; MetricStream — all major GRC platforms support custom framework import. Contact vendor for framework-specific module | AX13: Third parties in scope must demonstrate equivalent compliance. Contractual compliance obligations; right-to-audit clauses; annual third-party assessment | AY13: Non-compliance: regulatory action by issuing authority; fines and penalties as specified; operational and reputational consequences | AZ13: Sector-specific — consult official source | BA13: Sector-Specific | BB13: =IF(E13="","",IF(ISNUMBER(SEARCH("Institutional theory and regulatory governance theory underpin",AI13)),"TEMPLATE",IF(LEN(AI13)>100,"DEEP",IF(AI13="","SPARSE","SHALLOW")))) | BC13: =IF(E13="","",D13&"-"&B13&"-"&E13) | BD13: =IF(E13="","",SUBSTITUTE(SUBSTITUTE(B13&"-"&E13," ",""),":","-")) | BE13: =IF(E13="","",IF(ISNUMBER(SEARCH("ECC",E13)),"NCA-ECC-2-2024",IF(ISNUMBER(SEARCH("OTCC",E13)),"NCA-ECC-2-2024",IF(ISNUMBER(SEARCH("CCC",E13)),"NCA-ECC-2-2024",IF(ISNUMBER(SEARCH("DCC",E13)),"NCA-ECC-2-2024",IF(ISNUMBER(SEARCH("CSCC",E13)),"NCA-ECC-2-2024",IF(ISNUMBER(SEARCH("PDPL-IR",E13)),"PDPL-2021",IF(ISNUMBER(SEARCH("PDPL-DTR",E13)),"PDPL-2021","NONE")))))))) | BF13: =IF(E13="","",IF(BB13="DEEP",10,IF(BB13="SHALLOW",5,IF(BB13="TEMPLATE",3,1)))+IF(N13="HIGHEST",5,IF(N13="HIGH",3,IF(N13="MODERATE",1,0)))+IF(ISNUMBER(SEARCH("Mandatory",L13)),3,0))
A14: 11 | B14: NCA | C14: National Cybersecurity Authority | D14: 3. Cybersecurity & Data | E14: NCA-REG-2024 | F14: NCA Regulatory Framework (Enforcement & Penalties) | G14: لائحة الهيئة الوطنية للأمن السيبراني | H14: Dec 2024 | I14: 2024 | J14: N/A | K14: ISSUES/ENFORCES | L14: Mandatory Enforcer | M14: All entities subject to any NCA framework — fines up to SAR 25M | N14: HIGHEST | O14: https://www.twobirds.com/en/insights/2025/ | P14: Bird & Bird Jan 2025; Clyde & Co Jan 2025 | Q14: First enforcement regulation — Dec 21, 2024 | R14: First dedicated NCA enforcement mechanism. Powers: inspection/audit authority, administrative fines up to SAR 25 million, licence suspension/revocation, appointment of NCA inspectors with judicial powers, criminal referrals. Covers all NCA frameworks (ECC, OTCC, CCC, DCC, CSCC, TCC). Significant shift from guidance to enforceable compliance | S14: Issued: Dec 21, 2024. In force immediately | T14: Ongoing enforcement | U14: CURRENT — first enforcement regulation | V14: This IS the penalty framework — SAR 25M max; imprisonment via criminal referral; business suspension; public naming; appeals process defined | W14: NCA — Director General of Supervisory Affairs; NCA Inspectors (appointed Dec 2024 with judicial powers) | X14: All healthcare entities subject to any NCA framework | Y14: Both | Z14: NCA-initiated inspections; complaint-triggered; incident-triggered; scheduled sector reviews | AA14: As determined by NCA risk-based approach | AB14: N/A — enforcement mechanism, not technical controls | AC14: EU NIS2 Directive (enforcement model reference); Singapore CSA Cybersecurity Act (penalty benchmarking) | AD14: Arabic (primary); English unofficial translation | AE14: Layer 4: Compliance; Layer 5: Assurance | AF14: No maturity model — binary compliance/non-compliance | AG14: National Cybersecurity Strategy (enforcement pillar) | AH14: N/A — this is the enforcement regulation; entities must produce evidence of compliance with underlying NCA frameworks | AI14: Regulatory enforcement theory (Ayres & Braithwaite 1992): responsive regulation pyramid — persuasion → warning → penalty → criminal referral. Deterrence theory (Becker 1968): SAR 25M ceiling designed as credible deterrent calibrated to entity revenue. Administrative law theory: judicial inspector powers draw from Sharia-compliant regulatory enforcement tradition unique to KSA. | AJ14: FOR: First NCA-specific enforcement mechanism closes the 'paper tiger' critique of ECC-1 era; SAR 25M cap is proportionate compared to EU NIS2 (€10M/2% revenue); criminal referral authority adds personal accountability for executives. AGAINST: Critics argue SAR 25M is insufficient for large entities (Aramco, NEOM); no explicit whistleblower protections; enforcement regulation published before ECC-2 audit methodology finalised — sequencing gap. | AK14: Criticisms: (1) Enforcement regulation lacks graduated penalty schedule — inspectors have full discretion between SAR 0 and SAR 25M with no guidance; (2) Criminal referral pathway undefined — no precedent case law; (3) No appeal mechanism specified for disputed findings; (4) Saudisation mandate in ECC-2 creates workforce bottleneck for compliance — not enough qualified Saudi cyber professionals yet; (5) Arabic-only official text creates interpretation challenges for international organisations operating in KSA. | AL14: Compared to: EU NIS2 penalties (€10M/2% revenue — higher cap, turnover-linked); UK NIS Regulations (£17M max); Singapore Cybersecurity Act (S$100K — much lower); UAE NESA (case-by-case). KSA NCA-REG-2024 is mid-range on penalty severity but HIGHEST on scope breadth (covers all CNI + government entities). Unique: KSA adds criminal referral pathway not present in EU/UK/SG enforcement. | AM14: Ayres & Braithwaite (1992) Responsive Regulation; Bird & Bird (2025) KSA Cybersecurity Enforcement Guide; Clyde & Co (2025) NCA Regulatory Analysis; Al-Qahtani (2024) Administrative Enforcement in Saudi Law; NCA Official Gazette Publication (2024). | AN14: Official: Consult the official source URL in the database for the primary document. Training: ISACA, ISC2, RAPS, IAPP, and HIMSS offer professional development covering most regulatory domains. Estimated hours vary by framework complexity. | AO14: GH-ICGA positions NCA-REG-2024 as the ENFORCEMENT ENABLER layer — transforms the entire NCA framework stack from advisory to legally binding. Critical for thesis argument that KSA has moved from 'regulation by policy' to 'regulation by law' in healthcare cybersecurity governance. | AP14: G + C (Governance + Compliance — standard regulatory framework positioning) | AQ14: Senior management: accountability for framework compliance. Designated compliance officer: monitor requirements. All staff: awareness of applicable obligations | AR14: Regulatory Risk; Operational Risk; Reputational Risk — specific domains determined by framework scope | AS14: See official source — legal obligation, regulatory requirement, or voluntary standard as applicable | AT14: Administrative; Technical; Operational — specific distribution determined by framework content | AU14: 1. Compliance status (compliant/non-compliant). 2. # open findings from last assessment. 3. % controls implemented. 4. Time to remediate findings. 5. Incident rate in framework scope area | AV14: Self-assessment; internal audit; external assessment as specified by issuing authority | AW14: ServiceNow GRC; IBM OpenPages; RSA Archer; MetricStream — all major GRC platforms support custom framework import. Contact vendor for framework-specific module | AX14: Third parties in scope must demonstrate equivalent compliance. Contractual compliance obligations; right-to-audit clauses; annual third-party assessment | AY14: Non-compliance: regulatory action by issuing authority; fines and penalties as specified; operational and reputational consequences | AZ14: ALL 17 SECTORS — all NCA framework subjects | BA14: YES — ALL SECTORS | BB14: =IF(E14="","",IF(ISNUMBER(SEARCH("Institutional theory and regulatory governance theory underpin",AI14)),"TEMPLATE",IF(LEN(AI14)>100,"DEEP",IF(AI14="","SPARSE","SHALLOW")))) | BC14: =IF(E14="","",D14&"-"&B14&"-"&E14) | BD14: =IF(E14="","",SUBSTITUTE(SUBSTITUTE(B14&"-"&E14," ",""),":","-")) | BE14: =IF(E14="","",IF(ISNUMBER(SEARCH("ECC",E14)),"NCA-ECC-2-2024",IF(ISNUMBER(SEARCH("OTCC",E14)),"NCA-ECC-2-2024",IF(ISNUMBER(SEARCH("CCC",E14)),"NCA-ECC-2-2024",IF(ISNUMBER(SEARCH("DCC",E14)),"NCA-ECC-2-2024",IF(ISNUMBER(SEARCH("CSCC",E14)),"NCA-ECC-2-2024",IF(ISNUMBER(SEARCH("PDPL-IR",E14)),"PDPL-2021",IF(ISNUMBER(SEARCH("PDPL-DTR",E14)),"PDPL-2021","NONE")))))))) | BF14: =IF(E14="","",IF(BB14="DEEP",10,IF(BB14="SHALLOW",5,IF(BB14="TEMPLATE",3,1)))+IF(N14="HIGHEST",5,IF(N14="HIGH",3,IF(N14="MODERATE",1,0)))+IF(ISNUMBER(SEARCH("Mandatory",L14)),3,0))
A15: 12 | B15: NCA | C15: National Cybersecurity Authority | D15: 3. Cybersecurity & Data | E15: NCA-MCSOC | F15: Managed SOC Policy | G15: سياسة مراكز العمليات الأمنية المُدارة | H15: 2024 | I15: 2024 | J15: N/A | K15: ISSUES/ENFORCES | L15: Mandatory Enforcer | M15: MSOC service providers — hospital SOC services | N15: MODERATE | O15: https://nca.gov.sa/en/regulatory-documents/ | P15: NCA official | Q15: 2024 (First issue) | R15: Requirements for Managed Security Operations Centers. Defines MSOC service delivery standards, SOC analyst qualifications (Saudi nationals required), incident response SLAs, threat intelligence sharing obligations, reporting to NCA CERT. Healthcare SOCs using managed services must ensure vendor compliance | S15: Issued 2024 | T15: Annual review | U15: CURRENT | V15: Penalties defined by issuing authority; consult official source. NCA ECC-2 penalties apply if relevant | W15: Issuing authority and/or designated inspection department | X15: As specified in framework scope — consult official document | Y15: Both (unless specified otherwise in official document) | Z15: As defined by issuing authority | AA15: As defined by issuing authority | AB15: To be determined from framework text — see official source | AC15: See framework preamble for international standard references | AD15: Arabic (primary in KSA); English may be available | AE15: Mapped to relevant GH-ICGA layer — requires manual assessment | AF15: See official framework for maturity model details | AG15: Aligned with relevant Vision 2030 programme — see framework context | AH15: As specified in framework compliance requirements | AI15: Institutional theory and regulatory governance theory underpin all KSA regulatory frameworks. Specific theoretical basis varies by framework — consult academic literature via Google Scholar using framework name as search term. | AJ15: Academic debate varies by framework maturity and international adoption. For KSA-specific debate, consult: Almohammad & Wills (2021) J Cybersecurity; Al-Khater et al. (2020) IEEE Access; Baker McKenzie KSA regulatory updates. | AK15: Known criticisms include: implementation gap between standards and practice; resource constraints for smaller healthcare entities; rapid technology evolution outpacing regulation. Consult framework evaluation literature for specifics. | AL15: Framework comparison requires contextual analysis. Key comparators: NIST CSF 2.0 (international benchmark), ISO 27001 (certifiable standard), ECC-2 (KSA mandatory baseline). See main database for cross-framework mapping. | AM15: Key foundational references: Almohammad A & Wills G (2021) J Cybersecurity; NIST (2024) CSF 2.0; ISO (2022) 27001; NCA official documents (nca.gov.sa); Baker McKenzie Global Data & Cyber Handbook 2025. Consult SFDA, MOH, and NCA websites for framework-specific official citations. | AN15: Official: Consult the official source URL in the database for the primary document. Training: ISACA, ISC2, RAPS, IAPP, and HIMSS offer professional development covering most regulatory domains. Estimated hours vary by framework complexity. | AO15: Relevance to GH-ICGA framework varies by layer — see GH-ICGA Layer Mapping column. All KSA mandatory frameworks are compliance inputs to GH-ICGA Layer 4. Frameworks with IoMT-specific provisions directly inform Layers 2 and 3. | AP15: G + C (Governance + Compliance — standard regulatory framework positioning) | AQ15: Senior management: accountability for framework compliance. Designated compliance officer: monitor requirements. All staff: awareness of applicable obligations | AR15: Regulatory Risk; Operational Risk; Reputational Risk — specific domains determined by framework scope | AS15: See official source — legal obligation, regulatory requirement, or voluntary standard as applicable | AT15: Administrative; Technical; Operational — specific distribution determined by framework content | AU15: 1. Compliance status (compliant/non-compliant). 2. # open findings from last assessment. 3. % controls implemented. 4. Time to remediate findings. 5. Incident rate in framework scope area | AV15: Self-assessment; internal audit; external assessment as specified by issuing authority | AW15: ServiceNow GRC; IBM OpenPages; RSA Archer; MetricStream — all major GRC platforms support custom framework import. Contact vendor for framework-specific module | AX15: Third parties in scope must demonstrate equivalent compliance. Contractual compliance obligations; right-to-audit clauses; annual third-party assessment | AY15: Non-compliance: regulatory action by issuing authority; fines and penalties as specified; operational and reputational consequences | AZ15: Sector-specific — consult official source | BA15: Sector-Specific | BB15: =IF(E15="","",IF(ISNUMBER(SEARCH("Institutional theory and regulatory governance theory underpin",AI15)),"TEMPLATE",IF(LEN(AI15)>100,"DEEP",IF(AI15="","SPARSE","SHALLOW")))) | BC15: =IF(E15="","",D15&"-"&B15&"-"&E15) | BD15: =IF(E15="","",SUBSTITUTE(SUBSTITUTE(B15&"-"&E15," ",""),":","-")) | BE15: =IF(E15="","",IF(ISNUMBER(SEARCH("ECC",E15)),"NCA-ECC-2-2024",IF(ISNUMBER(SEARCH("OTCC",E15)),"NCA-ECC-2-2024",IF(ISNUMBER(SEARCH("CCC",E15)),"NCA-ECC-2-2024",IF(ISNUMBER(SEARCH("DCC",E15)),"NCA-ECC-2-2024",IF(ISNUMBER(SEARCH("CSCC",E15)),"NCA-ECC-2-2024",IF(ISNUMBER(SEARCH("PDPL-IR",E15)),"PDPL-2021",IF(ISNUMBER(SEARCH("PDPL-DTR",E15)),"PDPL-2021","NONE")))))))) | BF15: =IF(E15="","",IF(BB15="DEEP",10,IF(BB15="SHALLOW",5,IF(BB15="TEMPLATE",3,1)))+IF(N15="HIGHEST",5,IF(N15="HIGH",3,IF(N15="MODERATE",1,0)))+IF(ISNUMBER(SEARCH("Mandatory",L15)),3,0))
... A28: 25 | B28: SDAIA | C28: Saudi Data & AI Authority + NDMO | D28: 3. Cybersecurity & Data | E28: NCA-ECC-2:2024 | F28: Essential Cybersecurity Controls | G28: ضوابط الأمن السيبراني الأساسية | H28: ECC-2:2024 | I28: 2018 | J28: 108 | K28: MUST COMPLY WITH | L28: Mandatory Complier | M28: SDAIA as government entity | N28: HIGHEST | O28: https://nca.gov.sa/ | P28: NCA ECC scope | Q28: See official source for version history | R28: Framework issued by the relevant authority. Version details available on the official website referenced in the source URL column. The framework has been updated periodically since first issuance. | S28: See official source | T28: Updated as needed by the issuing authority | U28: CURRENT — consult official source for latest version | V28: Penalties defined by issuing authority; consult official source. NCA ECC-2 penalties apply if relevant | W28: Issuing authority and/or designated inspection department | X28: As specified in framework scope — consult official document | Y28: Both (unless specified otherwise in official document) | Z28: As defined by issuing authority | AA28: As defined by issuing authority | AB28: To be determined from framework text — see official source | AC28: See framework preamble for international standard references | AD28: Arabic (primary in KSA); English may be available | AE28: Mapped to relevant GH-ICGA layer — requires manual assessment | AF28: See official framework for maturity model details | AG28: Aligned with relevant Vision 2030 programme — see framework context | AH28: As specified in framework compliance requirements | AI28: Institutional isomorphism (DiMaggio & Powell 1983): SDAIA requiring NCA ECC-2 compliance demonstrates coercive isomorphism — the privacy regulator mandating cybersecurity baseline from the cyber regulator. Multi-agency governance theory: regulatory coordination through shared control adoption. | AJ28: FOR: SDAIA adopting ECC-2 creates harmonised cybersecurity baseline across both privacy and cyber domains — reduces compliance fragmentation; demonstrates regulatory coordination between NCA and SDAIA. AGAINST: Creates potential jurisdictional ambiguity — if SDAIA and NCA audit the same ECC-2 controls, which finding prevails? Double jeopardy risk for entities. | AK28: Criticisms: (1) SDAIA lacks cybersecurity audit expertise — may defer entirely to NCA findings; (2) Creates appearance of 108+ controls for SDAIA compliance when actual incremental burden is zero (same ECC-2 controls); (3) Double-counting inflates the regulatory burden perception for healthcare entities. | AL28: Framework comparison requires contextual analysis. Key comparators: NIST CSF 2.0 (international benchmark), ISO 27001 (certifiable standard), ECC-2 (KSA mandatory baseline). See main database for cross-framework mapping. | AM28: DiMaggio & Powell (1983) Institutional Isomorphism; NCA-SDAIA MoU (2023) Regulatory Coordination; Al-Harbi (2024) Multi-Agency Cyber Governance in KSA. | AN28: Official: Consult the official source URL in the database for the primary document. Training: ISACA, ISC2, RAPS, IAPP, and HIMSS offer professional development covering most regulatory domains. Estimated hours vary by framework complexity. | AO28: Relevance to GH-ICGA framework varies by layer — see GH-ICGA Layer Mapping column. All KSA mandatory frameworks are compliance inputs to GH-ICGA Layer 4. Frameworks with IoMT-specific provisions directly inform Layers 2 and 3. | AP28: G + C (Governance + Compliance — standard regulatory framework positioning) | AQ28: Senior management: accountability for framework compliance. Designated compliance officer: monitor requirements. All staff: awareness of applicable obligations | AR28: Regulatory Risk; Operational Risk; Reputational Risk — specific domains determined by framework scope | AS28: See official source — legal obligation, regulatory requirement, or voluntary standard as applicable | AT28: Administrative; Technical; Operational — specific distribution determined by framework content | AU28: 1. Compliance status (compliant/non-compliant). 2. # open findings from last assessment. 3. % controls implemented. 4. Time to remediate findings. 5. Incident rate in framework scope area | AV28: Self-assessment; internal audit; external assessment as specified by issuing authority | AW28: ServiceNow GRC; IBM OpenPages; RSA Archer; MetricStream — all major GRC platforms support custom framework import. Contact vendor for framework-specific module | AX28: Third parties in scope must demonstrate equivalent compliance. Contractual compliance obligations; right-to-audit clauses; annual third-party assessment | AY28: Non-compliance: regulatory action by issuing authority; fines and penalties as specified; operational and reputational consequences | AZ28: ALL 17 SECTORS | BA28: YES — ALL SECTORS | BB28: =IF(E28="","",IF(ISNUMBER(SEARCH("Institutional theory and regulatory governance theory underpin",AI28)),"TEMPLATE",IF(LEN(AI28)>100,"DEEP",IF(AI28="","SPARSE","SHALLOW")))) | BC28: =IF(E28="","",D28&"-"&B28&"-"&E28) | BD28: =IF(E28="","",SUBSTITUTE(SUBSTITUTE(B28&"-"&E28," ",""),":","-")) | BE28: =IF(E28="","",IF(ISNUMBER(SEARCH("ECC",E28)),"NCA-ECC-2-2024",IF(ISNUMBER(SEARCH("OTCC",E28)),"NCA-ECC-2-2024",IF(ISNUMBER(SEARCH("CCC",E28)),"NCA-ECC-2-2024",IF(ISNUMBER(SEARCH("DCC",E28)),"NCA-ECC-2-2024",IF(ISNUMBER(SEARCH("CSCC",E28)),"NCA-ECC-2-2024",IF(ISNUMBER(SEARCH("PDPL-IR",E28)),"PDPL-2021",IF(ISNUMBER(SEARCH("PDPL-DTR",E28)),"PDPL-2021","NONE")))))))) | BF28: =IF(E28="","",IF(BB28="DEEP",10,IF(BB28="SHALLOW",5,IF(BB28="TEMPLATE",3,1)))+IF(N28="HIGHEST",5,IF(N28="HIGH",3,IF(N28="MODERATE",1,0)))+IF(ISNUMBER(SEARCH("Mandatory",L28)),3,0))
BB29: =IF(E29="","",IF(ISNUMBER(SEARCH("Institutional theory and regulatory governance theory underpin",AI29)),"TEMPLATE",IF(LEN(AI29)>100,"DEEP",IF(AI29="","SPARSE","SHALLOW")))) | BC29: =IF(E29="","",D29&"-"&B29&"-"&E29) | BD29: =IF(E29="","",SUBSTITUTE(SUBSTITUTE(B29&"-"&E29," ",""),":","-")) | BE29: =IF(E29="","",IF(ISNUMBER(SEARCH("ECC",E29)),"NCA-ECC-2-2024",IF(ISNUMBER(SEARCH("OTCC",E29)),"NCA-ECC-2-2024",IF(ISNUMBER(SEARCH("CCC",E29)),"NCA-ECC-2-2024",IF(ISNUMBER(SEARCH("DCC",E29)),"NCA-ECC-2-2024",IF(ISNUMBER(SEARCH("CSCC",E29)),"NCA-ECC-2-2024",IF(ISNUMBER(SEARCH("PDPL-IR",E29)),"PDPL-2021",IF(ISNUMBER(SEARCH("PDPL-DTR",E29)),"PDPL-2021","NONE")))))))) | BF29: =IF(E29="","",IF(BB29="DEEP",10,IF(BB29="SHALLOW",5,IF(BB29="TEMPLATE",3,1)))+IF(N29="HIGHEST",5,IF(N29="HIGH",3,IF(N29="MODERATE",1,0)))+IF(ISNUMBER(SEARCH("Mandatory",L29)),3,0))
B30: ── 2. Healthcare & Life Sciences ── | BB30: =IF(E30="","",IF(ISNUMBER(SEARCH("Institutional theory and regulatory governance theory underpin",AI30)),"TEMPLATE",IF(LEN(AI30)>100,"DEEP",IF(AI30="","SPARSE","SHALLOW")))) | BC30: =IF(E30="","",D30&"-"&B30&"-"&E30) | BD30: =IF(E30="","",SUBSTITUTE(SUBSTITUTE(B30&"-"&E30," ",""),":","-")) | BE30: =IF(E30="","",IF(ISNUMBER(SEARCH("ECC",E30)),"NCA-ECC-2-2024",IF(ISNUMBER(SEARCH("OTCC",E30)),"NCA-ECC-2-2024",IF(ISNUMBER(SEARCH("CCC",E30)),"NCA-ECC-2-2024",IF(ISNUMBER(SEARCH("DCC",E30)),"NCA-ECC-2-2024",IF(ISNUMBER(SEARCH("CSCC",E30)),"NCA-ECC-2-2024",IF(ISNUMBER(SEARCH("PDPL-IR",E30)),"PDPL-2021",IF(ISNUMBER(SEARCH("PDPL-DTR",E30)),"PDPL-2021","NONE")))))))) | BF30: =IF(E30="","",IF(BB30="DEEP",10,IF(BB30="SHALLOW",5,IF(BB30="TEMPLATE",3,1)))+IF(N30="HIGHEST",5,IF(N30="HIGH",3,IF(N30="MODERATE",1,0)))+IF(ISNUMBER(SEARCH("Mandatory",L30)),3,0))
A31: 26 | B31: MOH | C31: Ministry of Health | D31: 2. Healthcare & Life Sciences | E31: MOH-HL | F31: Health Law | G31: نظام الصحة | H31: RD M/11 2002 updated | I31: 1949 | J31: N/A | K31: ISSUES/ENFORCES | L31: Mandatory Enforcer | M31: All healthcare facilities and providers | N31: HIGHEST | O31: https://www.moh.gov.sa/en/Ministry/Rules/Pages/default.aspx | P31: MOH official; Hammad & Al-Mehdar 2025 | Q31: Royal Decree M/11 1949 (foundational) → multiple Royal Decrees updating through 2024 | R31: Foundational health law establishing MOH mandate. Major milestones: 1950s-1990s: primary care network; 2001 National Health Plan; 2009 Private Hospitals Law; 2016 Health Clusters reform; 2021 NABIDH mandate; 2024 mandatory EMR adoption for all private facilities. Constitutes the overarching legal basis for all MOH regulations | S31: Original: 1949. Continuously updated by Royal Decrees | T31: Ongoing — amendments via Royal Decree | U31: CURRENT — foundational law with continuous amendments | V31: Penalties defined by issuing authority; consult official source. NCA ECC-2 penalties apply if relevant | W31: Issuing authority and/or designated inspection department | X31: As specified in framework scope — consult official document | Y31: Both (unless specified otherwise in official document) | Z31: As defined by issuing authority | AA31: As defined by issuing authority | AB31: To be determined from framework text — see official source | AC31: See framework preamble for international standard references | AD31: Arabic (primary in KSA); English may be available | AE31: Mapped to relevant GH-ICGA layer — requires manual assessment | AF31: See official framework for maturity model details | AG31: Aligned with relevant Vision 2030 programme — see framework context | AH31: As specified in framework compliance requirements | AI31: Health law theory: healthcare licensing as state power to protect public safety. Regulatory capture theory (Stigler 1971): MOH as both regulator and provider creates inherent conflict of interest. Institutional design theory: separation of MOH regulatory and operational functions under Vision 2030 restructuring. | AJ31: FOR: MOH Health Law (2022 update) consolidates scattered healthcare regulations into unified framework; explicitly addresses telemedicine, digital health, AI diagnostics for the first time; mandatory licensing for all digital health platforms. AGAINST: MOH simultaneously operates hospitals and regulates them — structural conflict of interest; licensing requirements for digital health innovations may slow adoption compared to UAE DHA sandbox model. | AK31: Criticisms: (1) MOH as regulator AND provider creates conflicts acknowledged by Vision 2030 restructuring plan but not yet resolved; (2) Digital health licensing framework lags behind innovation — SFDA AI-MDS published before MOH digital health licensing criteria; (3) Telemedicine regulations drafted pre-COVID lack post-pandemic cross-border provisions; (4) No explicit patient data rights within Health Law (relies on PDPL for data protection). | AL31: Framework comparison requires contextual analysis. Key comparators: NIST CSF 2.0 (international benchmark), ISO 27001 (certifiable standard), ECC-2 (KSA mandatory baseline). See main database for cross-framework mapping. | AM31: Stigler (1971) Economic Regulation; MOH Health Law (Royal Decree M/22); Al-Yousuf et al. (2023) Healthcare Regulation in KSA; WHO (2024) Health System Review: Saudi Arabia. | AN31: Official: Consult the official source URL in the database for the primary document. Training: ISACA, ISC2, RAPS, IAPP, and HIMSS offer professional development covering most regulatory domains. Estimated hours vary by framework complexity. | AO31: GH-ICGA positions MOH-HL as the HEALTHCARE GOVERNANCE BASELINE — the legal foundation upon which all health-sector-specific regulations build. Thesis argues MOH dual role (regulator+provider) is the key structural challenge for healthcare GRC in KSA. | AP31: G + C (Governance + Compliance — standard regulatory framework positioning) | AQ31: Senior management: accountability for framework compliance. Designated compliance officer: monitor requirements. All staff: awareness of applicable obligations | AR31: Regulatory Risk; Operational Risk; Reputational Risk — specific domains determined by framework scope | AS31: See official source — legal obligation, regulatory requirement, or voluntary standard as applicable | AT31: Administrative; Technical; Operational — specific distribution determined by framework content | AU31: 1. Compliance status (compliant/non-compliant). 2. # open findings from last assessment. 3. % controls implemented. 4. Time to remediate findings. 5. Incident rate in framework scope area | AV31: Self-assessment; internal audit; external assessment as specified by issuing authority | AW31: ServiceNow GRC; IBM OpenPages; RSA Archer; MetricStream — all major GRC platforms support custom framework import. Contact vendor for framework-specific module | AX31: Third parties in scope must demonstrate equivalent compliance. Contractual compliance obligations; right-to-audit clauses; annual third-party assessment | AY31: Non-compliance: regulatory action by issuing authority; fines and penalties as specified; operational and reputational consequences | AZ31: Healthcare & Life Sciences | BA31: Sector-Specific | BB31: =IF(E31="","",IF(ISNUMBER(SEARCH("Institutional theory and regulatory governance theory underpin",AI31)),"TEMPLATE",IF(LEN(AI31)>100,"DEEP",IF(AI31="","SPARSE","SHALLOW")))) | BC31: =IF(E31="","",D31&"-"&B31&"-"&E31) | BD31: =IF(E31="","",SUBSTITUTE(SUBSTITUTE(B31&"-"&E31," ",""),":","-")) | BE31: =IF(E31="","",IF(ISNUMBER(SEARCH("ECC",E31)),"NCA-ECC-2-2024",IF(ISNUMBER(SEARCH("OTCC",E31)),"NCA-ECC-2-2024",IF(ISNUMBER(SEARCH("CCC",E31)),"NCA-ECC-2-2024",IF(ISNUMBER(SEARCH("DCC",E31)),"NCA-ECC-2-2024",IF(ISNUMBER(SEARCH("CSCC",E31)),"NCA-ECC-2-2024",IF(ISNUMBER(SEARCH("PDPL-IR",E31)),"PDPL-2021",IF(ISNUMBER(SEARCH("PDPL-DTR",E31)),"PDPL-2021","NONE")))))))) | BF31: =IF(E31="","",IF(BB31="DEEP",10,IF(BB31="SHALLOW",5,IF(BB31="TEMPLATE",3,1)))+IF(N31="HIGHEST",5,IF(N31="HIGH",3,IF(N31="MODERATE",1,0)))+IF(ISNUMBER(SEARCH("Mandatory",L31)),3,0))
A32: 27 | B32: MOH | C32: Ministry of Health | D32: 2. Healthcare & Life Sciences | E32: MOH-HIS | F32: Health Information System Standards | G32: معايير نظم المعلومات الصحية | H32: 2024 update | I32: 2010 | J32: 112 | K32: ISSUES/ENFORCES | L32: Mandatory Enforcer | M32: All MOH-affiliated hospitals and clinics | N32: HIGHEST | O32: https://www.moh.gov.sa/en/ | P32: MOH; NHIC NABIDH; WHO/WEF PHSSR 2025 | Q32: First issued ~2010 → comprehensive update 2022 → mandatory EMR update 2024 | R32: Progressive standards covering: 2010 (basic EHR requirements); 2015 (interoperability standards added); 2018 (NABIDH integration); 2020 (mobile health and telemedicine modules); 2022 (comprehensive 112-control update covering clinical systems, imaging, medication management, emergency, genomics, training); 2024 (mandatory EMR adoption for all MOH and private facilities aligned with NABIDH) | S32: First: 2010. Major update: 2022. EMR mandate: 2024 | T32: Updated with NABIDH platform releases; typically annual minor updates | U32: CURRENT — 2024 version mandatory | V32: MOH facility licensing at risk; mandatory corrective action plan; financial penalties under Private Health Institutions Law; non-compliant systems barred from NABIDH connectivity | W32: MOH — Directorate of Health Information (DHI); regional health cluster inspection teams; NHIC for interoperability compliance | X32: Hospital; Clinic; Lab; Pharmacy (hospital); Government Health Entity | Y32: Both (mandatory for MOH facilities; mandatory for private facilities since 2024 PHILAW update) | Z32: MOH annual IT audit; NHIC interoperability assessment; CBAHI HIT standards review during accreditation | AA32: Annual MOH audit; NABIDH connectivity continuous monitoring | AB32: 28 (medical device integration into HIS; alarm management; device data capture; IoMT workflow integration; remote monitoring data ingestion; device incident reporting to HIS) | AC32: HL7 FHIR R4 (interoperability); IHE profiles (integration); ISO 27799:2016 (health ISMS); DICOM (imaging) | AD32: Arabic (primary); English technical annexes | AE32: Layer 1: Governance; Layer 3: Technical Controls; Layer 4: Compliance | AF32: Yes — 4 implementation levels (Basic / Intermediate / Advanced / Optimised); MOH tracks facility scores | AG32: HSTP digital health; NABIDH national EHR; Vision 2030 healthcare quality targets | AH32: HIS system documentation; NABIDH connectivity certificate; interoperability test results; staff training records; system access audit logs; downtime contingency procedure | AI32: Health informatics systems theory (Shortliffe & Cimino 2006): HIS as sociotechnical infrastructure. Interoperability theory (Kuperman 2011): semantic/syntactic/organisational interoperability levels. Technology adoption theory (TAM — Davis 1989): clinician adoption barriers to HIS. | AJ32: FOR: National standardisation essential for patient safety continuity (WHO 2019); NABIDH integration creates longitudinal patient record unavailable previously; IoMT data integration requirements push hospitals toward modern system architectures. AGAINST: Ajami & Bagheri-Tadi (2013) and Aloudah et al. (2021) document implementation-reality gap in Saudi HIS — standards exist but compliance varies widely by facility tier; urban-rural HIS capacity gap poorly addressed; cybersecurity requirements within HIS standards historically weak (pre-NABIDH) | AK32: 112 controls create compliance burden without proportionality guidance; small private clinics face disproportionate compliance cost; no formal HIS certification programme — self-declaration accepted; IoMT data standards not harmonised with international HL7 FHIR profiles; historical emphasis on data capture over data quality | AL32: MOH-HIS vs NHS Digital standards (UK): NHS has legally binding DCB standards with enforcement; MOH-HIS is ministerial directive with softer enforcement. MOH-HIS vs ONC Health IT Certification (US): US has federal certification; KSA moving toward certification (NABIDH conformance). MOH-HIS + NHIC-NABIDH = closest to ONC approach in KSA | AM32: Ajami S & Bagheri-Tadi T (2013) 'Barriers for Adopting Electronic Health Records' MateriaSociomed 25(3); Aloudah N et al. (2021) 'Digital Health in Saudi Arabia' Sustainability 13(12); Shortliffe EH & Cimino JJ (2006) Biomedical Informatics Springer; WHO (2019) Classification of Digital Interventions; Alotaibi YK & Federico F (2017) 'Impact of Health IT on Patient Safety' Saudi Medical J 38(12) | AN32: Official: MOH website (moh.gov.sa). Training: CPHIMS (Certified Professional Health Informatics & Information Management); HL7 FHIR Foundational (HL7.org); NHIC developer portal training (nhic.gov.sa). Language: Arabic primary. Estimated: 45 hours | AO32: GH-ICGA Layer 1 (Governance) + Layer 3 (Technical Controls) — MOH-HIS is the clinical data governance backbone that the preliminary GH-ICGA IoMT framework must integrate with. Thesis: GH-ICGA IoMT data model must align with HIS data standards to ensure IoMT device data flows into the national health record coherently | AP32: G + R + C (all three — clinical information governance foundation) | AQ32: Hospital CEO: accountable for HIS compliance. CIO/CMIO: responsible for HIS implementation and NABIDH connectivity. Clinical Informatics Committee: govern HIS standards adoption. Department Heads: responsible for clinical data quality in their systems | AR32: Operational Risk (HIS downtime = clinical risk); Patient Safety Risk; Data Quality Risk; Regulatory Risk (MOH non-compliance); Interoperability Risk (NABIDH disconnection) | AS32: REGULATORY — MOH ministerial directive. Mandatory for all licensed facilities. Non-compliance risks licensing. Enforced through MOH annual audit and NABIDH connectivity monitoring | AT32: Technical (T): 68 controls — system architecture; integration; security; availability; backup. Administrative (A): 28 controls — data governance; policies; training; documentation. Operational (O): 16 controls — downtime procedures; change management; vendor management | AU32: 1. NABIDH connectivity status (connected/disconnected). 2. HIS downtime incidents per month (target <4h/month). 3. Data quality score (completeness/accuracy) from NABIDH reports. 4. % clinical staff trained on HIS (target 100%). 5. Time-to-restore HIS after failure (target <4h). 6. # HIS security incidents per quarter | AV32: Annual MOH HIS audit (documentation + system walk-through); NABIDH API conformance test (NHIC automated); data quality audit; HIS security assessment; downtime procedure simulation; user access review | AW32: Epic; Cerner (Oracle Health); Philips Tasy EMR; Meditech; InterSystems HealthShare — all NABIDH-integrated. For compliance: ServiceNow Healthcare; Qualio (quality management); NHIC developer portal for FHIR conformance testing | AX32: HIS vendors: must be MOH-approved/NABIDH-certified; contractual data protection obligations; source code escrow for critical systems; SLA for 99.9% uptime; mandatory SFDA notification if HIS failure affects medical devices; annual security assessment of HIS vendors | AY32: Non-compliance: MOH corrective action; facility licence conditions; NABIDH disconnection (loss of referrals, national patient record access); PHILAW 2024 penalties for private facilities. Clinical impact: patient safety risk from poor data quality or HIS unavailability | AZ32: Healthcare & Life Sciences | BA32: Sector-Specific | BB32: =IF(E32="","",IF(ISNUMBER(SEARCH("Institutional theory and regulatory governance theory underpin",AI32)),"TEMPLATE",IF(LEN(AI32)>100,"DEEP",IF(AI32="","SPARSE","SHALLOW")))) | BC32: =IF(E32="","",D32&"-"&B32&"-"&E32) | BD32: =IF(E32="","",SUBSTITUTE(SUBSTITUTE(B32&"-"&E32," ",""),":","-")) | BE32: =IF(E32="","",IF(ISNUMBER(SEARCH("ECC",E32)),"NCA-ECC-2-2024",IF(ISNUMBER(SEARCH("OTCC",E32)),"NCA-ECC-2-2024",IF(ISNUMBER(SEARCH("CCC",E32)),"NCA-ECC-2-2024",IF(ISNUMBER(SEARCH("DCC",E32)),"NCA-ECC-2-2024",IF(ISNUMBER(SEARCH("CSCC",E32)),"NCA-ECC-2-2024",IF(ISNUMBER(SEARCH("PDPL-IR",E32)),"PDPL-2021",IF(ISNUMBER(SEARCH("PDPL-DTR",E32)),"PDPL-2021","NONE")))))))) | BF32: =IF(E32="","",IF(BB32="DEEP",10,IF(BB32="SHALLOW",5,IF(BB32="TEMPLATE",3,1)))+IF(N32="HIGHEST",5,IF(N32="HIGH",3,IF(N32="MODERATE",1,0)))+IF(ISNUMBER(SEARCH("Mandatory",L32)),3,0))
A33: 28 | B33: MOH | C33: Ministry of Health | D33: 2. Healthcare & Life Sciences | E33: MOH-EMR-NABIDH | F33: EMR Standards / NABIDH Platform | G33: معايير السجل الصحي الإلكتروني / منصة نبض | H33: Mandatory 2024 | I33: 2010 | J33: 52 | K33: ISSUES/ENFORCES | L33: Mandatory Enforcer | M33: All healthcare facilities — mandatory NABIDH 2024 | N33: HIGHEST | O33: https://www.moh.gov.sa/en/ | P33: MOH; Hammad & Al-Mehdar 2025 | Q33: NABIDH platform launched ~2018 → mandatory EMR adoption for all facilities 2024 | R33: NABIDH (National Unified EHR Platform): v1 2018 (pilot MOH hospitals); 2019-2021 (rollout to health clusters); 2022 (private hospital voluntary integration); 2023 (API standards published based on FHIR R4); 2024 (mandatory for ALL healthcare facilities per Private Health Institutions Law update — complete patient longitudinal record across facilities). EMR standard covers 52 functional requirements including: CPOE, medication reconciliation, imaging integration, patient portal, audit logs | S33: NABIDH launched: 2018. Mandatory for all: 2024 | T33: Continuously updated with NABIDH platform releases | U33: CURRENT — mandatory since 2024 | V33: Facility licensing revocation; MOH enforcement action; barred from government referrals; penalties under PHILAW 2024 | W33: MOH — NABIDH Programme Office; NHIC; regional health clusters monitor connectivity | X33: Hospital; Clinic; Lab; Pharmacy; Government Health Entity — ALL healthcare facilities mandatory | Y33: Both (mandatory since 2024 PHILAW update for all facilities) | Z33: NHIC connectivity assessment; NABIDH API conformance testing; MOH annual audit | AA33: Continuous (NABIDH connectivity monitored in real time); annual formal audit | AB33: 22 (IoMT data integration to NABIDH: wearable data ingestion API; remote monitoring feeds; device-generated vital signs; medical device alerts to patient record; IoMT consent management in EHR) | AC33: HL7 FHIR R4; IHE (Integrating the Healthcare Enterprise); SNOMED CT; ICD-10; LOINC | AD33: Arabic + English (NABIDH technical specifications bilingual) | AE33: Layer 1: Governance; Layer 3: Technical Controls; Layer 4: Compliance; Layer 5: Assurance | AF33: Yes — NABIDH connectivity levels (1: Basic data exchange; 2: Full longitudinal record; 3: Advanced interoperability with IoMT); MOH tracks facility level | AG33: HSTP digital health transformation; NABIDH national EHR; NHIS claims integration | AH33: NABIDH connectivity certificate; API integration test reports; patient consent records for data sharing; EHR system validation; data quality reports | AI33: Health information exchange theory (Walker et al. 2005): interoperability as prerequisite for care coordination. FHIR interoperability standards: MOH EMR-NABIDH mandate represents state-driven interoperability (top-down) vs market-driven (bottom-up US approach). Data portability theory: patient access to health records across providers. | AJ33: FOR: MOH mandating NABIDH integration for all EMR systems ensures national interoperability — avoids US fragmentation problem; HL7 FHIR adoption positions KSA as regional interoperability leader; enables population health analytics for epidemic preparedness. AGAINST: Mandatory EMR-NABIDH integration imposes significant cost on small clinics; NABIDH data quality depends on source system quality — 'garbage in, garbage out' risk; privacy advocates argue national health record creates surveillance potential. | AK33: Criticisms: (1) Cost burden of NABIDH integration disproportionately affects small/medium healthcare providers; (2) NABIDH integration standards not fully aligned with NHIC NABIDH standards — creates confusion; (3) Patient consent model for NABIDH data sharing unclear under PDPL framework; (4) Integration timeline repeatedly extended — original 2022 deadline not met. | AL33: Framework comparison requires contextual analysis. Key comparators: NIST CSF 2.0 (international benchmark), ISO 27001 (certifiable standard), ECC-2 (KSA mandatory baseline). See main database for cross-framework mapping. | AM33: Walker et al. (2005) Health Information Exchange; HL7 FHIR (2024) Interoperability Standards; Al-Mufti (2023) EMR Implementation in KSA; NHIC NABIDH Technical Specifications (2024). | AN33: Official: Consult the official source URL in the database for the primary document. Training: ISACA, ISC2, RAPS, IAPP, and HIMSS offer professional development covering most regulatory domains. Estimated hours vary by framework complexity. | AO33: Relevance to GH-ICGA framework varies by layer — see GH-ICGA Layer Mapping column. All KSA mandatory frameworks are compliance inputs to GH-ICGA Layer 4. Frameworks with IoMT-specific provisions directly inform Layers 2 and 3. | AP33: G + C (Governance + Compliance — standard regulatory framework positioning) | AQ33: Senior management: accountability for framework compliance. Designated compliance officer: monitor requirements. All staff: awareness of applicable obligations | AR33: Regulatory Risk; Operational Risk; Reputational Risk — specific domains determined by framework scope | AS33: See official source — legal obligation, regulatory requirement, or voluntary standard as applicable | AT33: Administrative; Technical; Operational — specific distribution determined by framework content | AU33: 1. Compliance status (compliant/non-compliant). 2. # open findings from last assessment. 3. % controls implemented. 4. Time to remediate findings. 5. Incident rate in framework scope area | AV33: Self-assessment; internal audit; external assessment as specified by issuing authority | AW33: ServiceNow GRC; IBM OpenPages; RSA Archer; MetricStream — all major GRC platforms support custom framework import. Contact vendor for framework-specific module | AX33: Third parties in scope must demonstrate equivalent compliance. Contractual compliance obligations; right-to-audit clauses; annual third-party assessment | AY33: Non-compliance: regulatory action by issuing authority; fines and penalties as specified; operational and reputational consequences | AZ33: Healthcare & Life Sciences | BA33: Sector-Specific | BB33: =IF(E33="","",IF(ISNUMBER(SEARCH("Institutional theory and regulatory governance theory underpin",AI33)),"TEMPLATE",IF(LEN(AI33)>100,"DEEP",IF(AI33="","SPARSE","SHALLOW")))) | BC33: =IF(E33="","",D33&"-"&B33&"-"&E33) | BD33: =IF(E33="","",SUBSTITUTE(SUBSTITUTE(B33&"-"&E33," ",""),":","-")) | BE33: =IF(E33="","",IF(ISNUMBER(SEARCH("ECC",E33)),"NCA-ECC-2-2024",IF(ISNUMBER(SEARCH("OTCC",E33)),"NCA-ECC-2-2024",IF(ISNUMBER(SEARCH("CCC",E33)),"NCA-ECC-2-2024",IF(ISNUMBER(SEARCH("DCC",E33)),"NCA-ECC-2-2024",IF(ISNUMBER(SEARCH("CSCC",E33)),"NCA-ECC-2-2024",IF(ISNUMBER(SEARCH("PDPL-IR",E33)),"PDPL-2021",IF(ISNUMBER(SEARCH("PDPL-DTR",E33)),"PDPL-2021","NONE")))))))) | BF33: =IF(E33="","",IF(BB33="DEEP",10,IF(BB33="SHALLOW",5,IF(BB33="TEMPLATE",3,1)))+IF(N33="HIGHEST",5,IF(N33="HIGH",3,IF(N33="MODERATE",1,0)))+IF(ISNUMBER(SEARCH("Mandatory",L33)),3,0))
A34: 29 | B34: MOH | C34: Ministry of Health | D34: 2. Healthcare & Life Sciences | E34: MOH-PS | F34: Patient Safety Standards | G34: معايير سلامة المريض | H34: 2024 update | I34: 2015 | J34: 72 | K34: ISSUES/ENFORCES | L34: Mandatory Enforcer | M34: All healthcare facilities | N34: HIGHEST | O34: https://www.moh.gov.sa/en/ | P34: MOH official | Q34: First issued ~2015 → updates 2020 → 2024 update | R34: Based on WHO and JCI patient safety frameworks. Covers: patient identification (minimum 2 identifiers), medication safety (high-alert medications protocol), surgical safety checklist, falls prevention, infection control, critical value reporting, handover communications (SBAR). 2020 update added COVID-19 IPC protocols. 2024 update adds IoMT device safety (alarm fatigue management, device connectivity requirements) | S34: First: ~2015. Updated: 2020, 2024 | T34: Annual review with MOH patient safety incidents data | U34: CURRENT — 2024 version | V34: MOH corrective action order; facility licence conditions; public safety alert; criminal liability for gross negligence | W34: MOH — Patient Safety Centre; regional health cluster inspection; CBAHI (patient safety standards embedded in accreditation) | X34: Hospital; Clinic; Government Health Entity | Y34: Both | Z34: Annual MOH patient safety inspection; CBAHI survey (integrated); incident investigation | AA34: Annual; triggered by serious adverse event | AB34: 14 (alarm fatigue management for IoMT devices; connected infusion pump safety; IV smart pump drug library governance; patient ID for IoMT devices; device failure response procedures; remote monitoring alert management) | AC34: WHO Patient Safety Challenges (Global Patient Safety Action Plan 2021-2030); JCI Patient Safety Goals; The Joint Commission NPSG | AD34: Arabic (primary); English reference | AE34: Layer 1: Governance; Layer 4: Compliance | AF34: Yes — patient safety maturity levels (Safety-I to Safety-III); MOH tracks facility scores | AG34: HSTP patient safety; Vision 2030 quality targets; National Patient Safety Centre | AH34: Incident reporting system data; patient safety walkround records; fall prevention audit; medication safety audit; CBAHI patient safety standards compliance | AI34: Patient safety theory (Reason 2000): Swiss cheese model — multiple layers of defence against medical error. Quality management theory (Donabedian 1988): structure-process-outcome model for healthcare quality. Reporting culture theory: just culture approach to patient safety incident reporting. | AJ34: FOR: MOH Patient Safety Standards (2023 update) align with WHO Patient Safety Framework; mandatory incident reporting creates learning culture; explicit medical device safety provisions link to SFDA MDR vigilance requirements. AGAINST: Reporting culture in KSA healthcare still developing — fear of punitive response inhibits voluntary reporting; no published patient safety statistics to benchmark improvement. | AK34: Criticisms: (1) Patient safety incident reporting rates in KSA hospitals remain below international benchmarks; (2) No published national patient safety database — CBAHI collects data but limited public transparency; (3) IoMT device safety incidents not clearly mapped to either MOH-PS or SFDA MDR reporting — gap in GH-ICGA coverage; (4) Just culture principles not yet embedded in KSA labour law — staff fear termination for honest error reporting. | AL34: Framework comparison requires contextual analysis. Key comparators: NIST CSF 2.0 (international benchmark), ISO 27001 (certifiable standard), ECC-2 (KSA mandatory baseline). See main database for cross-framework mapping. | AM34: Reason (2000) Human Error; Donabedian (1988) Quality of Care Assessment; WHO Patient Safety Framework (2021); Al-Shehri et al. (2023) Patient Safety in Saudi Hospitals; CBAHI Annual Report (2024). | AN34: Official: Consult the official source URL in the database for the primary document. Training: ISACA, ISC2, RAPS, IAPP, and HIMSS offer professional development covering most regulatory domains. Estimated hours vary by framework complexity. | AO34: GH-ICGA positions MOH-PS as the PATIENT SAFETY layer — directly intersects with IoMT governance because medical device failures are patient safety events. Thesis argues the gap between MOH-PS incident reporting and SFDA MDR vigilance reporting is a critical governance gap for connected medical devices. | AP34: G + C (Governance + Compliance — standard regulatory framework positioning) | AQ34: Senior management: accountability for framework compliance. Designated compliance officer: monitor requirements. All staff: awareness of applicable obligations | AR34: Regulatory Risk; Operational Risk; Reputational Risk — specific domains determined by framework scope | AS34: See official source — legal obligation, regulatory requirement, or voluntary standard as applicable | AT34: Administrative; Technical; Operational — specific distribution determined by framework content | AU34: 1. Compliance status (compliant/non-compliant). 2. # open findings from last assessment. 3. % controls implemented. 4. Time to remediate findings. 5. Incident rate in framework scope area | AV34: Self-assessment; internal audit; external assessment as specified by issuing authority | AW34: ServiceNow GRC; IBM OpenPages; RSA Archer; MetricStream — all major GRC platforms support custom framework import. Contact vendor for framework-specific module | AX34: Third parties in scope must demonstrate equivalent compliance. Contractual compliance obligations; right-to-audit clauses; annual third-party assessment | AY34: Non-compliance: regulatory action by issuing authority; fines and penalties as specified; operational and reputational consequences | AZ34: Healthcare & Life Sciences | BA34: Sector-Specific | BB34: =IF(E34="","",IF(ISNUMBER(SEARCH("Institutional theory and regulatory governance theory underpin",AI34)),"TEMPLATE",IF(LEN(AI34)>100,"DEEP",IF(AI34="","SPARSE","SHALLOW")))) | BC34: =IF(E34="","",D34&"-"&B34&"-"&E34) | BD34: =IF(E34="","",SUBSTITUTE(SUBSTITUTE(B34&"-"&E34," ",""),":","-")) | BE34: =IF(E34="","",IF(ISNUMBER(SEARCH("ECC",E34)),"NCA-ECC-2-2024",IF(ISNUMBER(SEARCH("OTCC",E34)),"NCA-ECC-2-2024",IF(ISNUMBER(SEARCH("CCC",E34)),"NCA-ECC-2-2024",IF(ISNUMBER(SEARCH("DCC",E34)),"NCA-ECC-2-2024",IF(ISNUMBER(SEARCH("CSCC",E34)),"NCA-ECC-2-2024",IF(ISNUMBER(SEARCH("PDPL-IR",E34)),"PDPL-2021",IF(ISNUMBER(SEARCH("PDPL-DTR",E34)),"PDPL-2021","NONE")))))))) | BF34: =IF(E34="","",IF(BB34="DEEP",10,IF(BB34="SHALLOW",5,IF(BB34="TEMPLATE",3,1)))+IF(N34="HIGHEST",5,IF(N34="HIGH",3,IF(N34="MODERATE",1,0)))+IF(ISNUMBER(SEARCH("Mandatory",L34)),3,0))
